Workbook

Sheet AP01
A1: APÊNDICE 01: EVOLUÇÃO DO FINANCIAMENTO COBRADO PELO BANCO
A3: Requerente: ADRIANA MELO DE OLIVEIRA
A4: Requerido: ITAÚ UNIBANCO
A5: Valor do Bem | D5: 432000 | F5: Qtde Prestações | I5: 360 | X5: =S7 -> 31402
A6: Entrada/Descontos | D6: 129600 | F6: Taxa de Juros Efetiva (a.m.) | I6: =((1+I7)^(1/12))-1 -> 0.0092631835 | W6: 1 | X6: =EDATE(X5,12) -> 31767
A7: Valor Financiado | D7: =D5-D6 -> 302400 | F7: Taxa de Juros Efetiva (a.a.) | I7: 0.117 | R7: Data Nasc | S7: 31402 | W7: =W6+1 -> 2 | X7: =EDATE(X6,12) -> 32132
A8: Data do Contrato | D8: 43241 | F8: Taxa de Juros com benfício (a.m.) | I8: =((1+I9)^(1/12))-1 -> 0.0056541454 | W8: =W7+1 -> 3 | X8: =EDATE(X7,12) -> 32498
A9: 1° Vencimento | D9: 43272 | F9: Taxa de Juros com benfício (a.a.) | I9: 0.07 | W9: =W8+1 -> 4 | X9: =EDATE(X8,12) -> 32863
A10: Sistema de Amortização | D10: SAC | F10: Prestação Mensal | I10: =(D7/I5)+(D7*I8) -> 2549.8136 | W10: =W9+1 -> 5 | X10: =EDATE(X9,12) -> 33228
A11: Índice Correção | D11: TR | F11: Enquadramento | I11: SFH | W11: =W10+1 -> 6 | X11: =EDATE(X10,12) -> 33593
W12: =W11+1 -> 7 | X12: =EDATE(X11,12) -> 33959
A13: Qtde | B13: Data Vencimento | C13: Taxa Efetiva a.a. | D13: Taxa Efetiva a.m. | E13: Prestação (a+j) | F13: Juros | G13: Amortização | H13: Seguro MIP | I13: Seguro DFI | J13: TCA | K13: Multa | L13: Mora | M13: Total da Parcela | N13: Correção Monetária | O13: Saldo Devedor | P13: Índice Correção | Q13: Valor Garantia | R13: Idade | S13: % MIP | T13: Seguro DFI2 | U13: Seguro MIP2 | W13: =W12+1 -> 8 | X13: =EDATE(X12,12) -> 34324
A14: 0 | B14: =D8 -> 43241 | O14: =D7 -> 302400 | Q14: 432000 | R14: =DATEDIF($S$7,'AP01'!$B14,"Y") -> 32 | S14: =VLOOKUP('AP01'!$R14,SEGUROS!$A:$B,2,TRUE) -> 0.0001381 | T14: ='AP01'!$O14*'AP01'!$S14 -> 41.76144 | U14: ='AP01'!$Q14*0.00899% -> 38.8368 | W14: =W13+1 -> 9 | X14: =EDATE(X13,12) -> 34689
A15: =A14+1 -> 1 | B15: =D9 -> 43272 | C15: =I9 -> 0.07 | D15: 0.005654 | E15: ='AP01'!$F15+'AP01'!$G15 -> 2549.76 | F15: 1709.76 | G15: =(O14*'AP01'!$P15)/($I$5-A14) -> 840 | H15: 62.54 | I15: 77.66 | J15: 25 | K15: 0 | L15: 0 | M15: =SUM('AP01'!$F15:$L15) -> 2714.96 | N15: =O14*('AP01'!$P15-1) -> 0 | O15: =(O14*'AP01'!$P15)-'AP01'!$G15 -> 301560 | P15: 1 | Q15: =(Q14*'AP01'!$P15) -> 432000 | R15: =DATEDIF($S$7,'AP01'!$B15,"Y") -> 32 | S15: =VLOOKUP('AP01'!$R15,SEGUROS!$A:$B,2,TRUE) -> 0.0001381 | T15: =('AP01'!$O15*'AP01'!$P15)*'AP01'!$S15 -> 41.645436 | U15: ='AP01'!$Q15*0.00899% -> 38.8368 | W15: =W14+1 -> 10 | X15: =EDATE(X14,12) -> 35054 | Z15: =H16/O16 -> 0.00010371774
A16: =A15+1 -> 2 | B16: =EDATE(B15,1) -> 43302 | C16: =C15 -> 0.07 | D16: =D15 -> 0.005654 | E16: ='AP01'!$F16+'AP01'!$G16 -> 2545.02 | F16: 1705.02 | G16: =(O15*'AP01'!$P16)/($I$5-A15) -> 840 | H16: 31.19 | I16: 38.83 | J16: =J15 -> 25 | K16: =K15 -> 0 | L16: =L15 -> 0 | M16: =SUM('AP01'!$F16:$L16) -> 2640.04 | N16: =O15*('AP01'!$P16-1) -> 0 | O16: =(O15*'AP01'!$P16)-'AP01'!$G16 -> 300720 | P16: =P15 -> 1 | Q16: =(Q15*'AP01'!$P16) -> 432000 | R16: =DATEDIF($S$7,'AP01'!$B16,"Y") -> 32 | S16: =VLOOKUP('AP01'!$R16,SEGUROS!$A:$B,2,TRUE) -> 0.0001381 | T16: =('AP01'!$O16*'AP01'!$P16)*'AP01'!$S16 -> 41.529432 | U16: ='AP01'!$Q16*0.00899% -> 38.8368 | W16: =W15+1 -> 11 | X16: =EDATE(X15,12) -> 35420 | Z16: =H17/O17 -> 0.00010370815
A17: =A16+1 -> 3 | B17: =EDATE(B16,1) -> 43333 | C17: =C16 -> 0.07 | D17: =D16 -> 0.005654 | E17: ='AP01'!$F17+'AP01'!$G17 -> 2540.27 | F17: 1700.27 | G17: =(O16*'AP01'!$P17)/($I$5-A16) -> 840 | H17: 31.1 | I17: 38.83 | J17: =J16 -> 25 | K17: =K16 -> 0 | L17: =L16 -> 0 | M17: =SUM('AP01'!$F17:$L17) -> 2635.2 | N17: =O16*('AP01'!$P17-1) -> 0 | O17: =(O16*'AP01'!$P17)-'AP01'!$G17 -> 299880 | P17: =P16 -> 1 | Q17: =(Q16*'AP01'!$P17) -> 432000 | R17: =DATEDIF($S$7,'AP01'!$B17,"Y") -> 32 | S17: =VLOOKUP('AP01'!$R17,SEGUROS!$A:$B,2,TRUE) -> 0.0001381 | T17: =('AP01'!$O17*'AP01'!$P17)*'AP01'!$S17 -> 41.413428 | U17: ='AP01'!$Q17*0.00899% -> 38.8368 | W17: =W16+1 -> 12 | X17: =EDATE(X16,12) -> 35785 | Z17: =H18/O18 -> 0.0001036985
A18: =A17+1 -> 4 | B18: =EDATE(B17,1) -> 43364 | C18: =C17 -> 0.07 | D18: =D17 -> 0.005654 | E18: ='AP01'!$F18+'AP01'!$G18 -> 2535.52 | F18: 1695.52 | G18: =(O17*'AP01'!$P18)/($I$5-A17) -> 840 | H18: 31.01 | I18: 38.83 | J18: =J17 -> 25 | K18: =K17 -> 0 | L18: =L17 -> 0 | M18: =SUM('AP01'!$F18:$L18) -> 2630.36 | N18: =O17*('AP01'!$P18-1) -> 0 | O18: =(O17*'AP01'!$P18)-'AP01'!$G18 -> 299040 | P18: =P17 -> 1 | Q18: =(Q17*'AP01'!$P18) -> 432000 | R18: =DATEDIF($S$7,'AP01'!$B18,"Y") -> 32 | S18: =VLOOKUP('AP01'!$R18,SEGUROS!$A:$B,2,TRUE) -> 0.0001381 | T18: =('AP01'!$O18*'AP01'!$P18)*'AP01'!$S18 -> 41.297424 | U18: ='AP01'!$Q18*0.00899% -> 38.8368 | W18: =W17+1 -> 13 | X18: =EDATE(X17,12) -> 36150 | Z18: =H19/O19 -> 0.0001036888
A19: =A18+1 -> 5 | B19: =EDATE(B18,1) -> 43394 | C19: =C18 -> 0.07 | D19: =D18 -> 0.005654 | E19: ='AP01'!$F19+'AP01'!$G19 -> 2530.77 | F19: 1690.77 | G19: =(O18*'AP01'!$P19)/($I$5-A18) -> 840 | H19: 30.92 | I19: 38.83 | J19: =J18 -> 25 | K19: =K18 -> 0 | L19: =L18 -> 0 | M19: =SUM('AP01'!$F19:$L19) -> 2625.52 | N19: =O18*('AP01'!$P19-1) -> 0 | O19: =(O18*'AP01'!$P19)-'AP01'!$G19 -> 298200 | P19: =P18 -> 1 | Q19: =(Q18*'AP01'!$P19) -> 432000 | R19: =DATEDIF($S$7,'AP01'!$B19,"Y") -> 32 | S19: =VLOOKUP('AP01'!$R19,SEGUROS!$A:$B,2,TRUE) -> 0.0001381 | T19: =('AP01'!$O19*'AP01'!$P19)*'AP01'!$S19 -> 41.18142 | U19: ='AP01'!$Q19*0.00899% -> 38.8368 | W19: =W18+1 -> 14 | X19: =EDATE(X18,12) -> 36515 | Z19: =H20/O20 -> 0.00010371267
A20: =A19+1 -> 6 | B20: =EDATE(B19,1) -> 43425 | C20: =C19 -> 0.07 | D20: =D19 -> 0.005654 | E20: ='AP01'!$F20+'AP01'!$G20 -> 2526.02 | F20: 1686.02 | G20: =(O19*'AP01'!$P20)/($I$5-A19) -> 840 | H20: 30.84 | I20: 38.83 | J20: =J19 -> 25 | K20: =K19 -> 0 | L20: =L19 -> 0 | M20: =SUM('AP01'!$F20:$L20) -> 2620.69 | N20: =O19*('AP01'!$P20-1) -> 0 | O20: =(O19*'AP01'!$P20)-'AP01'!$G20 -> 297360 | P20: =P19 -> 1 | Q20: =(Q19*'AP01'!$P20) -> 432000 | R20: =DATEDIF($S$7,'AP01'!$B20,"Y") -> 32 | S20: =VLOOKUP('AP01'!$R20,SEGUROS!$A:$B,2,TRUE) -> 0.0001381 | T20: =('AP01'!$O20*'AP01'!$P20)*'AP01'!$S20 -> 41.065416 | U20: ='AP01'!$Q20*0.00899% -> 38.8368 | W20: =W19+1 -> 15 | X20: =EDATE(X19,12) -> 36881 | Z20: =H21/O21 -> 0.00010559153
A21: =A20+1 -> 7 | B21: =EDATE(B20,1) -> 43455 | C21: =C20 -> 0.07 | D21: =D20 -> 0.005654 | E21: ='AP01'!$F21+'AP01'!$G21 -> 2521.27 | F21: 1681.27 | G21: =(O20*'AP01'!$P21)/($I$5-A20) -> 840 | H21: 31.31 | I21: 38.83 | J21: =J20 -> 25 | K21: =K20 -> 0 | L21: =L20 -> 0 | M21: =SUM('AP01'!$F21:$L21) -> 2616.41 | N21: =O20*('AP01'!$P21-1) -> 0 | O21: =(O20*'AP01'!$P21)-'AP01'!$G21 -> 296520 | P21: =P20 -> 1 | Q21: =(Q20*'AP01'!$P21) -> 432000 | R21: =DATEDIF($S$7,'AP01'!$B21,"Y") -> 33 | S21: =VLOOKUP('AP01'!$R21,SEGUROS!$A:$B,2,TRUE) -> 0.0001423 | T21: =('AP01'!$O21*'AP01'!$P21)*'AP01'!$S21 -> 42.194796 | U21: ='AP01'!$Q21*0.00899% -> 38.8368 | W21: =W20+1 -> 16 | X21: =EDATE(X20,12) -> 37246 | Z21: =H22/O22 -> 0.00010558712
A22: =A21+1 -> 8 | B22: =EDATE(B21,1) -> 43486 | C22: =C21 -> 0.07 | D22: =D21 -> 0.005654 | E22: ='AP01'!$F22+'AP01'!$G22 -> 2516.52 | F22: 1676.52 | G22: =(O21*'AP01'!$P22)/($I$5-A21) -> 840 | H22: 31.22 | I22: 38.83 | J22: =J21 -> 25 | K22: =K21 -> 0 | L22: =L21 -> 0 | M22: =SUM('AP01'!$F22:$L22) -> 2611.57 | N22: =O21*('AP01'!$P22-1) -> 0 | O22: =(O21*'AP01'!$P22)-'AP01'!$G22 -> 295680 | P22: =P21 -> 1 | Q22: =(Q21*'AP01'!$P22) -> 432000 | R22: =DATEDIF($S$7,'AP01'!$B22,"Y") -> 33 | S22: =VLOOKUP('AP01'!$R22,SEGUROS!$A:$B,2,TRUE) -> 0.0001423 | T22: =('AP01'!$O22*'AP01'!$P22)*'AP01'!$S22 -> 42.075264 | U22: ='AP01'!$Q22*0.00899% -> 38.8368 | W22: =W21+1 -> 17 | X22: =EDATE(X21,12) -> 37611 | Z22: =H23/O23 -> 0.00010558269
A23: =A22+1 -> 9 | B23: =EDATE(B22,1) -> 43517 | C23: =C22 -> 0.07 | D23: =D22 -> 0.005654 | E23: ='AP01'!$F23+'AP01'!$G23 -> 2511.77 | F23: 1671.77 | G23: =(O22*'AP01'!$P23)/($I$5-A22) -> 840 | H23: 31.13 | I23: 38.83 | J23: =J22 -> 25 | K23: =K22 -> 0 | L23: =L22 -> 0 | M23: =SUM('AP01'!$F23:$L23) -> 2606.73 | N23: =O22*('AP01'!$P23-1) -> 0 | O23: =(O22*'AP01'!$P23)-'AP01'!$G23 -> 294840 | P23: =P22 -> 1 | Q23: =(Q22*'AP01'!$P23) -> 432000 | R23: =DATEDIF($S$7,'AP01'!$B23,"Y") -> 33 | S23: =VLOOKUP('AP01'!$R23,SEGUROS!$A:$B,2,TRUE) -> 0.0001423 | T23: =('AP01'!$O23*'AP01'!$P23)*'AP01'!$S23 -> 41.955732 | U23: ='AP01'!$Q23*0.00899% -> 38.8368 | W23: =W22+1 -> 18 | X23: =EDATE(X22,12) -> 37976 | Z23: =H24/O24 -> 0.00010557823
A24: =A23+1 -> 10 | B24: =EDATE(B23,1) -> 43545 | C24: =C23 -> 0.07 | D24: =D23 -> 0.005654 | E24: ='AP01'!$F24+'AP01'!$G24 -> 2507.02 | F24: 1667.02 | G24: =(O23*'AP01'!$P24)/($I$5-A23) -> 840 | H24: 31.04 | I24: 38.83 | J24: =J23 -> 25 | K24: =K23 -> 0 | L24: =L23 -> 0 | M24: =SUM('AP01'!$F24:$L24) -> 2601.89 | N24: =O23*('AP01'!$P24-1) -> 0 | O24: =(O23*'AP01'!$P24)-'AP01'!$G24 -> 294000 | P24: =P23 -> 1 | Q24: =(Q23*'AP01'!$P24) -> 432000 | R24: =DATEDIF($S$7,'AP01'!$B24,"Y") -> 33 | S24: =VLOOKUP('AP01'!$R24,SEGUROS!$A:$B,2,TRUE) -> 0.0001423 | T24: =('AP01'!$O24*'AP01'!$P24)*'AP01'!$S24 -> 41.8362 | U24: ='AP01'!$Q24*0.00899% -> 38.8368 | W24: =W23+1 -> 19 | X24: =EDATE(X23,12) -> 38342 | Z24: =H25/O25 -> 0.00010557375
A25: =A24+1 -> 11 | B25: =EDATE(B24,1) -> 43576 | C25: =C24 -> 0.07 | D25: =D24 -> 0.005654 | E25: ='AP01'!$F25+'AP01'!$G25 -> 2502.27 | F25: 1662.27 | G25: =(O24*'AP01'!$P25)/($I$5-A24) -> 840 | H25: 30.95 | I25: 38.83 | J25: =J24 -> 25 | K25: =K24 -> 0 | L25: =L24 -> 0 | M25: =SUM('AP01'!$F25:$L25) -> 2597.05 | N25: =O24*('AP01'!$P25-1) -> 0 | O25: =(O24*'AP01'!$P25)-'AP01'!$G25 -> 293160 | P25: =P24 -> 1 | Q25: =(Q24*'AP01'!$P25) -> 432000 | R25: =DATEDIF($S$7,'AP01'!$B25,"Y") -> 33 | S25: =VLOOKUP('AP01'!$R25,SEGUROS!$A:$B,2,TRUE) -> 0.0001423 | T25: =('AP01'!$O25*'AP01'!$P25)*'AP01'!$S25 -> 41.716668 | U25: ='AP01'!$Q25*0.00899% -> 38.8368 | W25: =W24+1 -> 20 | X25: =EDATE(X24,12) -> 38707 | Z25: =H26/O26 -> 0.00010556924
A26: =A25+1 -> 12 | B26: =EDATE(B25,1) -> 43606 | C26: =C25 -> 0.07 | D26: =D25 -> 0.005654 | E26: ='AP01'!$F26+'AP01'!$G26 -> 2497.52 | F26: 1657.52 | G26: =(O25*'AP01'!$P26)/($I$5-A25) -> 840 | H26: 30.86 | I26: 38.83 | J26: =J25 -> 25 | K26: =K25 -> 0 | L26: =L25 -> 0 | M26: =SUM('AP01'!$F26:$L26) -> 2592.21 | N26: =O25*('AP01'!$P26-1) -> 0 | O26: =(O25*'AP01'!$P26)-'AP01'!$G26 -> 292320 | P26: =P25 -> 1 | Q26: =(Q25*'AP01'!$P26) -> 432000 | R26: =DATEDIF($S$7,'AP01'!$B26,"Y") -> 33 | S26: =VLOOKUP('AP01'!$R26,SEGUROS!$A:$B,2,TRUE) -> 0.0001423 | T26: =('AP01'!$O26*'AP01'!$P26)*'AP01'!$S26 -> 41.597136 | U26: ='AP01'!$Q26*0.00899% -> 38.8368 | W26: =W25+1 -> 21 | X26: =EDATE(X25,12) -> 39072 | Z26: =H27/O27 -> 0.00010559901
A27: =A26+1 -> 13 | B27: =EDATE(B26,1) -> 43637 | C27: =C26 -> 0.07 | D27: =D26 -> 0.005654 | E27: ='AP01'!$F27+'AP01'!$G27 -> 2492.77 | F27: 1652.77 | G27: =(O26*'AP01'!$P27)/($I$5-A26) -> 840 | H27: 30.78 | I27: 38.83 | J27: =J26 -> 25 | K27: =K26 -> 0 | L27: =L26 -> 0 | M27: =SUM('AP01'!$F27:$L27) -> 2587.38 | N27: =O26*('AP01'!$P27-1) -> 0 | O27: =(O26*'AP01'!$P27)-'AP01'!$G27 -> 291480 | P27: =P26 -> 1 | Q27: =(Q26*'AP01'!$P27) -> 432000 | R27: =DATEDIF($S$7,'AP01'!$B27,"Y") -> 33 | S27: =VLOOKUP('AP01'!$R27,SEGUROS!$A:$B,2,TRUE) -> 0.0001423 | T27: =('AP01'!$O27*'AP01'!$P27)*'AP01'!$S27 -> 41.477604 | U27: ='AP01'!$Q27*0.00899% -> 38.8368 | W27: =W26+1 -> 22 | X27: =EDATE(X26,12) -> 39437 | Z27: =H28/O28 -> 0.00010559455
A28: =A27+1 -> 14 | B28: =EDATE(B27,1) -> 43667 | C28: =C27 -> 0.07 | D28: =D27 -> 0.005654 | E28: ='AP01'!$F28+'AP01'!$G28 -> 2488.02 | F28: 1648.02 | G28: =(O27*'AP01'!$P28)/($I$5-A27) -> 840 | H28: 30.69 | I28: 38.83 | J28: =J27 -> 25 | K28: =K27 -> 0 | L28: =L27 -> 0 | M28: =SUM('AP01'!$F28:$L28) -> 2582.54 | N28: =O27*('AP01'!$P28-1) -> 0 | O28: =(O27*'AP01'!$P28)-'AP01'!$G28 -> 290640 | P28: =P27 -> 1 | Q28: =(Q27*'AP01'!$P28) -> 432000 | R28: =DATEDIF($S$7,'AP01'!$B28,"Y") -> 33 | S28: =VLOOKUP('AP01'!$R28,SEGUROS!$A:$B,2,TRUE) -> 0.0001423 | T28: =('AP01'!$O28*'AP01'!$P28)*'AP01'!$S28 -> 41.358072 | U28: ='AP01'!$Q28*0.00899% -> 38.8368 | W28: =W27+1 -> 23 | X28: =EDATE(X27,12) -> 39803
A29: =A28+1 -> 15 | B29: =EDATE(B28,1) -> 43698 | C29: =C28 -> 0.07 | D29: =D28 -> 0.005654 | E29: ='AP01'!$F29+'AP01'!$G29 -> 2483.27 | F29: 1643.27 | G29: =(O28*'AP01'!$P29)/($I$5-A28) -> 840 | H29: 30.6 | I29: 38.83 | J29: =J28 -> 25 | K29: =K28 -> 0 | L29: =L28 -> 0 | M29: =SUM('AP01'!$F29:$L29) -> 2577.7 | N29: =O28*('AP01'!$P29-1) -> 0 | O29: =(O28*'AP01'!$P29)-'AP01'!$G29 -> 289800 | P29: =P28 -> 1 | Q29: =(Q28*'AP01'!$P29) -> 432000 | R29: =DATEDIF($S$7,'AP01'!$B29,"Y") -> 33 | S29: =VLOOKUP('AP01'!$R29,SEGUROS!$A:$B,2,TRUE) -> 0.0001423 | T29: =('AP01'!$O29*'AP01'!$P29)*'AP01'!$S29 -> 41.23854 | U29: ='AP01'!$Q29*0.00899% -> 38.8368 | W29: =W28+1 -> 24 | X29: =EDATE(X28,12) -> 40168
A30: =A29+1 -> 16 | B30: =EDATE(B29,1) -> 43729 | C30: =C29 -> 0.07 | D30: =D29 -> 0.005654 | E30: ='AP01'!$F30+'AP01'!$G30 -> 2478.52 | F30: 1638.52 | G30: =(O29*'AP01'!$P30)/($I$5-A29) -> 840 | H30: 30.51 | I30: 38.83 | J30: =J29 -> 25 | K30: =K29 -> 0 | L30: =L29 -> 0 | M30: =SUM('AP01'!$F30:$L30) -> 2572.86 | N30: =O29*('AP01'!$P30-1) -> 0 | O30: =(O29*'AP01'!$P30)-'AP01'!$G30 -> 288960 | P30: =P29 -> 1 | Q30: =(Q29*'AP01'!$P30) -> 432000 | R30: =DATEDIF($S$7,'AP01'!$B30,"Y") -> 33 | S30: =VLOOKUP('AP01'!$R30,SEGUROS!$A:$B,2,TRUE) -> 0.0001423 | T30: =('AP01'!$O30*'AP01'!$P30)*'AP01'!$S30 -> 41.119008 | U30: ='AP01'!$Q30*0.00899% -> 38.8368 | W30: =W29+1 -> 25 | X30: =EDATE(X29,12) -> 40533
A31: =A30+1 -> 17 | B31: =EDATE(B30,1) -> 43759 | C31: =C30 -> 0.07 | D31: =D30 -> 0.005654 | E31: ='AP01'!$F31+'AP01'!$G31 -> 2473.77 | F31: 1633.77 | G31: =(O30*'AP01'!$P31)/($I$5-A30) -> 840 | H31: 30.42 | I31: 38.83 | J31: =J30 -> 25 | K31: =K30 -> 0 | L31: =L30 -> 0 | M31: =SUM('AP01'!$F31:$L31) -> 2568.02 | N31: =O30*('AP01'!$P31-1) -> 0 | O31: =(O30*'AP01'!$P31)-'AP01'!$G31 -> 288120 | P31: =P30 -> 1 | Q31: =(Q30*'AP01'!$P31) -> 432000 | R31: =DATEDIF($S$7,'AP01'!$B31,"Y") -> 33 | S31: =VLOOKUP('AP01'!$R31,SEGUROS!$A:$B,2,TRUE) -> 0.0001423 | T31: =('AP01'!$O31*'AP01'!$P31)*'AP01'!$S31 -> 40.999476 | U31: ='AP01'!$Q31*0.00899% -> 38.8368 | W31: =W30+1 -> 26 | X31: =EDATE(X30,12) -> 40898
A32: =A31+1 -> 18 | B32: =EDATE(B31,1) -> 43790 | C32: =C31 -> 0.07 | D32: =D31 -> 0.005654 | E32: ='AP01'!$F32+'AP01'!$G32 -> 2469.03 | F32: 1629.03 | G32: =(O31*'AP01'!$P32)/($I$5-A31) -> 840 | H32: 30.33 | I32: 38.83 | J32: =J31 -> 25 | K32: =K31 -> 0 | L32: =L31 -> 0 | M32: =SUM('AP01'!$F32:$L32) -> 2563.19 | N32: =O31*('AP01'!$P32-1) -> 0 | O32: =(O31*'AP01'!$P32)-'AP01'!$G32 -> 287280 | P32: =P31 -> 1 | Q32: =(Q31*'AP01'!$P32) -> 432000 | R32: =DATEDIF($S$7,'AP01'!$B32,"Y") -> 33 | S32: =VLOOKUP('AP01'!$R32,SEGUROS!$A:$B,2,TRUE) -> 0.0001423 | T32: =('AP01'!$O32*'AP01'!$P32)*'AP01'!$S32 -> 40.879944 | U32: ='AP01'!$Q32*0.00899% -> 38.8368 | W32: =W31+1 -> 27 | X32: =EDATE(X31,12) -> 41264
A33: =A32+1 -> 19 | B33: =EDATE(B32,1) -> 43820 | C33: =C32 -> 0.07 | D33: =D32 -> 0.005654 | E33: ='AP01'!$F33+'AP01'!$G33 -> 2464.28 | F33: 1624.28 | G33: =(O32*'AP01'!$P33)/($I$5-A32) -> 840 | H33: 30.87 | I33: 38.83 | J33: =J32 -> 25 | K33: =K32 -> 0 | L33: =L32 -> 0 | M33: =SUM('AP01'!$F33:$L33) -> 2558.98 | N33: =O32*('AP01'!$P33-1) -> 0 | O33: =(O32*'AP01'!$P33)-'AP01'!$G33 -> 286440 | P33: =P32 -> 1 | Q33: =(Q32*'AP01'!$P33) -> 432000 | R33: =DATEDIF($S$7,'AP01'!$B33,"Y") -> 34 | S33: =VLOOKUP('AP01'!$R33,SEGUROS!$A:$B,2,TRUE) -> 0.0001472 | T33: =('AP01'!$O33*'AP01'!$P33)*'AP01'!$S33 -> 42.163968 | U33: ='AP01'!$Q33*0.00899% -> 38.8368 | W33: =W32+1 -> 28 | X33: =EDATE(X32,12) -> 41629
A34: =A33+1 -> 20 | B34: =EDATE(B33,1) -> 43851 | C34: =C33 -> 0.07 | D34: =D33 -> 0.005654 | E34: ='AP01'!$F34+'AP01'!$G34 -> 2459.53 | F34: 1619.53 | G34: =(O33*'AP01'!$P34)/($I$5-A33) -> 840 | H34: 30.78 | I34: 38.83 | J34: =J33 -> 25 | K34: =K33 -> 0 | L34: =L33 -> 0 | M34: =SUM('AP01'!$F34:$L34) -> 2554.14 | N34: =O33*('AP01'!$P34-1) -> 0 | O34: =(O33*'AP01'!$P34)-'AP01'!$G34 -> 285600 | P34: =P33 -> 1 | Q34: =(Q33*'AP01'!$P34) -> 432000 | R34: =DATEDIF($S$7,'AP01'!$B34,"Y") -> 34 | S34: =VLOOKUP('AP01'!$R34,SEGUROS!$A:$B,2,TRUE) -> 0.0001472 | T34: =('AP01'!$O34*'AP01'!$P34)*'AP01'!$S34 -> 42.04032 | U34: ='AP01'!$Q34*0.00899% -> 38.8368 | W34: =W33+1 -> 29 | X34: =EDATE(X33,12) -> 41994
A35: =A34+1 -> 21 | B35: =EDATE(B34,1) -> 43882 | C35: =C34 -> 0.07 | D35: =D34 -> 0.005654 | E35: ='AP01'!$F35+'AP01'!$G35 -> 2454.78 | F35: 1614.78 | G35: =(O34*'AP01'!$P35)/($I$5-A34) -> 840 | H35: 39.94 | I35: 38.83 | J35: =J34 -> 25 | K35: =K34 -> 0 | L35: =L34 -> 0 | M35: =SUM('AP01'!$F35:$L35) -> 2558.55 | N35: =O34*('AP01'!$P35-1) -> 0 | O35: =(O34*'AP01'!$P35)-'AP01'!$G35 -> 284760 | P35: =P34 -> 1 | Q35: =(Q34*'AP01'!$P35) -> 432000 | R35: =DATEDIF($S$7,'AP01'!$B35,"Y") -> 34 | S35: =VLOOKUP('AP01'!$R35,SEGUROS!$A:$B,2,TRUE) -> 0.0001472 | T35: =('AP01'!$O35*'AP01'!$P35)*'AP01'!$S35 -> 41.916672 | U35: ='AP01'!$Q35*0.00899% -> 38.8368
A36: =A35+1 -> 22 | B36: =EDATE(B35,1) -> 43911 | C36: 0.062 | D36: 0.005025 | E36: ='AP01'!$F36+'AP01'!$G36 -> 2270.91 | F36: 1430.91 | G36: =(O35*'AP01'!$P36)/($I$5-A35) -> 840 | H36: 39.82 | I36: 38.83 | J36: =J35 -> 25 | K36: =K35 -> 0 | L36: =L35 -> 0 | M36: =SUM('AP01'!$F36:$L36) -> 2374.56 | N36: =O35*('AP01'!$P36-1) -> 0 | O36: =(O35*'AP01'!$P36)-'AP01'!$G36 -> 283920 | P36: =P35 -> 1 | Q36: =(Q35*'AP01'!$P36) -> 432000 | R36: =DATEDIF($S$7,'AP01'!$B36,"Y") -> 34 | S36: =VLOOKUP('AP01'!$R36,SEGUROS!$A:$B,2,TRUE) -> 0.0001472 | T36: =('AP01'!$O36*'AP01'!$P36)*'AP01'!$S36 -> 41.793024 | U36: ='AP01'!$Q36*0.00899% -> 38.8368
A37: =A36+1 -> 23 | B37: =EDATE(B36,1) -> 43942 | C37: 0.062 | D37: =D36 -> 0.005025 | E37: ='AP01'!$F37+'AP01'!$G37 -> 2266.69 | F37: 1426.69 | G37: =(O36*'AP01'!$P37)/($I$5-A36) -> 840 | H37: 39.71 | I37: 38.83 | J37: =J36 -> 25 | K37: =K36 -> 0 | L37: =L36 -> 0 | M37: =SUM('AP01'!$F37:$L37) -> 2370.23 | N37: =O36*('AP01'!$P37-1) -> 0 | O37: =(O36*'AP01'!$P37)-'AP01'!$G37 -> 283080 | P37: =P36 -> 1 | Q37: =(Q36*'AP01'!$P37) -> 432000 | R37: =DATEDIF($S$7,'AP01'!$B37,"Y") -> 34 | S37: =VLOOKUP('AP01'!$R37,SEGUROS!$A:$B,2,TRUE) -> 0.0001472 | T37: =('AP01'!$O37*'AP01'!$P37)*'AP01'!$S37 -> 41.669376 | U37: ='AP01'!$Q37*0.00899% -> 38.8368
A38: =A37+1 -> 24 | B38: =EDATE(B37,1) -> 43972 | C38: 0.062 | D38: =D37 -> 0.005025 | E38: ='AP01'!$F38+'AP01'!$G38 -> 2262.47 | F38: 1422.47 | G38: =(O37*'AP01'!$P38)/($I$5-A37) -> 840 | H38: 39.59 | I38: 38.83 | J38: =J37 -> 25 | K38: =K37 -> 0 | L38: =L37 -> 0 | M38: =SUM('AP01'!$F38:$L38) -> 2365.89 | N38: =O37*('AP01'!$P38-1) -> 0 | O38: =(O37*'AP01'!$P38)-'AP01'!$G38 -> 282240 | P38: =P37 -> 1 | Q38: =(Q37*'AP01'!$P38) -> 432000 | R38: =DATEDIF($S$7,'AP01'!$B38,"Y") -> 34 | S38: =VLOOKUP('AP01'!$R38,SEGUROS!$A:$B,2,TRUE) -> 0.0001472 | T38: =('AP01'!$O38*'AP01'!$P38)*'AP01'!$S38 -> 41.545728 | U38: ='AP01'!$Q38*0.00899% -> 38.8368
A39: =A38+1 -> 25 | B39: =EDATE(B38,1) -> 44003 | C39: 0.062 | D39: =D38 -> 0.005025 | E39: ='AP01'!$F39+'AP01'!$G39 -> 2258.25 | F39: 1418.25 | G39: =(O38*'AP01'!$P39)/($I$5-A38) -> 840 | H39: 39.47 | I39: 38.83 | J39: =J38 -> 25 | K39: =K38 -> 0 | L39: =L38 -> 0 | M39: =SUM('AP01'!$F39:$L39) -> 2361.55 | N39: =O38*('AP01'!$P39-1) -> 0 | O39: =(O38*'AP01'!$P39)-'AP01'!$G39 -> 281400 | P39: =P38 -> 1 | Q39: =(Q38*'AP01'!$P39) -> 432000 | R39: =DATEDIF($S$7,'AP01'!$B39,"Y") -> 34 | S39: =VLOOKUP('AP01'!$R39,SEGUROS!$A:$B,2,TRUE) -> 0.0001472 | T39: =('AP01'!$O39*'AP01'!$P39)*'AP01'!$S39 -> 41.42208 | U39: ='AP01'!$Q39*0.00899% -> 38.8368
A40: =A39+1 -> 26 | B40: =EDATE(B39,1) -> 44033 | C40: 0.062 | D40: =D39 -> 0.005025 | E40: ='AP01'!$F40+'AP01'!$G40 -> 2254.03 | F40: 1414.03 | G40: =(O39*'AP01'!$P40)/($I$5-A39) -> 840 | H40: 39.35 | I40: 38.83 | J40: =J39 -> 25 | K40: =K39 -> 0 | L40: =L39 -> 0 | M40: =SUM('AP01'!$F40:$L40) -> 2357.21 | N40: =O39*('AP01'!$P40-1) -> 0 | O40: =(O39*'AP01'!$P40)-'AP01'!$G40 -> 280560 | P40: =P39 -> 1 | Q40: =(Q39*'AP01'!$P40) -> 432000 | R40: =DATEDIF($S$7,'AP01'!$B40,"Y") -> 34 | S40: =VLOOKUP('AP01'!$R40,SEGUROS!$A:$B,2,TRUE) -> 0.0001472 | T40: =('AP01'!$O40*'AP01'!$P40)*'AP01'!$S40 -> 41.298432 | U40: ='AP01'!$Q40*0.00899% -> 38.8368
A41: =A40+1 -> 27 | B41: =EDATE(B40,1) -> 44064 | C41: 0.062 | D41: =D40 -> 0.005025 | E41: ='AP01'!$F41+'AP01'!$G41 -> 2249.81 | F41: 1409.81 | G41: =(O40*'AP01'!$P41)/($I$5-A40) -> 840 | H41: 39.24 | I41: 38.83 | J41: =J40 -> 25 | K41: =K40 -> 0 | L41: =L40 -> 0 | M41: =SUM('AP01'!$F41:$L41) -> 2352.88 | N41: =O40*('AP01'!$P41-1) -> 0 | O41: =(O40*'AP01'!$P41)-'AP01'!$G41 -> 279720 | P41: =P40 -> 1 | Q41: =(Q40*'AP01'!$P41) -> 432000 | R41: =DATEDIF($S$7,'AP01'!$B41,"Y") -> 34 | S41: =VLOOKUP('AP01'!$R41,SEGUROS!$A:$B,2,TRUE) -> 0.0001472 | T41: =('AP01'!$O41*'AP01'!$P41)*'AP01'!$S41 -> 41.174784 | U41: ='AP01'!$Q41*0.00899% -> 38.8368
A42: =A41+1 -> 28 | B42: =EDATE(B41,1) -> 44095 | C42: =C41 -> 0.062 | D42: =D41 -> 0.005025 | E42: ='AP01'!$F42+'AP01'!$G42 -> 2245.59 | F42: 1405.59 | G42: =(O41*'AP01'!$P42)/($I$5-A41) -> 840 | H42: 39.12 | I42: 38.83 | J42: =J41 -> 25 | K42: =K41 -> 0 | L42: =L41 -> 0 | M42: =SUM('AP01'!$F42:$L42) -> 2348.54 | N42: =O41*('AP01'!$P42-1) -> 0 | O42: =(O41*'AP01'!$P42)-'AP01'!$G42 -> 278880 | P42: =P41 -> 1 | Q42: =(Q41*'AP01'!$P42) -> 432000 | R42: =DATEDIF($S$7,'AP01'!$B42,"Y") -> 34 | S42: =VLOOKUP('AP01'!$R42,SEGUROS!$A:$B,2,TRUE) -> 0.0001472 | T42: =('AP01'!$O42*'AP01'!$P42)*'AP01'!$S42 -> 41.051136 | U42: ='AP01'!$Q42*0.00899% -> 38.8368
A43: =A42+1 -> 29 | B43: =EDATE(B42,1) -> 44125 | C43: =C42 -> 0.062 | D43: =D42 -> 0.005025 | E43: ='AP01'!$F43+'AP01'!$G43 -> 2241.49 | F43: 1401.49 | G43: =(O42*'AP01'!$P43)/($I$5-A42) -> 840 | H43: 39.01 | I43: 38.84 | J43: =J42 -> 25 | K43: =K42 -> 0 | L43: =L42 -> 0 | M43: =SUM('AP01'!$F43:$L43) -> 2344.34 | N43: =O42*('AP01'!$P43-1) -> 0 | O43: =(O42*'AP01'!$P43)-'AP01'!$G43 -> 278040 | P43: =P42 -> 1 | Q43: =(Q42*'AP01'!$P43) -> 432000 | R43: =DATEDIF($S$7,'AP01'!$B43,"Y") -> 34 | S43: =VLOOKUP('AP01'!$R43,SEGUROS!$A:$B,2,TRUE) -> 0.0001472 | T43: =('AP01'!$O43*'AP01'!$P43)*'AP01'!$S43 -> 40.927488 | U43: ='AP01'!$Q43*0.00899% -> 38.8368
A44: =A43+1 -> 30 | B44: =EDATE(B43,1) -> 44156 | C44: =C43 -> 0.062 | D44: =D43 -> 0.005025 | E44: ='AP01'!$F44+'AP01'!$G44 -> 2237.27 | F44: 1397.27 | G44: =(O43*'AP01'!$P44)/($I$5-A43) -> 840 | H44: 38.89 | I44: 38.84 | J44: =J43 -> 25 | K44: =K43 -> 0 | L44: =L43 -> 0 | M44: =SUM('AP01'!$F44:$L44) -> 2340 | N44: =O43*('AP01'!$P44-1) -> 0 | O44: =(O43*'AP01'!$P44)-'AP01'!$G44 -> 277200 | P44: =P43 -> 1 | Q44: =(Q43*'AP01'!$P44) -> 432000 | R44: =DATEDIF($S$7,'AP01'!$B44,"Y") -> 34 | S44: =VLOOKUP('AP01'!$R44,SEGUROS!$A:$B,2,TRUE) -> 0.0001472 | T44: =('AP01'!$O44*'AP01'!$P44)*'AP01'!$S44 -> 40.80384 | U44: ='AP01'!$Q44*0.00899% -> 38.8368
A45: =A44+1 -> 31 | B45: =EDATE(B44,1) -> 44186 | C45: =C44 -> 0.062 | D45: =D44 -> 0.005025 | E45: ='AP01'!$F45+'AP01'!$G45 -> 2233.04 | F45: 1393.04 | G45: =(O44*'AP01'!$P45)/($I$5-A44) -> 840 | H45: 39.71 | I45: 38.84 | J45: =J44 -> 25 | K45: =K44 -> 0 | L45: =L44 -> 0 | M45: =SUM('AP01'!$F45:$L45) -> 2336.59 | N45: =O44*('AP01'!$P45-1) -> 0 | O45: =(O44*'AP01'!$P45)-'AP01'!$G45 -> 276360 | P45: =P44 -> 1 | Q45: =(Q44*'AP01'!$P45) -> 432000 | R45: =DATEDIF($S$7,'AP01'!$B45,"Y") -> 35 | S45: =VLOOKUP('AP01'!$R45,SEGUROS!$A:$B,2,TRUE) -> 0.0001548 | T45: =('AP01'!$O45*'AP01'!$P45)*'AP01'!$S45 -> 42.780528 | U45: ='AP01'!$Q45*0.00899% -> 38.8368
A46: =A45+1 -> 32 | B46: =EDATE(B45,1) -> 44217 | C46: =C45 -> 0.062 | D46: =D45 -> 0.005025 | E46: ='AP01'!$F46+'AP01'!$G46 -> 2228.82 | F46: 1388.82 | G46: =(O45*'AP01'!$P46)/($I$5-A45) -> 840 | H46: 39.59 | I46: 38.84 | J46: =J45 -> 25 | K46: =K45 -> 0 | L46: =L45 -> 0 | M46: =SUM('AP01'!$F46:$L46) -> 2332.25 | N46: =O45*('AP01'!$P46-1) -> 0 | O46: =(O45*'AP01'!$P46)-'AP01'!$G46 -> 275520 | P46: =P45 -> 1 | Q46: =(Q45*'AP01'!$P46) -> 432000 | R46: =DATEDIF($S$7,'AP01'!$B46,"Y") -> 35 | S46: =VLOOKUP('AP01'!$R46,SEGUROS!$A:$B,2,TRUE) -> 0.0001548 | T46: =('AP01'!$O46*'AP01'!$P46)*'AP01'!$S46 -> 42.650496 | U46: ='AP01'!$Q46*0.00899% -> 38.8368
A47: =A46+1 -> 33 | B47: =EDATE(B46,1) -> 44248 | C47: =C46 -> 0.062 | D47: =D46 -> 0.005025 | E47: ='AP01'!$F47+'AP01'!$G47 -> 2224.6 | F47: 1384.6 | G47: =(O46*'AP01'!$P47)/($I$5-A46) -> 840 | H47: 40.09 | I47: 38.84 | J47: =J46 -> 25 | K47: =K46 -> 0 | L47: =L46 -> 0 | M47: =SUM('AP01'!$F47:$L47) -> 2328.53 | N47: =O46*('AP01'!$P47-1) -> 0 | O47: =(O46*'AP01'!$P47)-'AP01'!$G47 -> 274680 | P47: =P46 -> 1 | Q47: =(Q46*'AP01'!$P47) -> 432000 | R47: =DATEDIF($S$7,'AP01'!$B47,"Y") -> 35 | S47: =VLOOKUP('AP01'!$R47,SEGUROS!$A:$B,2,TRUE) -> 0.0001548 | T47: =('AP01'!$O47*'AP01'!$P47)*'AP01'!$S47 -> 42.520464 | U47: ='AP01'!$Q47*0.00899% -> 38.8368
A48: =A47+1 -> 34 | B48: =EDATE(B47,1) -> 44276 | C48: =C47 -> 0.062 | D48: =D47 -> 0.005025 | E48: ='AP01'!$F48+'AP01'!$G48 -> 2220.38 | F48: 1380.38 | G48: =(O47*'AP01'!$P48)/($I$5-A47) -> 840 | H48: 39.97 | I48: 38.84 | J48: =J47 -> 25 | K48: =K47 -> 0 | L48: =L47 -> 0 | M48: =SUM('AP01'!$F48:$L48) -> 2324.19 | N48: =O47*('AP01'!$P48-1) -> 0 | O48: =(O47*'AP01'!$P48)-'AP01'!$G48 -> 273840 | P48: =P47 -> 1 | Q48: =(Q47*'AP01'!$P48) -> 432000 | R48: =DATEDIF($S$7,'AP01'!$B48,"Y") -> 35 | S48: =VLOOKUP('AP01'!$R48,SEGUROS!$A:$B,2,TRUE) -> 0.0001548 | T48: =('AP01'!$O48*'AP01'!$P48)*'AP01'!$S48 -> 42.390432 | U48: ='AP01'!$Q48*0.00899% -> 38.8368
A49: =A48+1 -> 35 | B49: =EDATE(B48,1) -> 44307 | C49: =C48 -> 0.062 | D49: =D48 -> 0.005025 | E49: ='AP01'!$F49+'AP01'!$G49 -> 2216.16 | F49: 1376.16 | G49: =(O48*'AP01'!$P49)/($I$5-A48) -> 840 | H49: 39.85 | I49: 38.84 | J49: =J48 -> 25 | K49: =K48 -> 0 | L49: =L48 -> 0 | M49: =SUM('AP01'!$F49:$L49) -> 2319.85 | N49: =O48*('AP01'!$P49-1) -> 0 | O49: =(O48*'AP01'!$P49)-'AP01'!$G49 -> 273000 | P49: =P48 -> 1 | Q49: =(Q48*'AP01'!$P49) -> 432000 | R49: =DATEDIF($S$7,'AP01'!$B49,"Y") -> 35 | S49: =VLOOKUP('AP01'!$R49,SEGUROS!$A:$B,2,TRUE) -> 0.0001548 | T49: =('AP01'!$O49*'AP01'!$P49)*'AP01'!$S49 -> 42.2604 | U49: ='AP01'!$Q49*0.00899% -> 38.8368
A50: =A49+1 -> 36 | B50: =EDATE(B49,1) -> 44337 | C50: =C49 -> 0.062 | D50: =D49 -> 0.005025 | E50: ='AP01'!$F50+'AP01'!$G50 -> 2211.94 | F50: 1371.94 | G50: =(O49*'AP01'!$P50)/($I$5-A49) -> 840 | H50: 39.73 | I50: 38.84 | J50: =J49 -> 25 | K50: =K49 -> 0 | L50: =L49 -> 0 | M50: =SUM('AP01'!$F50:$L50) -> 2315.51 | N50: =O49*('AP01'!$P50-1) -> 0 | O50: =(O49*'AP01'!$P50)-'AP01'!$G50 -> 272160 | P50: =P49 -> 1 | Q50: =(Q49*'AP01'!$P50) -> 432000 | R50: =DATEDIF($S$7,'AP01'!$B50,"Y") -> 35 | S50: =VLOOKUP('AP01'!$R50,SEGUROS!$A:$B,2,TRUE) -> 0.0001548 | T50: =('AP01'!$O50*'AP01'!$P50)*'AP01'!$S50 -> 42.130368 | U50: ='AP01'!$Q50*0.00899% -> 38.8368
A51: =A50+1 -> 37 | B51: =EDATE(B50,1) -> 44368 | C51: =C50 -> 0.062 | D51: =D50 -> 0.005025 | E51: ='AP01'!$F51+'AP01'!$G51 -> 2207.72 | F51: 1367.72 | G51: =(O50*'AP01'!$P51)/($I$5-A50) -> 840 | H51: 39.6 | I51: 38.84 | J51: =J50 -> 25 | K51: =K50 -> 0 | L51: =L50 -> 0 | M51: =SUM('AP01'!$F51:$L51) -> 2311.16 | N51: =O50*('AP01'!$P51-1) -> 0 | O51: =(O50*'AP01'!$P51)-'AP01'!$G51 -> 271320 | P51: =P50 -> 1 | Q51: =(Q50*'AP01'!$P51) -> 432000 | R51: =DATEDIF($S$7,'AP01'!$B51,"Y") -> 35 | S51: =VLOOKUP('AP01'!$R51,SEGUROS!$A:$B,2,TRUE) -> 0.0001548 | T51: =('AP01'!$O51*'AP01'!$P51)*'AP01'!$S51 -> 42.000336 | U51: ='AP01'!$Q51*0.00899% -> 38.8368
A52: =A51+1 -> 38 | B52: =EDATE(B51,1) -> 44398 | C52: =C51 -> 0.062 | D52: =D51 -> 0.005025 | E52: ='AP01'!$F52+'AP01'!$G52 -> 2203.49 | F52: 1363.49 | G52: =(O51*'AP01'!$P52)/($I$5-A51) -> 840 | H52: 39.48 | I52: 38.84 | J52: =J51 -> 25 | K52: =K51 -> 0 | L52: =L51 -> 0 | M52: =SUM('AP01'!$F52:$L52) -> 2306.81 | N52: =O51*('AP01'!$P52-1) -> 0 | O52: =(O51*'AP01'!$P52)-'AP01'!$G52 -> 270480 | P52: =P51 -> 1 | Q52: =(Q51*'AP01'!$P52) -> 432000 | R52: =DATEDIF($S$7,'AP01'!$B52,"Y") -> 35 | S52: =VLOOKUP('AP01'!$R52,SEGUROS!$A:$B,2,TRUE) -> 0.0001548 | T52: =('AP01'!$O52*'AP01'!$P52)*'AP01'!$S52 -> 41.870304 | U52: ='AP01'!$Q52*0.00899% -> 38.8368
A53: =A52+1 -> 39 | B53: =EDATE(B52,1) -> 44429 | C53: =C52 -> 0.062 | D53: =D52 -> 0.005025 | E53: ='AP01'!$F53+'AP01'!$G53 -> 2199.27 | F53: 1359.27 | G53: =(O52*'AP01'!$P53)/($I$5-A52) -> 840 | H53: 39.36 | I53: 38.84 | J53: =J52 -> 25 | K53: =K52 -> 0 | L53: =L52 -> 0 | M53: =SUM('AP01'!$F53:$L53) -> 2302.47 | N53: =O52*('AP01'!$P53-1) -> 0 | O53: =(O52*'AP01'!$P53)-'AP01'!$G53 -> 269640 | P53: =P52 -> 1 | Q53: =(Q52*'AP01'!$P53) -> 432000 | R53: =DATEDIF($S$7,'AP01'!$B53,"Y") -> 35 | S53: =VLOOKUP('AP01'!$R53,SEGUROS!$A:$B,2,TRUE) -> 0.0001548 | T53: =('AP01'!$O53*'AP01'!$P53)*'AP01'!$S53 -> 41.740272 | U53: ='AP01'!$Q53*0.00899% -> 38.8368
... A57: =A56+1 -> 43 | B57: =EDATE(B56,1) -> 44551 | C57: =C56 -> 0.062 | D57: =D56 -> 0.005025 | E57: ='AP01'!$F57+'AP01'!$G57 -> 2182.39 | F57: 1342.39 | G57: =(O56*'AP01'!$P57)/($I$5-A56) -> 840 | H57: 48.24 | I57: 38.84 | J57: =J56 -> 25 | K57: =K56 -> 0 | L57: =L56 -> 0 | M57: =SUM('AP01'!$F57:$L57) -> 2294.47 | N57: =O56*('AP01'!$P57-1) -> 0 | O57: =(O56*'AP01'!$P57)-'AP01'!$G57 -> 266280 | P57: =P56 -> 1 | Q57: =(Q56*'AP01'!$P57) -> 432000 | R57: =DATEDIF($S$7,'AP01'!$B57,"Y") -> 36 | S57: =VLOOKUP('AP01'!$R57,SEGUROS!$A:$B,2,TRUE) -> 0.0002337 | T57: =('AP01'!$O57*'AP01'!$P57)*'AP01'!$S57 -> 62.229636 | U57: ='AP01'!$Q57*0.00899% -> 38.8368
A58: =A57+1 -> 44 | B58: =EDATE(B57,1) -> 44582 | C58: =C57 -> 0.062 | D58: =D57 -> 0.005025 | E58: ='AP01'!$F58+'AP01'!$G58 -> 2180.7738 | F58: 1339.77 | G58: =(O57*'AP01'!$P58)/($I$5-A57) -> 841.0038 | H58: 48.14 | I58: 38.88 | J58: =J57 -> 25 | K58: =K57 -> 0 | L58: =L57 -> 0 | M58: =SUM('AP01'!$F58:$L58) -> 2292.7938 | N58: =O57*('AP01'!$P58-1) -> 318.2046 | O58: =(O57*'AP01'!$P58)-'AP01'!$G58 -> 265757.2 | P58: 1.001195 | Q58: =(Q57*'AP01'!$P58) -> 432516.24 | R58: =DATEDIF($S$7,'AP01'!$B58,"Y") -> 36 | S58: =VLOOKUP('AP01'!$R58,SEGUROS!$A:$B,2,TRUE) -> 0.0002337 | T58: =('AP01'!$O58*'AP01'!$P58)*'AP01'!$S58 -> 62.181676 | U58: ='AP01'!$Q58*0.00899% -> 38.88321
A59: =A58+1 -> 45 | B59: =EDATE(B58,1) -> 44613 | C59: =C58 -> 0.062 | D59: =D58 -> 0.005025 | E59: ='AP01'!$F59+'AP01'!$G59 -> 2178.3711 | F59: 1336.66 | G59: =(O58*'AP01'!$P59)/($I$5-A58) -> 841.71108 | H59: 48.65 | I59: 38.92 | J59: =J58 -> 25 | K59: =K58 -> 0 | L59: =L58 -> 0 | M59: =SUM('AP01'!$F59:$L59) -> 2290.9411 | N59: =O58*('AP01'!$P59-1) -> 223.50181 | O59: =(O58*'AP01'!$P59)-'AP01'!$G59 -> 265138.99 | P59: 1.000841 | Q59: =(Q58*'AP01'!$P59) -> 432879.99 | R59: =DATEDIF($S$7,'AP01'!$B59,"Y") -> 36 | S59: =VLOOKUP('AP01'!$R59,SEGUROS!$A:$B,2,TRUE) -> 0.0002337 | T59: =('AP01'!$O59*'AP01'!$P59)*'AP01'!$S59 -> 62.015093 | U59: ='AP01'!$Q59*0.00899% -> 38.915911
A60: =A59+1 -> 46 | B60: =EDATE(B59,1) -> 44641 | C60: =C59 -> 0.062 | D60: =D59 -> 0.005025 | E60: ='AP01'!$F60+'AP01'!$G60 -> 2174.1411 | F60: 1332.43 | G60: =(O59*'AP01'!$P60)/($I$5-A59) -> 841.71108 | H60: 48.5 | I60: 38.92 | J60: =J59 -> 25 | K60: =K59 -> 0 | L60: =L59 -> 0 | M60: =SUM('AP01'!$F60:$L60) -> 2286.5611 | N60: =O59*('AP01'!$P60-1) -> 0 | O60: =(O59*'AP01'!$P60)-'AP01'!$G60 -> 264297.28 | P60: 1 | Q60: =(Q59*'AP01'!$P60) -> 432879.99 | R60: =DATEDIF($S$7,'AP01'!$B60,"Y") -> 36 | S60: =VLOOKUP('AP01'!$R60,SEGUROS!$A:$B,2,TRUE) -> 0.0002337 | T60: =('AP01'!$O60*'AP01'!$P60)*'AP01'!$S60 -> 61.766274 | U60: ='AP01'!$Q60*0.00899% -> 38.915911
A61: =A60+1 -> 47 | B61: =EDATE(B60,1) -> 44672 | C61: =C60 -> 0.062 | D61: =D60 -> 0.005025 | E61: ='AP01'!$F61+'AP01'!$G61 -> 2172.7838 | F61: 1329.96 | G61: =(O60*'AP01'!$P61)/($I$5-A60) -> 842.82383 | H61: 48.41 | I61: 38.97 | J61: =J60 -> 25 | K61: =K60 -> 0 | L61: =L60 -> 0 | M61: =SUM('AP01'!$F61:$L61) -> 2285.1638 | N61: =O60*('AP01'!$P61-1) -> 349.401 | O61: =(O60*'AP01'!$P61)-'AP01'!$G61 -> 263803.86 | P61: 1.001322 | Q61: =(Q60*'AP01'!$P61) -> 433452.25 | R61: =DATEDIF($S$7,'AP01'!$B61,"Y") -> 36 | S61: =VLOOKUP('AP01'!$R61,SEGUROS!$A:$B,2,TRUE) -> 0.0002337 | T61: =('AP01'!$O61*'AP01'!$P61)*'AP01'!$S61 -> 61.732464 | U61: ='AP01'!$Q61*0.00899% -> 38.967358
A62: =A61+1 -> 48 | B62: =EDATE(B61,1) -> 44702 | C62: =C61 -> 0.062 | D62: =D61 -> 0.005025 | E62: ='AP01'!$F62+'AP01'!$G62 -> 2171.3712 | F62: 1327.45 | G62: =(O61*'AP01'!$P62)/($I$5-A61) -> 843.92118 | H62: 48.32 | I62: 39.02 | J62: =J61 -> 25 | K62: =K61 -> 0 | L62: =L61 -> 0 | M62: =SUM('AP01'!$F62:$L62) -> 2283.7112 | N62: =O61*('AP01'!$P62-1) -> 343.47262 | O62: =(O61*'AP01'!$P62)-'AP01'!$G62 -> 263303.41 | P62: 1.001302 | Q62: =(Q61*'AP01'!$P62) -> 434016.61 | R62: =DATEDIF($S$7,'AP01'!$B62,"Y") -> 36 | S62: =VLOOKUP('AP01'!$R62,SEGUROS!$A:$B,2,TRUE) -> 0.0002337 | T62: =('AP01'!$O62*'AP01'!$P62)*'AP01'!$S62 -> 61.614124 | U62: ='AP01'!$Q62*0.00899% -> 39.018093
A63: =A62+1 -> 49 | B63: =EDATE(B62,1) -> 44733 | C63: =C62 -> 0.062 | D63: =D62 -> 0.005025 | E63: =E62 -> 2171.3712 | F63: 1324.61 | G63: =(O62*'AP01'!$P63)/($I$5-A62) -> 844.81743 | H63: 48.21 | I63: 39.06 | J63: =J62 -> 25 | K63: =K62 -> 0 | L63: =L62 -> 0 | M63: =SUM('AP01'!$F63:$L63) -> 2281.6974 | N63: =O62*('AP01'!$P63-1) -> 279.62822 | O63: =(O62*'AP01'!$P63)-'AP01'!$G63 -> 262738.22 | P63: 1.001062 | Q63: =(Q62*'AP01'!$P63) -> 434477.53 | R63: =DATEDIF($S$7,'AP01'!$B63,"Y") -> 36 | S63: =VLOOKUP('AP01'!$R63,SEGUROS!$A:$B,2,TRUE) -> 0.0002337 | T63: =('AP01'!$O63*'AP01'!$P63)*'AP01'!$S63 -> 61.467131 | U63: ='AP01'!$Q63*0.00899% -> 39.05953
A64: =A63+1 -> 50 | B64: =EDATE(B63,1) -> 44763 | C64: =C63 -> 0.062 | D64: =D63 -> 0.005025 | E64: =E63 -> 2171.3712 | F64: 1322.91 | G64: =(O63*'AP01'!$P64)/($I$5-A63) -> 846.44201 | H64: 48.15 | I64: 39.13 | J64: =J63 -> 25 | K64: =K63 -> 0 | L64: =L63 -> 0 | M64: =SUM('AP01'!$F64:$L64) -> 2281.632 | N64: =O63*('AP01'!$P64-1) -> 505.2456 | O64: 262397.03 | P64: 1.001923 | Q64: =(Q63*'AP01'!$P64) -> 435313.03 | R64: =DATEDIF($S$7,'AP01'!$B64,"Y") -> 36 | S64: =VLOOKUP('AP01'!$R64,SEGUROS!$A:$B,2,TRUE) -> 0.0002337 | T64: =('AP01'!$O64*'AP01'!$P64)*'AP01'!$S64 -> 61.440108 | U64: ='AP01'!$Q64*0.00899% -> 39.134642
A65: =A64+1 -> 51 | B65: =EDATE(B64,1) -> 44794 | C65: =C64 -> 0.062 | D65: =D64 -> 0.005025 | E65: =E64 -> 2171.3712 | F65: 1321.41 | G65: =(O64*'AP01'!$P65)/($I$5-A64) -> 848.2111 | H65: 48.1 | I65: 39.22 | J65: =J64 -> 25 | K65: =K64 -> 0 | L65: =L64 -> 0 | M65: =SUM('AP01'!$F65:$L65) -> 2281.9411 | N65: =O64*('AP01'!$P65-1) -> 548.40979 | O65: 262097.23 | P65: 1.00209 | Q65: =(Q64*'AP01'!$P65) -> 436222.84 | R65: =DATEDIF($S$7,'AP01'!$B65,"Y") -> 36 | S65: =VLOOKUP('AP01'!$R65,SEGUROS!$A:$B,2,TRUE) -> 0.0002337 | T65: =('AP01'!$O65*'AP01'!$P65)*'AP01'!$S65 -> 61.38014 | U65: ='AP01'!$Q65*0.00899% -> 39.216433
A66: =A65+1 -> 52 | B66: =EDATE(B65,1) -> 44825 | C66: =C65 -> 0.062 | D66: =D65 -> 0.005025 | E66: =E65 -> 2171.3712 | F66: 1319.51 | G66: =(O65*'AP01'!$P66)/($I$5-A65) -> 849.73109 | H66: 48.03 | I66: 39.29 | J66: =J65 -> 25 | K66: =K65 -> 0 | L66: =L65 -> 0 | M66: =SUM('AP01'!$F66:$L66) -> 2281.5611 | N66: =O65*('AP01'!$P66-1) -> 469.67824 | O66: 261717.18 | P66: 1.001792 | Q66: =(Q65*'AP01'!$P66) -> 437004.55 | R66: =DATEDIF($S$7,'AP01'!$B66,"Y") -> 36 | S66: =VLOOKUP('AP01'!$R66,SEGUROS!$A:$B,2,TRUE) -> 0.0002337 | T66: =('AP01'!$O66*'AP01'!$P66)*'AP01'!$S66 -> 61.27291 | U66: ='AP01'!$Q66*0.00899% -> 39.286709
A67: =A66+1 -> 53 | B67: =EDATE(B66,1) -> 44855 | C67: =C66 -> 0.062 | D67: =D66 -> 0.005025 | E67: =E66 -> 2171.3712 | F67: 1317.65 | G67: =(O66*'AP01'!$P67)/($I$5-A66) -> 851.29121 | H67: 47.96 | I67: 39.36 | J67: =J66 -> 25 | K67: =K66 -> 0 | L67: =L66 -> 0 | M67: =SUM('AP01'!$F67:$L67) -> 2281.2612 | N67: =O66*('AP01'!$P67-1) -> 480.51274 | O67: 261346.4 | P67: 1.001836 | Q67: =(Q66*'AP01'!$P67) -> 437806.89 | R67: =DATEDIF($S$7,'AP01'!$B67,"Y") -> 36 | S67: =VLOOKUP('AP01'!$R67,SEGUROS!$A:$B,2,TRUE) -> 0.0002337 | T67: =('AP01'!$O67*'AP01'!$P67)*'AP01'!$S67 -> 61.18879 | U67: ='AP01'!$Q67*0.00899% -> 39.358839
A68: =A67+1 -> 54 | B68: =EDATE(B67,1) -> 44886 | C68: =C67 -> 0.062 | D68: =D67 -> 0.005025 | E68: =E67 -> 2171.3712 | F68: 1314.87 | G68: =(O67*'AP01'!$P68)/($I$5-A67) -> 852.25912 | H68: 47.86 | I68: 39.4 | J68: =J67 -> 25 | K68: =K67 -> 0 | L68: =L67 -> 0 | M68: =SUM('AP01'!$F68:$L68) -> 2279.3891 | N68: =O67*('AP01'!$P68-1) -> 297.15086 | O68: 260791.29 | P68: 1.001137 | Q68: =(Q67*'AP01'!$P68) -> 438304.68 | R68: =DATEDIF($S$7,'AP01'!$B68,"Y") -> 36 | S68: =VLOOKUP('AP01'!$R68,SEGUROS!$A:$B,2,TRUE) -> 0.0002337 | T68: =('AP01'!$O68*'AP01'!$P68)*'AP01'!$S68 -> 61.016221 | U68: ='AP01'!$Q68*0.00899% -> 39.40359
A69: =A68+1 -> 55 | B69: =EDATE(B68,1) -> 44916 | C69: =C68 -> 0.062 | D69: =D68 -> 0.005025 | E69: =E68 -> 2171.3712 | F69: 1313.33 | G69: =(O68*'AP01'!$P69)/($I$5-A68) -> 854.0429 | H69: 49.34 | I69: 39.49 | J69: =J68 -> 25 | K69: =K68 -> 0 | L69: =L68 -> 0 | M69: =SUM('AP01'!$F69:$L69) -> 2281.2029 | N69: =O68*('AP01'!$P69-1) -> 545.83617 | O69: 260483.09 | P69: 1.002093 | Q69: =(Q68*'AP01'!$P69) -> 439222.05 | R69: =DATEDIF($S$7,'AP01'!$B69,"Y") -> 37 | S69: =VLOOKUP('AP01'!$R69,SEGUROS!$A:$B,2,TRUE) -> 0.0002469 | T69: =('AP01'!$O69*'AP01'!$P69)*'AP01'!$S69 -> 64.447883 | U69: ='AP01'!$Q69*0.00899% -> 39.486062
A70: =A69+1 -> 56 | B70: =EDATE(B69,1) -> 44947 | C70: =C69 -> 0.062 | D70: =D69 -> 0.005025 | E70: =E69 -> 2171.3712 | F70: 1312.19 | G70: =(O69*'AP01'!$P70)/($I$5-A69) -> 856.10116 | H70: 49.29 | I70: 39.58 | J70: =J69 -> 25 | K70: =K69 -> 0 | L70: =L69 -> 0 | M70: =SUM('AP01'!$F70:$L70) -> 2282.1612 | N70: =O69*('AP01'!$P70-1) -> 627.76425 | O70: 260254.75 | P70: 1.00241 | Q70: =(Q69*'AP01'!$P70) -> 440280.57 | R70: =DATEDIF($S$7,'AP01'!$B70,"Y") -> 37 | S70: =VLOOKUP('AP01'!$R70,SEGUROS!$A:$B,2,TRUE) -> 0.0002469 | T70: =('AP01'!$O70*'AP01'!$P70)*'AP01'!$S70 -> 64.411757 | U70: ='AP01'!$Q70*0.00899% -> 39.581224
A71: =A70+1 -> 57 | B71: =EDATE(B70,1) -> 44978 | C71: =C70 -> 0.062 | D71: =D70 -> 0.005025 | E71: =E70 -> 2171.3712 | F71: 1309.83 | G71: =(O70*'AP01'!$P71)/($I$5-A70) -> 857.37503 | H71: 49.91 | I71: 39.64 | J71: =J70 -> 25 | K71: =K70 -> 0 | L71: =L70 -> 0 | M71: =SUM('AP01'!$F71:$L71) -> 2281.755 | N71: =O70*('AP01'!$P71-1) -> 387.25907 | O71: 259784.63 | P71: 1.001488 | Q71: =(Q70*'AP01'!$P71) -> 440935.71 | R71: =DATEDIF($S$7,'AP01'!$B71,"Y") -> 37 | S71: =VLOOKUP('AP01'!$R71,SEGUROS!$A:$B,2,TRUE) -> 0.0002469 | T71: =('AP01'!$O71*'AP01'!$P71)*'AP01'!$S71 -> 64.236267 | U71: ='AP01'!$Q71*0.00899% -> 39.64012
A72: =A71+1 -> 58 | B72: =EDATE(B71,1) -> 45006 | C72: =C71 -> 0.062 | D72: =D71 -> 0.005025 | E72: =E71 -> 2171.3712 | F72: 1306.95 | G72: =(O71*'AP01'!$P72)/($I$5-A71) -> 858.31298 | H72: 49.8 | I72: 39.68 | J72: =J71 -> 25 | K72: =K71 -> 0 | L72: =L71 -> 0 | M72: =SUM('AP01'!$F72:$L72) -> 2279.743 | N72: =O71*('AP01'!$P72-1) -> 284.20439 | O72: 259210.52 | P72: 1.001094 | Q72: =(Q71*'AP01'!$P72) -> 441418.09 | R72: =DATEDIF($S$7,'AP01'!$B72,"Y") -> 37 | S72: =VLOOKUP('AP01'!$R72,SEGUROS!$A:$B,2,TRUE) -> 0.0002469 | T72: =('AP01'!$O72*'AP01'!$P72)*'AP01'!$S72 -> 64.069092 | U72: ='AP01'!$Q72*0.00899% -> 39.683487
A73: =A72+1 -> 59 | B73: =EDATE(B72,1) -> 45037 | C73: =C72 -> 0.062 | D73: =D72 -> 0.005025 | E73: =E72 -> 2171.3712 | F73: 1305.36 | G73: =(O72*'AP01'!$P73)/($I$5-A72) -> 860.106 | H73: 49.74 | I73: 39.77 | J73: =J72 -> 25 | K73: =K72 -> 0 | L73: =L72 -> 0 | M73: =SUM('AP01'!$F73:$L73) -> 2279.976 | N73: =O72*('AP01'!$P73-1) -> 541.49078 | O73: 258891.9 | P73: 1.002089 | Q73: =(Q72*'AP01'!$P73) -> 442340.22 | R73: =DATEDIF($S$7,'AP01'!$B73,"Y") -> 37 | S73: =VLOOKUP('AP01'!$R73,SEGUROS!$A:$B,2,TRUE) -> 0.0002469 | T73: =('AP01'!$O73*'AP01'!$P73)*'AP01'!$S73 -> 64.05394 | U73: ='AP01'!$Q73*0.00899% -> 39.766386
A74: =A73+1 -> 60 | B74: =EDATE(B73,1) -> 45067 | C74: =C73 -> 0.062 | D74: =D73 -> 0.005025 | E74: =E73 -> 2171.3712 | F74: 1302.5 | G74: =(O73*'AP01'!$P74)/($I$5-A73) -> 861.0693 | H74: 49.63 | I74: 39.81 | J74: =J73 -> 25 | K74: =K73 -> 0 | L74: =L73 -> 0 | M74: =SUM('AP01'!$F74:$L74) -> 2278.0093 | N74: =O73*('AP01'!$P74-1) -> 289.95893 | O74: 258320.79 | P74: 1.00112 | Q74: =(Q73*'AP01'!$P74) -> 442835.64 | R74: =DATEDIF($S$7,'AP01'!$B74,"Y") -> 37 | S74: =VLOOKUP('AP01'!$R74,SEGUROS!$A:$B,2,TRUE) -> 0.0002469 | T74: =('AP01'!$O74*'AP01'!$P74)*'AP01'!$S74 -> 63.850836 | U74: ='AP01'!$Q74*0.00899% -> 39.810924
A75: =A74+1 -> 61 | B75: =EDATE(B74,1) -> 45098 | C75: =C74 -> 0.062 | D75: =D74 -> 0.005025 | E75: =E74 -> 2171.3712 | F75: 1300.49 | G75: =(O74*'AP01'!$P75)/($I$5-A74) -> 862.61148 | H75: 49.56 | I75: 39.88 | J75: =J74 -> 25 | K75: =K74 -> 0 | L75: =L74 -> 0 | M75: =SUM('AP01'!$F75:$L75) -> 2277.5415 | N75: =O74*('AP01'!$P75-1) -> 462.65253 | O75: 257920.83 | P75: 1.001791 | Q75: =(Q74*'AP01'!$P75) -> 443628.76 | R75: =DATEDIF($S$7,'AP01'!$B75,"Y") -> 37 | S75: =VLOOKUP('AP01'!$R75,SEGUROS!$A:$B,2,TRUE) -> 0.0002469 | T75: =('AP01'!$O75*'AP01'!$P75)*'AP01'!$S75 -> 63.794705 | U75: ='AP01'!$Q75*0.00899% -> 39.882225
A76: =A75+1 -> 62 | B76: =EDATE(B75,1) -> 45128 | C76: =C75 -> 0.062 | D76: =D75 -> 0.005025 | E76: =E75 -> 2171.3712 | F76: 1298.75 | G76: =(O75*'AP01'!$P76)/($I$5-A75) -> 864.33928 | H76: 49.49 | I76: 39.96 | J76: =J75 -> 25 | K76: =K75 -> 0 | L76: =L75 -> 0 | M76: =SUM('AP01'!$F76:$L76) -> 2277.5393 | N76: =O75*('AP01'!$P76-1) -> 516.61542 | O76: 257573.11 | P76: 1.002003 | Q76: =(Q75*'AP01'!$P76) -> 444517.35 | R76: =DATEDIF($S$7,'AP01'!$B76,"Y") -> 37 | S76: =VLOOKUP('AP01'!$R76,SEGUROS!$A:$B,2,TRUE) -> 0.0002469 | T76: =('AP01'!$O76*'AP01'!$P76)*'AP01'!$S76 -> 63.722181 | U76: ='AP01'!$Q76*0.00899% -> 39.962109
A77: =A76+1 -> 63 | B77: =EDATE(B76,1) -> 45159 | C77: 0.1049 | D77: =((1+'AP01'!$C77)^(1/12))-1 -> 0.0083475509 | E77: =E76 -> 2171.3712 | F77: 2153.5 | G77: =(O76*'AP01'!$P77)/($I$5-A76) -> 865.70495 | H77: 49.4 | I77: 40.03 | J77: =J76 -> 25 | K77: =K76 -> 0 | L77: =L76 -> 0 | M77: =SUM('AP01'!$F77:$L77) -> 3133.635 | N77: =O76*('AP01'!$P77-1) -> 406.96551 | O77: 257114.38 | P77: 1.00158 | Q77: =(Q76*'AP01'!$P77) -> 445219.68 | R77: =DATEDIF($S$7,'AP01'!$B77,"Y") -> 37 | S77: =VLOOKUP('AP01'!$R77,SEGUROS!$A:$B,2,TRUE) -> 0.0002469 | T77: =('AP01'!$O77*'AP01'!$P77)*'AP01'!$S77 -> 63.581841 | U77: ='AP01'!$Q77*0.00899% -> 40.025249
A78: =A77+1 -> 64 | B78: =EDATE(B77,1) -> 45190 | C78: =C77 -> 0.1049 | D78: =((1+'AP01'!$C78)^(1/12))-1 -> 0.0083475509 | E78: =E77 -> 2171.3712 | F78: 2150.09 | G78: =(O77*'AP01'!$P78)/($I$5-A77) -> 867.24421 | H78: 49.33 | I78: 40.1 | J78: =J77 -> 25 | K78: =K77 -> 0 | L78: =L77 -> 0 | M78: =SUM('AP01'!$F78:$L78) -> 3131.7642 | N78: =O77*('AP01'!$P78-1) -> 457.14937 | O78: 256704.29 | P78: 1.001778 | Q78: =(Q77*'AP01'!$P78) -> 446011.28 | R78: =DATEDIF($S$7,'AP01'!$B78,"Y") -> 37 | S78: =VLOOKUP('AP01'!$R78,SEGUROS!$A:$B,2,TRUE) -> 0.0002469 | T78: =('AP01'!$O78*'AP01'!$P78)*'AP01'!$S78 -> 63.492979 | U78: ='AP01'!$Q78*0.00899% -> 40.096414
A79: =A78+1 -> 65 | B79: =EDATE(B78,1) -> 45220 | C79: =C78 -> 0.1049 | D79: =((1+'AP01'!$C79)^(1/12))-1 -> 0.0083475509 | E79: =E78 -> 2171.3712 | F79: 2145.32 | G79: =(O78*'AP01'!$P79)/($I$5-A78) -> 868.24155 | H79: 49.22 | I79: 40.14 | J79: =J78 -> 25 | K79: =K78 -> 0 | L79: =L78 -> 0 | M79: =SUM('AP01'!$F79:$L79) -> 3127.9216 | N79: =O78*('AP01'!$P79-1) -> 295.20993 | O79: 256131.26 | P79: 1.00115 | Q79: =(Q78*'AP01'!$P79) -> 446524.2 | R79: =DATEDIF($S$7,'AP01'!$B79,"Y") -> 37 | S79: =VLOOKUP('AP01'!$R79,SEGUROS!$A:$B,2,TRUE) -> 0.0002469 | T79: =('AP01'!$O79*'AP01'!$P79)*'AP01'!$S79 -> 63.311533 | U79: ='AP01'!$Q79*0.00899% -> 40.142525
A80: =A79+1 -> 66 | B80: =EDATE(B79,1) -> 45251 | C80: =C79 -> 0.1049 | D80: =((1+'AP01'!$C80)^(1/12))-1 -> 0.0083475509 | E80: =E79 -> 2171.3712 | F80: 2139.13 | G80: =(O79*'AP01'!$P80)/($I$5-A79) -> 868.67308 | H80: 49.08 | I80: 40.16 | J80: =J79 -> 25 | K80: =K79 -> 0 | L80: =L79 -> 0 | M80: =SUM('AP01'!$F80:$L80) -> 3122.0431 | N80: =O79*('AP01'!$P80-1) -> 127.29724 | O80: 255389.89 | P80: 1.000497 | Q80: =(Q79*'AP01'!$P80) -> 446746.12 | R80: =DATEDIF($S$7,'AP01'!$B80,"Y") -> 37 | S80: =VLOOKUP('AP01'!$R80,SEGUROS!$A:$B,2,TRUE) -> 0.0002469 | T80: =('AP01'!$O80*'AP01'!$P80)*'AP01'!$S80 -> 63.087103 | U80: ='AP01'!$Q80*0.00899% -> 40.162476
A81: =A80+1 -> 67 | B81: =EDATE(B80,1) -> 45281 | C81: =C80 -> 0.1049 | D81: =((1+'AP01'!$C81)^(1/12))-1 -> 0.0083475509 | E81: =E80 -> 2171.3712 | F81: 2134.6 | G81: =(O80*'AP01'!$P81)/($I$5-A80) -> 869.78239 | H81: 50.82 | I81: 40.21 | J81: =J80 -> 25 | K81: =K80 -> 0 | L81: =L80 -> 0 | M81: =SUM('AP01'!$F81:$L81) -> 3120.4124 | N81: =O80*('AP01'!$P81-1) -> 326.13289 | O81: 254846.24 | P81: 1.001277 | Q81: =(Q80*'AP01'!$P81) -> 447316.61 | R81: =DATEDIF($S$7,'AP01'!$B81,"Y") -> 38 | S81: =VLOOKUP('AP01'!$R81,SEGUROS!$A:$B,2,TRUE) -> 0.0002632 | T81: =('AP01'!$O81*'AP01'!$P81)*'AP01'!$S81 -> 67.161186 | U81: ='AP01'!$Q81*0.00899% -> 40.213764
A82: =A81+1 -> 68 | B82: =EDATE(B81,1) -> 45312 | C82: =C81 -> 0.1049 | D82: =((1+'AP01'!$C82)^(1/12))-1 -> 0.0083475509 | E82: =E81 -> 2171.3712 | F82: 2128.33 | G82: =(O81*'AP01'!$P82)/($I$5-A81) -> 870.18597 | H82: 50.67 | I82: 40.23 | J82: =J81 -> 25 | K82: =K81 -> 0 | L82: =L81 -> 0 | M82: =SUM('AP01'!$F82:$L82) -> 3114.416 | N82: =O81*('AP01'!$P82-1) -> 118.24866 | O82: 254094.3 | P82: 1.000464 | Q82: =(Q81*'AP01'!$P82) -> 447524.17 | R82: =DATEDIF($S$7,'AP01'!$B82,"Y") -> 38 | S82: =VLOOKUP('AP01'!$R82,SEGUROS!$A:$B,2,TRUE) -> 0.0002632 | T82: =('AP01'!$O82*'AP01'!$P82)*'AP01'!$S82 -> 66.908651 | U82: ='AP01'!$Q82*0.00899% -> 40.232423
A83: =A82+1 -> 69 | B83: =EDATE(B82,1) -> 45343 | C83: =C82 -> 0.1049 | D83: =((1+'AP01'!$C83)^(1/12))-1 -> 0.0083475509 | E83: =E82 -> 2171.3712 | F83: 2121.86 | G83: =(O82*'AP01'!$P83)/($I$5-A82) -> 870.51402 | H83: 51.59 | I83: 40.25 | J83: =J82 -> 25 | K83: =K82 -> 0 | L83: =L82 -> 0 | M83: =SUM('AP01'!$F83:$L83) -> 3109.214 | N83: =O82*('AP01'!$P83-1) -> 95.793551 | O83: 253319.58 | P83: 1.000377 | Q83: =(Q82*'AP01'!$P83) -> 447692.88 | R83: =DATEDIF($S$7,'AP01'!$B83,"Y") -> 38 | S83: =VLOOKUP('AP01'!$R83,SEGUROS!$A:$B,2,TRUE) -> 0.0002632 | T83: =('AP01'!$O83*'AP01'!$P83)*'AP01'!$S83 -> 66.698849 | U83: ='AP01'!$Q83*0.00899% -> 40.24759
A84: =A83+1 -> 70 | B84: =EDATE(B83,1) -> 45372 | C84: =C83 -> 0.1049 | D84: =((1+'AP01'!$C84)^(1/12))-1 -> 0.0083475509 | E84: =E83 -> 2171.3712 | F84: 2115.97 | G84: =(O83*'AP01'!$P84)/($I$5-A83) -> 871.07811 | H84: 51.45 | I84: 40.27 | J84: =J83 -> 25 | K84: =K83 -> 0 | L84: =L83 -> 0 | M84: =SUM('AP01'!$F84:$L84) -> 3103.7681 | N84: =O83*('AP01'!$P84-1) -> 164.15109 | O84: 252612.65 | P84: 1.000648 | Q84: =(Q83*'AP01'!$P84) -> 447982.99 | R84: =DATEDIF($S$7,'AP01'!$B84,"Y") -> 38 | S84: =VLOOKUP('AP01'!$R84,SEGUROS!$A:$B,2,TRUE) -> 0.0002632 | T84: =('AP01'!$O84*'AP01'!$P84)*'AP01'!$S84 -> 66.530733 | U84: ='AP01'!$Q84*0.00899% -> 40.273671
A85: =A84+1 -> 71 | B85: =EDATE(B84,1) -> 45403 | C85: =C84 -> 0.1049 | D85: =((1+'AP01'!$C85)^(1/12))-1 -> 0.0083475509 | E85: =E84 -> 2171.3712 | F85: 2135.95 | G85: 882.33 | H85: 51.94 | I85: 40.3 | J85: =J84 -> 25 | K85: =K84 -> 0 | L85: =L84 -> 0 | M85: =SUM('AP01'!$F85:$L85) -> 3135.52 | N85: =O84*('AP01'!$P85-1) -> 158.64074 | O85: 254994.68 | P85: 1.000628 | Q85: =(Q84*'AP01'!$P85) -> 448264.32 | R85: =DATEDIF($S$7,'AP01'!$B85,"Y") -> 38 | S85: =VLOOKUP('AP01'!$R85,SEGUROS!$A:$B,2,TRUE) -> 0.0002632 | T85: =('AP01'!$O85*'AP01'!$P85)*'AP01'!$S85 -> 67.156748 | U85: ='AP01'!$Q85*0.00899% -> 40.298963
A86: =A85+1 -> 72 | B86: =EDATE(B85,1) -> 45433 | C86: =C85 -> 0.1049 | D86: =((1+'AP01'!$C86)^(1/12))-1 -> 0.0083475509 | E86: =E85 -> 2171.3712 | F86: 2155.54 | G86: 893.51 | H86: 52.41 | I86: 40.31 | J86: =J85 -> 25 | K86: 77.99 | L86: 733.09 | M86: =SUM('AP01'!$F86:$L86) -> 3977.85 | N86: =O85*('AP01'!$P86-1) -> 92.563069 | O86: 257330.39 | P86: 1.000363 | Q86: =(Q85*'AP01'!$P86) -> 448427.04 | R86: =DATEDIF($S$7,'AP01'!$B86,"Y") -> 38 | S86: =VLOOKUP('AP01'!$R86,SEGUROS!$A:$B,2,TRUE) -> 0.0002632 | T86: =('AP01'!$O86*'AP01'!$P86)*'AP01'!$S86 -> 67.753944 | U86: ='AP01'!$Q86*0.00899% -> 40.313591
A87: =A86+1 -> 73 | B87: =EDATE(B86,1) -> 45464 | C87: =C86 -> 0.1049 | D87: =((1+'AP01'!$C87)^(1/12))-1 -> 0.0083475509 | E87: =E86 -> 2171.3712 | F87: =(O86*'AP01'!$P87)*'AP01'!$D87 -> 2150.0569 | G87: =(O86*'AP01'!$P87)/($I$5-A86) -> 894.33122 | H87: 52.28 | I87: 40.35 | J87: =J86 -> 25 | K87: 76.44 | L87: =L86 -> 733.09 | M87: =SUM('AP01'!$F87:$L87) -> 3971.5481 | N87: =O86*('AP01'!$P87-1) -> 237.00129 | O87: =(O86*'AP01'!$P87)-'AP01'!$G87 -> 256673.06 | P87: 1.000921 | Q87: =(Q86*'AP01'!$P87) -> 448840.04 | R87: =DATEDIF($S$7,'AP01'!$B87,"Y") -> 38 | S87: =VLOOKUP('AP01'!$R87,SEGUROS!$A:$B,2,TRUE) -> 0.0002632 | T87: =('AP01'!$O87*'AP01'!$P87)*'AP01'!$S87 -> 67.618569 | U87: ='AP01'!$Q87*0.00899% -> 40.35072
A88: =A87+1 -> 74 | B88: =EDATE(B87,1) -> 45494 | C88: =C87 -> 0.1049 | D88: =((1+'AP01'!$C88)^(1/12))-1 -> 0.0083475509 | E88: =E87 -> 2171.3712 | F88: =(O87*'AP01'!$P88)*'AP01'!$D88 -> 2143.9905 | G88: =(O87*'AP01'!$P88)/($I$5-A87) -> 894.91522 | H88: 52.13 | I88: 40.38 | J88: =J87 -> 25 | K88: 74.94 | L88: =L87 -> 733.09 | M88: =SUM('AP01'!$F88:$L88) -> 3964.4458 | N88: =O87*('AP01'!$P88-1) -> 167.60751 | O88: =(O87*'AP01'!$P88)-'AP01'!$G88 -> 255945.75 | P88: 1.000653 | Q88: =(Q87*'AP01'!$P88) -> 449133.14 | R88: =DATEDIF($S$7,'AP01'!$B88,"Y") -> 38 | S88: =VLOOKUP('AP01'!$R88,SEGUROS!$A:$B,2,TRUE) -> 0.0002632 | T88: =('AP01'!$O88*'AP01'!$P88)*'AP01'!$S88 -> 67.408911 | U88: ='AP01'!$Q88*0.00899% -> 40.377069
A89: =A88+1 -> 75 | B89: =EDATE(B88,1) -> 45525 | C89: =C88 -> 0.1049 | D89: =((1+'AP01'!$C89)^(1/12))-1 -> 0.0083475509 | E89: =E88 -> 2171.3712 | F89: =(O88*'AP01'!$P89)*'AP01'!$D89 -> 2138.0328 | G89: =(O88*'AP01'!$P89)/($I$5-A88) -> 895.54882 | H89: 51.99 | I89: 40.41 | J89: =J88 -> 25 | K89: 73.44 | L89: =L88 -> 733.09 | M89: =SUM('AP01'!$F89:$L89) -> 3957.5117 | N89: =O88*('AP01'!$P89-1) -> 181.20959 | O89: =(O88*'AP01'!$P89)-'AP01'!$G89 -> 255231.41 | P89: 1.000708 | Q89: =(Q88*'AP01'!$P89) -> 449451.12 | R89: =DATEDIF($S$7,'AP01'!$B89,"Y") -> 38 | S89: =VLOOKUP('AP01'!$R89,SEGUROS!$A:$B,2,TRUE) -> 0.0002632 | T89: =('AP01'!$O89*'AP01'!$P89)*'AP01'!$S89 -> 67.224469 | U89: ='AP01'!$Q89*0.00899% -> 40.405656
A90: =A89+1 -> 76 | B90: =EDATE(B89,1) -> 45556 | C90: =C89 -> 0.1049 | D90: =((1+'AP01'!$C90)^(1/12))-1 -> 0.0083475509 | E90: =E89 -> 2171.3712 | F90: =(O89*'AP01'!$P90)*'AP01'!$D90 -> 2132.1445 | G90: =(O89*'AP01'!$P90)/($I$5-A89) -> 896.216 | H90: 51.84 | I90: 40.44 | J90: =J89 -> 25 | K90: 71.96 | L90: =L89 -> 733.09 | M90: =SUM('AP01'!$F90:$L90) -> 3950.6905 | N90: =O89*('AP01'!$P90-1) -> 190.1474 | O90: =(O89*'AP01'!$P90)-'AP01'!$G90 -> 254525.34 | P90: 1.000745 | Q90: =(Q89*'AP01'!$P90) -> 449785.96 | R90: =DATEDIF($S$7,'AP01'!$B90,"Y") -> 38 | S90: =VLOOKUP('AP01'!$R90,SEGUROS!$A:$B,2,TRUE) -> 0.0002632 | T90: =('AP01'!$O90*'AP01'!$P90)*'AP01'!$S90 -> 67.040979 | U90: ='AP01'!$Q90*0.00899% -> 40.435758
A91: =A90+1 -> 77 | B91: =EDATE(B90,1) -> 45586 | C91: =C90 -> 0.1049 | D91: =((1+'AP01'!$C91)^(1/12))-1 -> 0.0083475509 | E91: =E90 -> 2171.3712 | F91: =(O90*'AP01'!$P91)*'AP01'!$D91 -> 2126.0762 | G91: =(O90*'AP01'!$P91)/($I$5-A90) -> 896.81199 | H91: 51.7 | I91: 40.46 | J91: =J90 -> 25 | K91: 70.52 | L91: =L90 -> 733.09 | M91: =SUM('AP01'!$F91:$L91) -> 3943.6582 | N91: =O90*('AP01'!$P91-1) -> 169.25935 | O91: =(O90*'AP01'!$P91)-'AP01'!$G91 -> 253797.79 | P91: 1.000665 | Q91: =(Q90*'AP01'!$P91) -> 450085.07 | R91: =DATEDIF($S$7,'AP01'!$B91,"Y") -> 38 | S91: =VLOOKUP('AP01'!$R91,SEGUROS!$A:$B,2,TRUE) -> 0.0002632 | T91: =('AP01'!$O91*'AP01'!$P91)*'AP01'!$S91 -> 66.844001 | U91: ='AP01'!$Q91*0.00899% -> 40.462648
A92: =A91+1 -> 78 | B92: =EDATE(B91,1) -> 45617 | C92: =C91 -> 0.1049 | D92: =((1+'AP01'!$C92)^(1/12))-1 -> 0.0083475509 | E92: =E91 -> 2171.3712 | F92: =(O91*'AP01'!$P92)*'AP01'!$D92 -> 2120.1217 | G92: =(O91*'AP01'!$P92)/($I$5-A91) -> 897.46038 | H92: 51.55 | I92: 40.49 | J92: =J91 -> 25 | K92: 69.09 | L92: =L91 -> 733.09 | M92: =SUM('AP01'!$F92:$L92) -> 3936.8021 | N92: =O91*('AP01'!$P92-1) -> 183.4958 | O92: =(O91*'AP01'!$P92)-'AP01'!$G92 -> 253083.83 | P92: 1.000723 | Q92: =(Q91*'AP01'!$P92) -> 450410.48 | R92: =DATEDIF($S$7,'AP01'!$B92,"Y") -> 38 | S92: =VLOOKUP('AP01'!$R92,SEGUROS!$A:$B,2,TRUE) -> 0.0002632 | T92: =('AP01'!$O92*'AP01'!$P92)*'AP01'!$S92 -> 66.659824 | U92: ='AP01'!$Q92*0.00899% -> 40.491902
A93: =A92+1 -> 79 | B93: =EDATE(B92,1) -> 45647 | C93: =C92 -> 0.1049 | D93: =((1+'AP01'!$C93)^(1/12))-1 -> 0.0083475509 | E93: =E92 -> 2171.3712 | F93: =(O92*'AP01'!$P93)*'AP01'!$D93 -> 2114.7406 | G93: =(O92*'AP01'!$P93)/($I$5-A92) -> 898.35694 | H93: 53.67 | I93: 40.53 | J93: =J92 -> 25 | K93: 67.75 | L93: =L92 -> 733.09 | M93: =SUM('AP01'!$F93:$L93) -> 3933.1376 | N93: =O92*('AP01'!$P93-1) -> 252.83074 | O93: =(O92*'AP01'!$P93)-'AP01'!$G93 -> 252438.3 | P93: 1.000999 | Q93: =(Q92*'AP01'!$P93) -> 450860.44 | R93: =DATEDIF($S$7,'AP01'!$B93,"Y") -> 39 | S93: =VLOOKUP('AP01'!$R93,SEGUROS!$A:$B,2,TRUE) -> 0.0002832 | T93: =('AP01'!$O93*'AP01'!$P93)*'AP01'!$S93 -> 71.561946 | U93: ='AP01'!$Q93*0.00899% -> 40.532354
A94: =A93+1 -> 80 | B94: =EDATE(B93,1) -> 45678 | C94: =C93 -> 0.1049 | D94: =((1+'AP01'!$C94)^(1/12))-1 -> 0.0083475509 | E94: =E93 -> 2171.3712 | F94: =(O93*'AP01'!$P94)*'AP01'!$D94 -> 2108.9274 | G94: =(O93*'AP01'!$P94)/($I$5-A93) -> 899.07563 | H94: 53.52 | I94: 40.56 | J94: =J93 -> 25 | K94: 66.35 | L94: =L93 -> 733.09 | M94: =SUM('AP01'!$F94:$L94) -> 3926.523 | N94: =O93*('AP01'!$P94-1) -> 201.95064 | O94: =(O93*'AP01'!$P94)-'AP01'!$G94-0.01 -> 251741.17 | P94: 1.0008 | Q94: =(Q93*'AP01'!$P94) -> 451221.13 | R94: =DATEDIF($S$7,'AP01'!$B94,"Y") -> 39 | S94: =VLOOKUP('AP01'!$R94,SEGUROS!$A:$B,2,TRUE) -> 0.0002832 | T94: =('AP01'!$O94*'AP01'!$P94)*'AP01'!$S94 -> 71.350133 | U94: ='AP01'!$Q94*0.00899% -> 40.56478
A95: =A94+1 -> 81 | B95: =EDATE(B94,1) -> 45709 | C95: =C94 -> 0.1049 | D95: =((1+'AP01'!$C95)^(1/12))-1 -> 0.0083475509 | E95: =E94 -> 2171.3712 | F95: =(O94*'AP01'!$P95)*'AP01'!$D95 -> 2105.0198 | G95: =(O94*'AP01'!$P95)/($I$5-A94) -> 900.61481 | H95: 64.48 | I95: 40.63 | J95: =J94 -> 25 | K95: 65.21 | L95: =L94 -> 733.09 | M95: =SUM('AP01'!$F95:$L95) -> 3934.0446 | N95: =O94*('AP01'!$P95-1) -> 430.98088 | O95: =(O94*'AP01'!$P95)-'AP01'!$G95+0.01 -> 251271.54 | P95: 1.001712 | Q95: =(Q94*'AP01'!$P95) -> 451993.62 | R95: =DATEDIF($S$7,'AP01'!$B95,"Y") -> 39 | S95: =VLOOKUP('AP01'!$R95,SEGUROS!$A:$B,2,TRUE) -> 0.0002832 | T95: =('AP01'!$O95*'AP01'!$P95)*'AP01'!$S95 -> 71.281927 | U95: ='AP01'!$Q95*0.00899% -> 40.634227
A96: =A95+1 -> 82 | B96: =EDATE(B95,1) -> 45737 | C96: =C95 -> 0.1049 | D96: =((1+'AP01'!$C96)^(1/12))-1 -> 0.0083475509 | E96: =E95 -> 2171.3712 | F96: =(O95*'AP01'!$P96)*'AP01'!$D96 -> 2099.0604 | G96: =(O95*'AP01'!$P96)/($I$5-A95) -> 901.284 | H96: 64.3 | I96: 40.66 | J96: =J95 -> 25 | K96: 63.92 | L96: =L95 -> 733.09 | M96: =SUM('AP01'!$F96:$L96) -> 3927.3144 | N96: =O95*('AP01'!$P96-1) -> 186.69476 | O96: =(O95*'AP01'!$P96)-'AP01'!$G96 -> 250556.95 | P96: 1.000743 | Q96: =(Q95*'AP01'!$P96) -> 452329.45 | R96: =DATEDIF($S$7,'AP01'!$B96,"Y") -> 39 | S96: =VLOOKUP('AP01'!$R96,SEGUROS!$A:$B,2,TRUE) -> 0.0002832 | T96: =('AP01'!$O96*'AP01'!$P96)*'AP01'!$S96 -> 71.010451 | U96: ='AP01'!$Q96*0.00899% -> 40.664418
A97: =A96+1 -> 83 | B97: =EDATE(B96,1) -> 45768 | C97: =C96 -> 0.1049 | D97: =((1+'AP01'!$C97)^(1/12))-1 -> 0.0083475509 | E97: =E96 -> 2171.3712 | F97: =(O96*'AP01'!$P97)*'AP01'!$D97 -> 2095.0674 | G97: =(O96*'AP01'!$P97)/($I$5-A96) -> 902.80537 | H97: 64.18 | I97: 40.73 | J97: =J96 -> 25 | K97: 0 | L97: 0 | M97: =SUM('AP01'!$F97:$L97) -> 3127.7828 | N97: =O96*('AP01'!$P97-1) -> 422.94014 | O97: =(O96*'AP01'!$P97)-'AP01'!$G97-0.01 -> 250077.08 | P97: 1.001688 | Q97: =(Q96*'AP01'!$P97) -> 453092.99 | R97: =DATEDIF($S$7,'AP01'!$B97,"Y") -> 39 | S97: =VLOOKUP('AP01'!$R97,SEGUROS!$A:$B,2,TRUE) -> 0.0002832 | T97: =('AP01'!$O97*'AP01'!$P97)*'AP01'!$S97 -> 70.941376 | U97: ='AP01'!$Q97*0.00899% -> 40.733059 | W97: ='AP01'!$H97/(O96*'AP01'!$P97) -> 0.0002557177
A98: =A97+1 -> 84 | B98: =EDATE(B97,1) -> 45798 | C98: =C97 -> 0.1049 | D98: =((1+'AP01'!$C98)^(1/12))-1 -> 0.0083475509 | E98: =E97 -> 2171.3712 | F98: =(O97*'AP01'!$P98)*'AP01'!$D98 -> 2087.5311 | G98: =(O97*'AP01'!$P98)/($I$5-A97) -> 902.80533 | H98: =(O97*'AP01'!$P98)*$W$97 -> 63.949134 | I98: ='AP01'!$Q98*0.00899% -> 40.733059 | J98: =J97 -> 25 | K98: =K97 -> 0 | L98: =L97 -> 0 | M98: =SUM('AP01'!$F98:$L98) -> 3120.0187 | N98: =O97*('AP01'!$P98-1) -> 0 | O98: =(O97*'AP01'!$P98)-'AP01'!$G98 -> 249174.27 | P98: 1 | Q98: =(Q97*'AP01'!$P98) -> 453092.99 | R98: =DATEDIF($S$7,'AP01'!$B98,"Y") -> 39 | S98: =VLOOKUP('AP01'!$R98,SEGUROS!$A:$B,2,TRUE) -> 0.0002832 | T98: =('AP01'!$O98*'AP01'!$P98)*'AP01'!$S98 -> 70.566154 | U98: ='AP01'!$Q98*0.00899% -> 40.733059
A99: =A98+1 -> 85 | B99: =EDATE(B98,1) -> 45829 | C99: =C98 -> 0.1049 | D99: =((1+'AP01'!$C99)^(1/12))-1 -> 0.0083475509 | E99: =E98 -> 2171.3712 | F99: =(O98*'AP01'!$P99)*'AP01'!$D99 -> 2079.9949 | G99: =(O98*'AP01'!$P99)/($I$5-A98) -> 902.80533 | H99: =(O98*'AP01'!$P99)*$W$97 -> 63.718271 | I99: ='AP01'!$Q99*0.00899% -> 40.733059 | J99: =J98 -> 25 | K99: =K98 -> 0 | L99: =L98 -> 0 | M99: =SUM('AP01'!$F99:$L99) -> 3112.2516 | N99: =O98*('AP01'!$P99-1) -> 0 | O99: =(O98*'AP01'!$P99)-'AP01'!$G99 -> 248271.47 | P99: =P98 -> 1 | Q99: =(Q98*'AP01'!$P99) -> 453092.99 | R99: =DATEDIF($S$7,'AP01'!$B99,"Y") -> 39 | S99: =VLOOKUP('AP01'!$R99,SEGUROS!$A:$B,2,TRUE) -> 0.0002832 | T99: =('AP01'!$O99*'AP01'!$P99)*'AP01'!$S99 -> 70.310479 | U99: ='AP01'!$Q99*0.00899% -> 40.733059
A100: =A99+1 -> 86 | B100: =EDATE(B99,1) -> 45859 | C100: =C99 -> 0.1049 | D100: =((1+'AP01'!$C100)^(1/12))-1 -> 0.0083475509 | E100: =E99 -> 2171.3712 | F100: =(O99*'AP01'!$P100)*'AP01'!$D100 -> 2072.4587 | G100: =(O99*'AP01'!$P100)/($I$5-A99) -> 902.80533 | H100: =(O99*'AP01'!$P100)*$W$97 -> 63.487408 | I100: ='AP01'!$Q100*0.00899% -> 40.733059 | J100: =J99 -> 25 | K100: =K99 -> 0 | L100: =L99 -> 0 | M100: =SUM('AP01'!$F100:$L100) -> 3104.4845 | N100: =O99*('AP01'!$P100-1) -> 0 | O100: =(O99*'AP01'!$P100)-'AP01'!$G100 -> 247368.66 | P100: =P99 -> 1 | Q100: =(Q99*'AP01'!$P100) -> 453092.99 | R100: =DATEDIF($S$7,'AP01'!$B100,"Y") -> 39 | S100: =VLOOKUP('AP01'!$R100,SEGUROS!$A:$B,2,TRUE) -> 0.0002832 | T100: =('AP01'!$O100*'AP01'!$P100)*'AP01'!$S100 -> 70.054805 | U100: ='AP01'!$Q100*0.00899% -> 40.733059
A101: =A100+1 -> 87 | B101: =EDATE(B100,1) -> 45890 | C101: =C100 -> 0.1049 | D101: =((1+'AP01'!$C101)^(1/12))-1 -> 0.0083475509 | E101: =E100 -> 2171.3712 | F101: =(O100*'AP01'!$P101)*'AP01'!$D101 -> 2064.9225 | G101: =(O100*'AP01'!$P101)/($I$5-A100) -> 902.80533 | H101: =(O100*'AP01'!$P101)*$W$97 -> 63.256544 | I101: ='AP01'!$Q101*0.00899% -> 40.733059 | J101: =J100 -> 25 | K101: =K100 -> 0 | L101: =L100 -> 0 | M101: =SUM('AP01'!$F101:$L101) -> 3096.7174 | N101: =O100*('AP01'!$P101-1) -> 0 | O101: =(O100*'AP01'!$P101)-'AP01'!$G101 -> 246465.86 | P101: =P100 -> 1 | Q101: =(Q100*'AP01'!$P101) -> 453092.99 | R101: =DATEDIF($S$7,'AP01'!$B101,"Y") -> 39 | S101: =VLOOKUP('AP01'!$R101,SEGUROS!$A:$B,2,TRUE) -> 0.0002832 | T101: =('AP01'!$O101*'AP01'!$P101)*'AP01'!$S101 -> 69.799131 | U101: ='AP01'!$Q101*0.00899% -> 40.733059 | X101: 51161.85
A102: =A101+1 -> 88 | B102: =EDATE(B101,1) -> 45921 | C102: =C101 -> 0.1049 | D102: =((1+'AP01'!$C102)^(1/12))-1 -> 0.0083475509 | E102: =E101 -> 2171.3712 | F102: =(O101*'AP01'!$P102)*'AP01'!$D102 -> 2057.3863 | G102: =(O101*'AP01'!$P102)/($I$5-A101) -> 902.80533 | H102: =(O101*'AP01'!$P102)*$W$97 -> 63.025681 | I102: ='AP01'!$Q102*0.00899% -> 40.733059 | J102: =J101 -> 25 | K102: =K101 -> 0 | L102: =L101 -> 0 | M102: =SUM('AP01'!$F102:$L102) -> 3088.9504 | N102: =O101*('AP01'!$P102-1) -> 0 | O102: =(O101*'AP01'!$P102)-'AP01'!$G102 -> 245563.05 | P102: =P101 -> 1 | Q102: =(Q101*'AP01'!$P102) -> 453092.99 | R102: =DATEDIF($S$7,'AP01'!$B102,"Y") -> 39 | S102: =VLOOKUP('AP01'!$R102,SEGUROS!$A:$B,2,TRUE) -> 0.0002832 | T102: =('AP01'!$O102*'AP01'!$P102)*'AP01'!$S102 -> 69.543456 | U102: ='AP01'!$Q102*0.00899% -> 40.733059 | X102: 7.8e-05
A103: =A102+1 -> 89 | B103: =EDATE(B102,1) -> 45951 | C103: =C102 -> 0.1049 | D103: =((1+'AP01'!$C103)^(1/12))-1 -> 0.0083475509 | E103: =E102 -> 2171.3712 | F103: =(O102*'AP01'!$P103)*'AP01'!$D103 -> 2049.8501 | G103: =(O102*'AP01'!$P103)/($I$5-A102) -> 902.80533 | H103: =(O102*'AP01'!$P103)*$W$97 -> 62.794818 | I103: ='AP01'!$Q103*0.00899% -> 40.733059 | J103: =J102 -> 25 | K103: =K102 -> 0 | L103: =L102 -> 0 | M103: =SUM('AP01'!$F103:$L103) -> 3081.1833 | N103: =O102*('AP01'!$P103-1) -> 0 | O103: =(O102*'AP01'!$P103)-'AP01'!$G103 -> 244660.25 | P103: =P102 -> 1 | Q103: =(Q102*'AP01'!$P103) -> 453092.99 | R103: =DATEDIF($S$7,'AP01'!$B103,"Y") -> 39 | S103: =VLOOKUP('AP01'!$R103,SEGUROS!$A:$B,2,TRUE) -> 0.0002832 | T103: =('AP01'!$O103*'AP01'!$P103)*'AP01'!$S103 -> 69.287782 | U103: ='AP01'!$Q103*0.00899% -> 40.733059 | X103: =X101*X102 -> 3.9906243
A104: =A103+1 -> 90 | B104: =EDATE(B103,1) -> 45982 | C104: =C103 -> 0.1049 | D104: =((1+'AP01'!$C104)^(1/12))-1 -> 0.0083475509 | E104: =E103 -> 2171.3712 | F104: =(O103*'AP01'!$P104)*'AP01'!$D104 -> 2042.3138 | G104: =(O103*'AP01'!$P104)/($I$5-A103) -> 902.80533 | H104: =(O103*'AP01'!$P104)*$W$97 -> 62.563954 | I104: ='AP01'!$Q104*0.00899% -> 40.733059 | J104: =J103 -> 25 | K104: =K103 -> 0 | L104: =L103 -> 0 | M104: =SUM('AP01'!$F104:$L104) -> 3073.4162 | N104: =O103*('AP01'!$P104-1) -> 0 | O104: =(O103*'AP01'!$P104)-'AP01'!$G104 -> 243757.44 | P104: =P103 -> 1 | Q104: =(Q103*'AP01'!$P104) -> 453092.99 | R104: =DATEDIF($S$7,'AP01'!$B104,"Y") -> 39 | S104: =VLOOKUP('AP01'!$R104,SEGUROS!$A:$B,2,TRUE) -> 0.0002832 | T104: =('AP01'!$O104*'AP01'!$P104)*'AP01'!$S104 -> 69.032107 | U104: ='AP01'!$Q104*0.00899% -> 40.733059
...

Sheet SEGUROS
A1: Idade | B1: Taxa DFI
A2: 21 | B2: 7.57e-05
A3: =A2+1 -> 22 | B3: 7.57e-05
A4: =A3+1 -> 23 | B4: 7.57e-05
A5: =A4+1 -> 24 | B5: 7.57e-05
A6: =A5+1 -> 25 | B6: 7.57e-05
A7: =A6+1 -> 26 | B7: 7.57e-05
A8: =A7+1 -> 27 | B8: 7.57e-05
A9: =A8+1 -> 28 | B9: 7.57e-05
A10: =A9+1 -> 29 | B10: 7.57e-05
A11: =A10+1 -> 30 | B11: 7.57e-05
A12: 31 | B12: 0.000134
A13: =A12+1 -> 32 | B13: 0.0001381
A14: =A13+1 -> 33 | B14: 0.0001423
A15: =A14+1 -> 34 | B15: 0.0001472
A16: =A15+1 -> 35 | B16: 0.0001548
A17: =A16+1 -> 36 | B17: 0.0002337
A18: =A17+1 -> 37 | B18: 0.0002469
A19: =A18+1 -> 38 | B19: 0.0002632
A20: =A19+1 -> 39 | B20: 0.0002832
A21: =A20+1 -> 40 | B21: 0.0003073
A22: =A21+1 -> 41 | B22: 0.0003179
A23: =A22+1 -> 42 | B23: 0.0003181
A24: =A23+1 -> 43 | B24: 0.0003525
... A61: =A60+1 -> 80 | B61: 0.0155781

Sheet TR
A1: Data | B1: Data fim | C1: 226 - Taxa referencial (TR) - % a.m.
A2: 43221 | B2: 43251 | C2: 0
A3: 43221 | B3: 43252 | C3: 0
A4: 43222 | B4: 43253 | C4: 0
A5: 43223 | B5: 43254 | C5: 0
A6: 43224 | B6: 43255 | C6: 0
A7: 43225 | B7: 43256 | C7: 0
A8: 43226 | B8: 43257 | C8: 0
A9: 43227 | B9: 43258 | C9: 0
A10: 43228 | B10: 43259 | C10: 0
A11: 43229 | B11: 43260 | C11: 0
A12: 43230 | B12: 43261 | C12: 0
A13: 43231 | B13: 43262 | C13: 0
... A2643: 45814 | B2643: 45844 | C2643: 0.17
A2644: Fonte | B2644: - | C2644: BCB-Demab

Sheet AP02
A1: APÊNDICE 02: EVOLUÇÃO DO FINANCIAMENTO COM TAXA MÉDIA E EXPURGO DOS SEGUROS
A3: ='AP01'!A3 -> Requerente: ADRIANA MELO DE OLIVEIRA
A4: ='AP01'!A4 -> Requerido: ITAÚ UNIBANCO
A5: Valor do Bem | D5: ='AP01'!D5 -> 432000 | F5: Qtde Prestações | I5: ='AP01'!I5 -> 360 | L5: Para calcular a prestação (a+j):
A6: Entrada/Descontos | D6: ='AP01'!D6 -> 129600 | F6: Taxa MÉDIA Efetiva (a.m.) | I6: 0.0062 | L6: 1. Calcule a amortização dividindo o valor financiado pela quantidade de prestações; | T6: OBS: muda quando começa o vencimento com a correção monetária. Neste caso basta atualizar primeiro o saldo utilizando a mesma fórmula.
A7: Valor Financiado | D7: =D5-D6 -> 302400 | F7: Taxa MÉDIA Efetiva (a.a.) | I7: 0.0775 | L7: A = | M7: Valor Financiado | N7: =D7/I5 -> 840 | O7: <= cálculo feito
A8: Data do Contrato | D8: ='AP01'!D8 -> 43241 | F8: Taxa de Juros Efetiva (a.a.) | I8: ='AP01'!I7 -> 0.117 | M8: Qtde Pmt´s
A9: 1° Vencimento | D9: ='AP01'!D9 -> 43272 | F9: (%) Excesso Taxa Média | I9: =(I8/I7)-1 -> 0.50967742 | L9: 2. Depois é só calcular os juros aplicando sobre o saldo financiado o percentual da taxa;
A10: Sistema de Amortização | D10: ='AP01'!D10 -> SAC | F10: Prestação Mensal | I10: ='AP01'!I10 -> 2549.8136 | L10: J = | M10: Saldo Devedor x i% | N10: =D7*I6 -> 1874.88 | O10: <= cálculo feito
A11: Índice Correção | D11: ='AP01'!D11 -> TR | F11: Enquadramento | I11: ='AP01'!I11 -> SFH | L11: Pmt = A + J | N11: =N7+N10 -> 2714.88
A13: Qtde | B13: Data Vencimento | C13: Taxa Efetiva a.a. | D13: Taxa Efetiva a.m. | E13: Prestação (a+j) | F13: Juros | G13: Amortização | H13: Seguro MIP | I13: Seguro DFI | J13: TCA | K13: Multa | L13: Mora | M13: Total da Parcela Devida | N13: Correção Monetária | O13: Saldo Devedor | P13: Índice Correção
A14: 0 | B14: =D8 -> 43241 | O14: =D7 -> 302400
A15: =A14+1 -> 1 | B15: =D9 -> 43272 | C15: 0.07 | D15: 0.005654 | E15: ='AP02'!$F15+'AP02'!$G15 -> 2549.7696 | F15: =(O14*'AP02'!$P15)*'AP02'!$D15 -> 1709.7696 | G15: =(O14*'AP02'!$P15)/($I$5-A14) -> 840 | H15: 0 | I15: 0 | J15: 25 | K15: 0 | L15: 0 | M15: =SUM('AP02'!$F15:$L15) -> 2574.7696 | N15: =O14*('AP02'!$P15-1) -> 0 | O15: =(O14*'AP02'!$P15)-'AP02'!$G15 -> 301560 | P15: 1
A16: =A15+1 -> 2 | B16: =EDATE(B15,1) -> 43302 | C16: =C15 -> 0.07 | D16: =D15 -> 0.005654 | E16: ='AP02'!$F16+'AP02'!$G16 -> 2545.0202 | F16: =(O15*'AP02'!$P16)*'AP02'!$D16 -> 1705.0202 | G16: =(O15*'AP02'!$P16)/($I$5-A15) -> 840 | H16: =H15 -> 0 | I16: =I15 -> 0 | J16: =J15 -> 25 | K16: =K15 -> 0 | L16: =L15 -> 0 | M16: =SUM('AP02'!$F16:$L16) -> 2570.0202 | N16: =O15*('AP02'!$P16-1) -> 0 | O16: =(O15*'AP02'!$P16)-'AP02'!$G16 -> 300720 | P16: =P15 -> 1
A17: =A16+1 -> 3 | B17: =EDATE(B16,1) -> 43333 | C17: =C16 -> 0.07 | D17: =D16 -> 0.005654 | E17: ='AP02'!$F17+'AP02'!$G17 -> 2540.2709 | F17: =(O16*'AP02'!$P17)*'AP02'!$D17 -> 1700.2709 | G17: =(O16*'AP02'!$P17)/($I$5-A16) -> 840 | H17: =H16 -> 0 | I17: =I16 -> 0 | J17: =J16 -> 25 | K17: =K16 -> 0 | L17: =L16 -> 0 | M17: =SUM('AP02'!$F17:$L17) -> 2565.2709 | N17: =O16*('AP02'!$P17-1) -> 0 | O17: =(O16*'AP02'!$P17)-'AP02'!$G17 -> 299880 | P17: =P16 -> 1
A18: =A17+1 -> 4 | B18: =EDATE(B17,1) -> 43364 | C18: =C17 -> 0.07 | D18: =D17 -> 0.005654 | E18: ='AP02'!$F18+'AP02'!$G18 -> 2535.5215 | F18: =(O17*'AP02'!$P18)*'AP02'!$D18 -> 1695.5215 | G18: =(O17*'AP02'!$P18)/($I$5-A17) -> 840 | H18: =H17 -> 0 | I18: =I17 -> 0 | J18: =J17 -> 25 | K18: =K17 -> 0 | L18: =L17 -> 0 | M18: =SUM('AP02'!$F18:$L18) -> 2560.5215 | N18: =O17*('AP02'!$P18-1) -> 0 | O18: =(O17*'AP02'!$P18)-'AP02'!$G18 -> 299040 | P18: =P17 -> 1
A19: =A18+1 -> 5 | B19: =EDATE(B18,1) -> 43394 | C19: =C18 -> 0.07 | D19: =D18 -> 0.005654 | E19: ='AP02'!$F19+'AP02'!$G19 -> 2530.7722 | F19: =(O18*'AP02'!$P19)*'AP02'!$D19 -> 1690.7722 | G19: =(O18*'AP02'!$P19)/($I$5-A18) -> 840 | H19: =H18 -> 0 | I19: =I18 -> 0 | J19: =J18 -> 25 | K19: =K18 -> 0 | L19: =L18 -> 0 | M19: =SUM('AP02'!$F19:$L19) -> 2555.7722 | N19: =O18*('AP02'!$P19-1) -> 0 | O19: =(O18*'AP02'!$P19)-'AP02'!$G19 -> 298200 | P19: =P18 -> 1
A20: =A19+1 -> 6 | B20: =EDATE(B19,1) -> 43425 | C20: =C19 -> 0.07 | D20: =D19 -> 0.005654 | E20: ='AP02'!$F20+'AP02'!$G20 -> 2526.0228 | F20: =(O19*'AP02'!$P20)*'AP02'!$D20 -> 1686.0228 | G20: =(O19*'AP02'!$P20)/($I$5-A19) -> 840 | H20: =H19 -> 0 | I20: =I19 -> 0 | J20: =J19 -> 25 | K20: =K19 -> 0 | L20: =L19 -> 0 | M20: =SUM('AP02'!$F20:$L20) -> 2551.0228 | N20: =O19*('AP02'!$P20-1) -> 0 | O20: =(O19*'AP02'!$P20)-'AP02'!$G20 -> 297360 | P20: =P19 -> 1
A21: =A20+1 -> 7 | B21: =EDATE(B20,1) -> 43455 | C21: =C20 -> 0.07 | D21: =D20 -> 0.005654 | E21: ='AP02'!$F21+'AP02'!$G21 -> 2521.2734 | F21: =(O20*'AP02'!$P21)*'AP02'!$D21 -> 1681.2734 | G21: =(O20*'AP02'!$P21)/($I$5-A20) -> 840 | H21: =H20 -> 0 | I21: =I20 -> 0 | J21: =J20 -> 25 | K21: =K20 -> 0 | L21: =L20 -> 0 | M21: =SUM('AP02'!$F21:$L21) -> 2546.2734 | N21: =O20*('AP02'!$P21-1) -> 0 | O21: =(O20*'AP02'!$P21)-'AP02'!$G21 -> 296520 | P21: =P20 -> 1
A22: =A21+1 -> 8 | B22: =EDATE(B21,1) -> 43486 | C22: =C21 -> 0.07 | D22: =D21 -> 0.005654 | E22: ='AP02'!$F22+'AP02'!$G22 -> 2516.5241 | F22: =(O21*'AP02'!$P22)*'AP02'!$D22 -> 1676.5241 | G22: =(O21*'AP02'!$P22)/($I$5-A21) -> 840 | H22: =H21 -> 0 | I22: =I21 -> 0 | J22: =J21 -> 25 | K22: =K21 -> 0 | L22: =L21 -> 0 | M22: =SUM('AP02'!$F22:$L22) -> 2541.5241 | N22: =O21*('AP02'!$P22-1) -> 0 | O22: =(O21*'AP02'!$P22)-'AP02'!$G22 -> 295680 | P22: =P21 -> 1
A23: =A22+1 -> 9 | B23: =EDATE(B22,1) -> 43517 | C23: =C22 -> 0.07 | D23: =D22 -> 0.005654 | E23: ='AP02'!$F23+'AP02'!$G23 -> 2511.7747 | F23: =(O22*'AP02'!$P23)*'AP02'!$D23 -> 1671.7747 | G23: =(O22*'AP02'!$P23)/($I$5-A22) -> 840 | H23: =H22 -> 0 | I23: =I22 -> 0 | J23: =J22 -> 25 | K23: =K22 -> 0 | L23: =L22 -> 0 | M23: =SUM('AP02'!$F23:$L23) -> 2536.7747 | N23: =O22*('AP02'!$P23-1) -> 0 | O23: =(O22*'AP02'!$P23)-'AP02'!$G23 -> 294840 | P23: =P22 -> 1
A24: =A23+1 -> 10 | B24: =EDATE(B23,1) -> 43545 | C24: =C23 -> 0.07 | D24: =D23 -> 0.005654 | E24: ='AP02'!$F24+'AP02'!$G24 -> 2507.0254 | F24: =(O23*'AP02'!$P24)*'AP02'!$D24 -> 1667.0254 | G24: =(O23*'AP02'!$P24)/($I$5-A23) -> 840 | H24: =H23 -> 0 | I24: =I23 -> 0 | J24: =J23 -> 25 | K24: =K23 -> 0 | L24: =L23 -> 0 | M24: =SUM('AP02'!$F24:$L24) -> 2532.0254 | N24: =O23*('AP02'!$P24-1) -> 0 | O24: =(O23*'AP02'!$P24)-'AP02'!$G24 -> 294000 | P24: =P23 -> 1
A25: =A24+1 -> 11 | B25: =EDATE(B24,1) -> 43576 | C25: =C24 -> 0.07 | D25: =D24 -> 0.005654 | E25: ='AP02'!$F25+'AP02'!$G25 -> 2502.276 | F25: =(O24*'AP02'!$P25)*'AP02'!$D25 -> 1662.276 | G25: =(O24*'AP02'!$P25)/($I$5-A24) -> 840 | H25: =H24 -> 0 | I25: =I24 -> 0 | J25: =J24 -> 25 | K25: =K24 -> 0 | L25: =L24 -> 0 | M25: =SUM('AP02'!$F25:$L25) -> 2527.276 | N25: =O24*('AP02'!$P25-1) -> 0 | O25: =(O24*'AP02'!$P25)-'AP02'!$G25 -> 293160 | P25: =P24 -> 1
A26: =A25+1 -> 12 | B26: =EDATE(B25,1) -> 43606 | C26: =C25 -> 0.07 | D26: =D25 -> 0.005654 | E26: ='AP02'!$F26+'AP02'!$G26 -> 2497.5266 | F26: =(O25*'AP02'!$P26)*'AP02'!$D26 -> 1657.5266 | G26: =(O25*'AP02'!$P26)/($I$5-A25) -> 840 | H26: =H25 -> 0 | I26: =I25 -> 0 | J26: =J25 -> 25 | K26: =K25 -> 0 | L26: =L25 -> 0 | M26: =SUM('AP02'!$F26:$L26) -> 2522.5266 | N26: =O25*('AP02'!$P26-1) -> 0 | O26: =(O25*'AP02'!$P26)-'AP02'!$G26 -> 292320 | P26: =P25 -> 1
A27: =A26+1 -> 13 | B27: =EDATE(B26,1) -> 43637 | C27: =C26 -> 0.07 | D27: =D26 -> 0.005654 | E27: ='AP02'!$F27+'AP02'!$G27 -> 2492.7773 | F27: =(O26*'AP02'!$P27)*'AP02'!$D27 -> 1652.7773 | G27: =(O26*'AP02'!$P27)/($I$5-A26) -> 840 | H27: =H26 -> 0 | I27: =I26 -> 0 | J27: =J26 -> 25 | K27: =K26 -> 0 | L27: =L26 -> 0 | M27: =SUM('AP02'!$F27:$L27) -> 2517.7773 | N27: =O26*('AP02'!$P27-1) -> 0 | O27: =(O26*'AP02'!$P27)-'AP02'!$G27 -> 291480 | P27: =P26 -> 1
... A35: =A34+1 -> 21 | B35: =EDATE(B34,1) -> 43882 | C35: =C34 -> 0.07 | D35: =D34 -> 0.005654 | E35: ='AP02'!$F35+'AP02'!$G35 -> 2454.7824 | F35: =(O34*'AP02'!$P35)*'AP02'!$D35 -> 1614.7824 | G35: =(O34*'AP02'!$P35)/($I$5-A34) -> 840 | H35: =H34 -> 0 | I35: =I34 -> 0 | J35: =J34 -> 25 | K35: =K34 -> 0 | L35: =L34 -> 0 | M35: =SUM('AP02'!$F35:$L35) -> 2479.7824 | N35: =O34*('AP02'!$P35-1) -> 0 | O35: =(O34*'AP02'!$P35)-'AP02'!$G35 -> 284760 | P35: =P34 -> 1
A36: =A35+1 -> 22 | B36: =EDATE(B35,1) -> 43911 | C36: 0.062 | D36: 0.005025 | E36: ='AP02'!$F36+'AP02'!$G36 -> 2270.919 | F36: =(O35*'AP02'!$P36)*'AP02'!$D36 -> 1430.919 | G36: =(O35*'AP02'!$P36)/($I$5-A35) -> 840 | H36: =H35 -> 0 | I36: =I35 -> 0 | J36: =J35 -> 25 | K36: =K35 -> 0 | L36: =L35 -> 0 | M36: =SUM('AP02'!$F36:$L36) -> 2295.919 | N36: =O35*('AP02'!$P36-1) -> 0 | O36: =(O35*'AP02'!$P36)-'AP02'!$G36 -> 283920 | P36: =P35 -> 1
A37: =A36+1 -> 23 | B37: =EDATE(B36,1) -> 43942 | C37: 0.062 | D37: =D36 -> 0.005025 | E37: ='AP02'!$F37+'AP02'!$G37 -> 2266.698 | F37: =(O36*'AP02'!$P37)*'AP02'!$D37 -> 1426.698 | G37: =(O36*'AP02'!$P37)/($I$5-A36) -> 840 | H37: =H36 -> 0 | I37: =I36 -> 0 | J37: =J36 -> 25 | K37: =K36 -> 0 | L37: =L36 -> 0 | M37: =SUM('AP02'!$F37:$L37) -> 2291.698 | N37: =O36*('AP02'!$P37-1) -> 0 | O37: =(O36*'AP02'!$P37)-'AP02'!$G37 -> 283080 | P37: =P36 -> 1
A38: =A37+1 -> 24 | B38: =EDATE(B37,1) -> 43972 | C38: 0.062 | D38: =D37 -> 0.005025 | E38: ='AP02'!$F38+'AP02'!$G38 -> 2262.477 | F38: =(O37*'AP02'!$P38)*'AP02'!$D38 -> 1422.477 | G38: =(O37*'AP02'!$P38)/($I$5-A37) -> 840 | H38: =H37 -> 0 | I38: =I37 -> 0 | J38: =J37 -> 25 | K38: =K37 -> 0 | L38: =L37 -> 0 | M38: =SUM('AP02'!$F38:$L38) -> 2287.477 | N38: =O37*('AP02'!$P38-1) -> 0 | O38: =(O37*'AP02'!$P38)-'AP02'!$G38 -> 282240 | P38: =P37 -> 1
A39: =A38+1 -> 25 | B39: =EDATE(B38,1) -> 44003 | C39: 0.062 | D39: =D38 -> 0.005025 | E39: ='AP02'!$F39+'AP02'!$G39 -> 2258.256 | F39: =(O38*'AP02'!$P39)*'AP02'!$D39 -> 1418.256 | G39: =(O38*'AP02'!$P39)/($I$5-A38) -> 840 | H39: =H38 -> 0 | I39: =I38 -> 0 | J39: =J38 -> 25 | K39: =K38 -> 0 | L39: =L38 -> 0 | M39: =SUM('AP02'!$F39:$L39) -> 2283.256 | N39: =O38*('AP02'!$P39-1) -> 0 | O39: =(O38*'AP02'!$P39)-'AP02'!$G39 -> 281400 | P39: =P38 -> 1
A40: =A39+1 -> 26 | B40: =EDATE(B39,1) -> 44033 | C40: 0.062 | D40: =D39 -> 0.005025 | E40: ='AP02'!$F40+'AP02'!$G40 -> 2254.035 | F40: =(O39*'AP02'!$P40)*'AP02'!$D40 -> 1414.035 | G40: =(O39*'AP02'!$P40)/($I$5-A39) -> 840 | H40: =H39 -> 0 | I40: =I39 -> 0 | J40: =J39 -> 25 | K40: =K39 -> 0 | L40: =L39 -> 0 | M40: =SUM('AP02'!$F40:$L40) -> 2279.035 | N40: =O39*('AP02'!$P40-1) -> 0 | O40: =(O39*'AP02'!$P40)-'AP02'!$G40 -> 280560 | P40: =P39 -> 1
A41: =A40+1 -> 27 | B41: =EDATE(B40,1) -> 44064 | C41: 0.062 | D41: =D40 -> 0.005025 | E41: ='AP02'!$F41+'AP02'!$G41 -> 2249.814 | F41: =(O40*'AP02'!$P41)*'AP02'!$D41 -> 1409.814 | G41: =(O40*'AP02'!$P41)/($I$5-A40) -> 840 | H41: =H40 -> 0 | I41: =I40 -> 0 | J41: =J40 -> 25 | K41: =K40 -> 0 | L41: =L40 -> 0 | M41: =SUM('AP02'!$F41:$L41) -> 2274.814 | N41: =O40*('AP02'!$P41-1) -> 0 | O41: =(O40*'AP02'!$P41)-'AP02'!$G41 -> 279720 | P41: =P40 -> 1
A42: =A41+1 -> 28 | B42: =EDATE(B41,1) -> 44095 | C42: =C41 -> 0.062 | D42: =D41 -> 0.005025 | E42: ='AP02'!$F42+'AP02'!$G42 -> 2245.593 | F42: =(O41*'AP02'!$P42)*'AP02'!$D42 -> 1405.593 | G42: =(O41*'AP02'!$P42)/($I$5-A41) -> 840 | H42: =H41 -> 0 | I42: =I41 -> 0 | J42: =J41 -> 25 | K42: =K41 -> 0 | L42: =L41 -> 0 | M42: =SUM('AP02'!$F42:$L42) -> 2270.593 | N42: =O41*('AP02'!$P42-1) -> 0 | O42: =(O41*'AP02'!$P42)-'AP02'!$G42 -> 278880 | P42: =P41 -> 1
A43: =A42+1 -> 29 | B43: =EDATE(B42,1) -> 44125 | C43: =C42 -> 0.062 | D43: =D42 -> 0.005025 | E43: ='AP02'!$F43+'AP02'!$G43 -> 2241.372 | F43: =(O42*'AP02'!$P43)*'AP02'!$D43 -> 1401.372 | G43: =(O42*'AP02'!$P43)/($I$5-A42) -> 840 | H43: =H42 -> 0 | I43: =I42 -> 0 | J43: =J42 -> 25 | K43: =K42 -> 0 | L43: =L42 -> 0 | M43: =SUM('AP02'!$F43:$L43) -> 2266.372 | N43: =O42*('AP02'!$P43-1) -> 0 | O43: =(O42*'AP02'!$P43)-'AP02'!$G43 -> 278040 | P43: =P42 -> 1
A44: =A43+1 -> 30 | B44: =EDATE(B43,1) -> 44156 | C44: =C43 -> 0.062 | D44: =D43 -> 0.005025 | E44: ='AP02'!$F44+'AP02'!$G44 -> 2237.151 | F44: =(O43*'AP02'!$P44)*'AP02'!$D44 -> 1397.151 | G44: =(O43*'AP02'!$P44)/($I$5-A43) -> 840 | H44: =H43 -> 0 | I44: =I43 -> 0 | J44: =J43 -> 25 | K44: =K43 -> 0 | L44: =L43 -> 0 | M44: =SUM('AP02'!$F44:$L44) -> 2262.151 | N44: =O43*('AP02'!$P44-1) -> 0 | O44: =(O43*'AP02'!$P44)-'AP02'!$G44 -> 277200 | P44: =P43 -> 1
A45: =A44+1 -> 31 | B45: =EDATE(B44,1) -> 44186 | C45: =C44 -> 0.062 | D45: =D44 -> 0.005025 | E45: ='AP02'!$F45+'AP02'!$G45 -> 2232.93 | F45: =(O44*'AP02'!$P45)*'AP02'!$D45 -> 1392.93 | G45: =(O44*'AP02'!$P45)/($I$5-A44) -> 840 | H45: =H44 -> 0 | I45: =I44 -> 0 | J45: =J44 -> 25 | K45: =K44 -> 0 | L45: =L44 -> 0 | M45: =SUM('AP02'!$F45:$L45) -> 2257.93 | N45: =O44*('AP02'!$P45-1) -> 0 | O45: =(O44*'AP02'!$P45)-'AP02'!$G45 -> 276360 | P45: =P44 -> 1
A46: =A45+1 -> 32 | B46: =EDATE(B45,1) -> 44217 | C46: =C45 -> 0.062 | D46: =D45 -> 0.005025 | E46: ='AP02'!$F46+'AP02'!$G46 -> 2228.709 | F46: =(O45*'AP02'!$P46)*'AP02'!$D46 -> 1388.709 | G46: =(O45*'AP02'!$P46)/($I$5-A45) -> 840 | H46: =H45 -> 0 | I46: =I45 -> 0 | J46: =J45 -> 25 | K46: =K45 -> 0 | L46: =L45 -> 0 | M46: =SUM('AP02'!$F46:$L46) -> 2253.709 | N46: =O45*('AP02'!$P46-1) -> 0 | O46: =(O45*'AP02'!$P46)-'AP02'!$G46 -> 275520 | P46: =P45 -> 1
A47: =A46+1 -> 33 | B47: =EDATE(B46,1) -> 44248 | C47: =C46 -> 0.062 | D47: =D46 -> 0.005025 | E47: ='AP02'!$F47+'AP02'!$G47 -> 2224.488 | F47: =(O46*'AP02'!$P47)*'AP02'!$D47 -> 1384.488 | G47: =(O46*'AP02'!$P47)/($I$5-A46) -> 840 | H47: =H46 -> 0 | I47: =I46 -> 0 | J47: =J46 -> 25 | K47: =K46 -> 0 | L47: =L46 -> 0 | M47: =SUM('AP02'!$F47:$L47) -> 2249.488 | N47: =O46*('AP02'!$P47-1) -> 0 | O47: =(O46*'AP02'!$P47)-'AP02'!$G47 -> 274680 | P47: =P46 -> 1
A48: =A47+1 -> 34 | B48: =EDATE(B47,1) -> 44276 | C48: =C47 -> 0.062 | D48: =D47 -> 0.005025 | E48: ='AP02'!$F48+'AP02'!$G48 -> 2220.267 | F48: =(O47*'AP02'!$P48)*'AP02'!$D48 -> 1380.267 | G48: =(O47*'AP02'!$P48)/($I$5-A47) -> 840 | H48: =H47 -> 0 | I48: =I47 -> 0 | J48: =J47 -> 25 | K48: =K47 -> 0 | L48: =L47 -> 0 | M48: =SUM('AP02'!$F48:$L48) -> 2245.267 | N48: =O47*('AP02'!$P48-1) -> 0 | O48: =(O47*'AP02'!$P48)-'AP02'!$G48 -> 273840 | P48: =P47 -> 1
A49: =A48+1 -> 35 | B49: =EDATE(B48,1) -> 44307 | C49: =C48 -> 0.062 | D49: =D48 -> 0.005025 | E49: ='AP02'!$F49+'AP02'!$G49 -> 2216.046 | F49: =(O48*'AP02'!$P49)*'AP02'!$D49 -> 1376.046 | G49: =(O48*'AP02'!$P49)/($I$5-A48) -> 840 | H49: =H48 -> 0 | I49: =I48 -> 0 | J49: =J48 -> 25 | K49: =K48 -> 0 | L49: =L48 -> 0 | M49: =SUM('AP02'!$F49:$L49) -> 2241.046 | N49: =O48*('AP02'!$P49-1) -> 0 | O49: =(O48*'AP02'!$P49)-'AP02'!$G49 -> 273000 | P49: =P48 -> 1
A50: =A49+1 -> 36 | B50: =EDATE(B49,1) -> 44337 | C50: =C49 -> 0.062 | D50: =D49 -> 0.005025 | E50: ='AP02'!$F50+'AP02'!$G50 -> 2211.825 | F50: =(O49*'AP02'!$P50)*'AP02'!$D50 -> 1371.825 | G50: =(O49*'AP02'!$P50)/($I$5-A49) -> 840 | H50: =H49 -> 0 | I50: =I49 -> 0 | J50: =J49 -> 25 | K50: =K49 -> 0 | L50: =L49 -> 0 | M50: =SUM('AP02'!$F50:$L50) -> 2236.825 | N50: =O49*('AP02'!$P50-1) -> 0 | O50: =(O49*'AP02'!$P50)-'AP02'!$G50 -> 272160 | P50: =P49 -> 1
A51: =A50+1 -> 37 | B51: =EDATE(B50,1) -> 44368 | C51: =C50 -> 0.062 | D51: =D50 -> 0.005025 | E51: ='AP02'!$F51+'AP02'!$G51 -> 2207.604 | F51: =(O50*'AP02'!$P51)*'AP02'!$D51 -> 1367.604 | G51: =(O50*'AP02'!$P51)/($I$5-A50) -> 840 | H51: =H50 -> 0 | I51: =I50 -> 0 | J51: =J50 -> 25 | K51: =K50 -> 0 | L51: =L50 -> 0 | M51: =SUM('AP02'!$F51:$L51) -> 2232.604 | N51: =O50*('AP02'!$P51-1) -> 0 | O51: =(O50*'AP02'!$P51)-'AP02'!$G51 -> 271320 | P51: =P50 -> 1
A52: =A51+1 -> 38 | B52: =EDATE(B51,1) -> 44398 | C52: =C51 -> 0.062 | D52: =D51 -> 0.005025 | E52: ='AP02'!$F52+'AP02'!$G52 -> 2203.383 | F52: =(O51*'AP02'!$P52)*'AP02'!$D52 -> 1363.383 | G52: =(O51*'AP02'!$P52)/($I$5-A51) -> 840 | H52: =H51 -> 0 | I52: =I51 -> 0 | J52: =J51 -> 25 | K52: =K51 -> 0 | L52: =L51 -> 0 | M52: =SUM('AP02'!$F52:$L52) -> 2228.383 | N52: =O51*('AP02'!$P52-1) -> 0 | O52: =(O51*'AP02'!$P52)-'AP02'!$G52 -> 270480 | P52: =P51 -> 1
A53: =A52+1 -> 39 | B53: =EDATE(B52,1) -> 44429 | C53: =C52 -> 0.062 | D53: =D52 -> 0.005025 | E53: ='AP02'!$F53+'AP02'!$G53 -> 2199.162 | F53: =(O52*'AP02'!$P53)*'AP02'!$D53 -> 1359.162 | G53: =(O52*'AP02'!$P53)/($I$5-A52) -> 840 | H53: =H52 -> 0 | I53: =I52 -> 0 | J53: =J52 -> 25 | K53: =K52 -> 0 | L53: =L52 -> 0 | M53: =SUM('AP02'!$F53:$L53) -> 2224.162 | N53: =O52*('AP02'!$P53-1) -> 0 | O53: =(O52*'AP02'!$P53)-'AP02'!$G53 -> 269640 | P53: =P52 -> 1
... A57: =A56+1 -> 43 | B57: =EDATE(B56,1) -> 44551 | C57: =C56 -> 0.062 | D57: =D56 -> 0.005025 | E57: ='AP02'!$F57+'AP02'!$G57 -> 2182.278 | F57: =(O56*'AP02'!$P57)*'AP02'!$D57 -> 1342.278 | G57: =(O56*'AP02'!$P57)/($I$5-A56) -> 840 | H57: =H56 -> 0 | I57: =I56 -> 0 | J57: =J56 -> 25 | K57: =K56 -> 0 | L57: =L56 -> 0 | M57: =SUM('AP02'!$F57:$L57) -> 2207.278 | N57: =O56*('AP02'!$P57-1) -> 0 | O57: =(O56*'AP02'!$P57)-'AP02'!$G57 -> 266280 | P57: =P56 -> 1
A58: =A57+1 -> 44 | B58: =EDATE(B57,1) -> 44582 | C58: =C57 -> 0.062 | D58: =D57 -> 0.005025 | E58: ='AP02'!$F58+'AP02'!$G58 -> 2180.6598 | F58: =(O57*'AP02'!$P58)*'AP02'!$D58 -> 1339.656 | G58: =(O57*'AP02'!$P58)/($I$5-A57) -> 841.0038 | H58: =H57 -> 0 | I58: =I57 -> 0 | J58: =J57 -> 25 | K58: =K57 -> 0 | L58: =L57 -> 0 | M58: =SUM('AP02'!$F58:$L58) -> 2205.6598 | N58: =O57*('AP02'!$P58-1) -> 318.2046 | O58: =(O57*'AP02'!$P58)-'AP02'!$G58 -> 265757.2 | P58: 1.001195
A59: =A58+1 -> 45 | B59: =EDATE(B58,1) -> 44613 | C59: =C58 -> 0.062 | D59: =D58 -> 0.005025 | E59: ='AP02'!$F59+'AP02'!$G59 -> 2178.2641 | F59: =(O58*'AP02'!$P59)*'AP02'!$D59 -> 1336.553 | G59: =(O58*'AP02'!$P59)/($I$5-A58) -> 841.71108 | H59: =H58 -> 0 | I59: =I58 -> 0 | J59: =J58 -> 25 | K59: =K58 -> 0 | L59: =L58 -> 0 | M59: =SUM('AP02'!$F59:$L59) -> 2203.2641 | N59: =O58*('AP02'!$P59-1) -> 223.50181 | O59: =(O58*'AP02'!$P59)-'AP02'!$G59 -> 265138.99 | P59: 1.000841
A60: =A59+1 -> 46 | B60: =EDATE(B59,1) -> 44641 | C60: =C59 -> 0.062 | D60: =D59 -> 0.005025 | E60: ='AP02'!$F60+'AP02'!$G60 -> 2174.0345 | F60: =(O59*'AP02'!$P60)*'AP02'!$D60 -> 1332.3234 | G60: =(O59*'AP02'!$P60)/($I$5-A59) -> 841.71108 | H60: =H59 -> 0 | I60: =I59 -> 0 | J60: =J59 -> 25 | K60: =K59 -> 0 | L60: =L59 -> 0 | M60: =SUM('AP02'!$F60:$L60) -> 2199.0345 | N60: =O59*('AP02'!$P60-1) -> 0 | O60: =(O59*'AP02'!$P60)-'AP02'!$G60 -> 264297.28 | P60: 1
A61: =A60+1 -> 47 | B61: =EDATE(B60,1) -> 44672 | C61: =C60 -> 0.062 | D61: =D60 -> 0.005025 | E61: ='AP02'!$F61+'AP02'!$G61 -> 2172.6734 | F61: =(O60*'AP02'!$P61)*'AP02'!$D61 -> 1329.8496 | G61: =(O60*'AP02'!$P61)/($I$5-A60) -> 842.82383 | H61: =H60 -> 0 | I61: =I60 -> 0 | J61: =J60 -> 25 | K61: =K60 -> 0 | L61: =L60 -> 0 | M61: =SUM('AP02'!$F61:$L61) -> 2197.6734 | N61: =O60*('AP02'!$P61-1) -> 349.401 | O61: =(O60*'AP02'!$P61)-'AP02'!$G61 -> 263803.86 | P61: 1.001322
A62: =A61+1 -> 48 | B62: =EDATE(B61,1) -> 44702 | C62: =C61 -> 0.062 | D62: =D61 -> 0.005025 | E62: ='AP02'!$F62+'AP02'!$G62 -> 2171.2615 | F62: =(O61*'AP02'!$P62)*'AP02'!$D62 -> 1327.3403 | G62: =(O61*'AP02'!$P62)/($I$5-A61) -> 843.92118 | H62: =H61 -> 0 | I62: =I61 -> 0 | J62: =J61 -> 25 | K62: =K61 -> 0 | L62: =L61 -> 0 | M62: =SUM('AP02'!$F62:$L62) -> 2196.2615 | N62: =O61*('AP02'!$P62-1) -> 343.47262 | O62: =(O61*'AP02'!$P62)-'AP02'!$G62 -> 263303.41 | P62: 1.001302
A63: =A62+1 -> 49 | B63: =EDATE(B62,1) -> 44733 | C63: =C62 -> 0.062 | D63: =D62 -> 0.005025 | E63: =E62 -> 2171.2615 | F63: =(O62*'AP02'!$P63)*'AP02'!$D63 -> 1324.5048 | G63: =(O62*'AP02'!$P63)/($I$5-A62) -> 844.81743 | H63: =H62 -> 0 | I63: =I62 -> 0 | J63: =J62 -> 25 | K63: =K62 -> 0 | L63: =L62 -> 0 | M63: =SUM('AP02'!$F63:$L63) -> 2194.3222 | N63: =O62*('AP02'!$P63-1) -> 279.62822 | O63: =(O62*'AP02'!$P63)-'AP02'!$G63 -> 262738.22 | P63: 1.001062
A64: =A63+1 -> 50 | B64: =EDATE(B63,1) -> 44763 | C64: =C63 -> 0.062 | D64: =D63 -> 0.005025 | E64: =E63 -> 2171.2615 | F64: =(O63*'AP02'!$P64)*'AP02'!$D64 -> 1322.7984 | G64: =(O63*'AP02'!$P64)/($I$5-A63) -> 846.44201 | H64: =H63 -> 0 | I64: =I63 -> 0 | J64: =J63 -> 25 | K64: =K63 -> 0 | L64: =L63 -> 0 | M64: =SUM('AP02'!$F64:$L64) -> 2194.2404 | N64: =O63*('AP02'!$P64-1) -> 505.2456 | O64: =(O63*'AP02'!$P64)-'AP02'!$G64 -> 262397.02 | P64: 1.001923
A65: =A64+1 -> 51 | B65: =EDATE(B64,1) -> 44794 | C65: =C64 -> 0.062 | D65: =D64 -> 0.005025 | E65: =E64 -> 2171.2615 | F65: =(O64*'AP02'!$P65)*'AP02'!$D65 -> 1321.3008 | G65: =(O64*'AP02'!$P65)/($I$5-A64) -> 848.21107 | H65: =H64 -> 0 | I65: =I64 -> 0 | J65: =J64 -> 25 | K65: =K64 -> 0 | L65: =L64 -> 0 | M65: =SUM('AP02'!$F65:$L65) -> 2194.5119 | N65: =O64*('AP02'!$P65-1) -> 548.40978 | O65: =(O64*'AP02'!$P65)-'AP02'!$G65 -> 262097.22 | P65: 1.00209
A66: =A65+1 -> 52 | B66: =EDATE(B65,1) -> 44825 | C66: =C65 -> 0.062 | D66: =D65 -> 0.005025 | E66: =E65 -> 2171.2615 | F66: =(O65*'AP02'!$P66)*'AP02'!$D66 -> 1319.3987 | G66: =(O65*'AP02'!$P66)/($I$5-A65) -> 849.73107 | H66: =H65 -> 0 | I66: =I65 -> 0 | J66: =J65 -> 25 | K66: =K65 -> 0 | L66: =L65 -> 0 | M66: =SUM('AP02'!$F66:$L66) -> 2194.1297 | N66: =O65*('AP02'!$P66-1) -> 469.67822 | O66: =(O65*'AP02'!$P66)-'AP02'!$G66 -> 261717.17 | P66: 1.001792
A67: =A66+1 -> 53 | B67: =EDATE(B66,1) -> 44855 | C67: =C66 -> 0.062 | D67: =D66 -> 0.005025 | E67: =E66 -> 2171.2615 | F67: =(O66*'AP02'!$P67)*'AP02'!$D67 -> 1317.5434 | G67: =(O66*'AP02'!$P67)/($I$5-A66) -> 851.29118 | H67: =H66 -> 0 | I67: =I66 -> 0 | J67: =J66 -> 25 | K67: =K66 -> 0 | L67: =L66 -> 0 | M67: =SUM('AP02'!$F67:$L67) -> 2193.8345 | N67: =O66*('AP02'!$P67-1) -> 480.51272 | O67: =(O66*'AP02'!$P67)-'AP02'!$G67 -> 261346.39 | P67: 1.001836
A68: =A67+1 -> 54 | B68: =EDATE(B67,1) -> 44886 | C68: =C67 -> 0.062 | D68: =D67 -> 0.005025 | E68: =E67 -> 2171.2615 | F68: =(O67*'AP02'!$P68)*'AP02'!$D68 -> 1314.7588 | G68: =(O67*'AP02'!$P68)/($I$5-A67) -> 852.25909 | H68: =H67 -> 0 | I68: =I67 -> 0 | J68: =J67 -> 25 | K68: =K67 -> 0 | L68: =L67 -> 0 | M68: =SUM('AP02'!$F68:$L68) -> 2192.0179 | N68: =O67*('AP02'!$P68-1) -> 297.15085 | O68: =(O67*'AP02'!$P68)-'AP02'!$G68 -> 260791.28 | P68: 1.001137
A69: =A68+1 -> 55 | B69: =EDATE(B68,1) -> 44916 | C69: =C68 -> 0.062 | D69: =D68 -> 0.005025 | E69: =E68 -> 2171.2615 | F69: =(O68*'AP02'!$P69)*'AP02'!$D69 -> 1313.219 | G69: =(O68*'AP02'!$P69)/($I$5-A68) -> 854.04287 | H69: =H68 -> 0 | I69: =I68 -> 0 | J69: =J68 -> 25 | K69: =K68 -> 0 | L69: =L68 -> 0 | M69: =SUM('AP02'!$F69:$L69) -> 2192.2619 | N69: =O68*('AP02'!$P69-1) -> 545.83615 | O69: =(O68*'AP02'!$P69)-'AP02'!$G69 -> 260483.08 | P69: 1.002093
A70: =A69+1 -> 56 | B70: =EDATE(B69,1) -> 44947 | C70: =C69 -> 0.062 | D70: =D69 -> 0.005025 | E70: =E69 -> 2171.2615 | F70: =(O69*'AP02'!$P70)*'AP02'!$D70 -> 1312.082 | G70: =(O69*'AP02'!$P70)/($I$5-A69) -> 856.10112 | H70: =H69 -> 0 | I70: =I69 -> 0 | J70: =J69 -> 25 | K70: =K69 -> 0 | L70: =L69 -> 0 | M70: =SUM('AP02'!$F70:$L70) -> 2193.1831 | N70: =O69*('AP02'!$P70-1) -> 627.76421 | O70: =(O69*'AP02'!$P70)-'AP02'!$G70 -> 260254.74 | P70: 1.00241
A71: =A70+1 -> 57 | B71: =EDATE(B70,1) -> 44978 | C71: =C70 -> 0.062 | D71: =D70 -> 0.005025 | E71: =E70 -> 2171.2615 | F71: =(O70*'AP02'!$P71)*'AP02'!$D71 -> 1309.726 | G71: =(O70*'AP02'!$P71)/($I$5-A70) -> 857.37499 | H71: =H70 -> 0 | I71: =I70 -> 0 | J71: =J70 -> 25 | K71: =K70 -> 0 | L71: =L70 -> 0 | M71: =SUM('AP02'!$F71:$L71) -> 2192.101 | N71: =O70*('AP02'!$P71-1) -> 387.25905 | O71: =(O70*'AP02'!$P71)-'AP02'!$G71 -> 259784.62 | P71: 1.001488
A72: =A71+1 -> 58 | B72: =EDATE(B71,1) -> 45006 | C72: =C71 -> 0.062 | D72: =D71 -> 0.005025 | E72: =E71 -> 2171.2615 | F72: =(O71*'AP02'!$P72)*'AP02'!$D72 -> 1306.8459 | G72: =(O71*'AP02'!$P72)/($I$5-A71) -> 858.31296 | H72: =H71 -> 0 | I72: =I71 -> 0 | J72: =J71 -> 25 | K72: =K71 -> 0 | L72: =L71 -> 0 | M72: =SUM('AP02'!$F72:$L72) -> 2190.1588 | N72: =O71*('AP02'!$P72-1) -> 284.20438 | O72: =(O71*'AP02'!$P72)-'AP02'!$G72 -> 259210.51 | P72: 1.001094
A73: =A72+1 -> 59 | B73: =EDATE(B72,1) -> 45037 | C73: =C72 -> 0.062 | D73: =D72 -> 0.005025 | E73: =E72 -> 2171.2615 | F73: =(O72*'AP02'!$P73)*'AP02'!$D73 -> 1305.2538 | G73: =(O72*'AP02'!$P73)/($I$5-A72) -> 860.10598 | H73: =H72 -> 0 | I73: =I72 -> 0 | J73: =J72 -> 25 | K73: =K72 -> 0 | L73: =L72 -> 0 | M73: =SUM('AP02'!$F73:$L73) -> 2190.3598 | N73: =O72*('AP02'!$P73-1) -> 541.49076 | O73: =(O72*'AP02'!$P73)-'AP02'!$G73 -> 258891.9 | P73: 1.002089
A74: =A73+1 -> 60 | B74: =EDATE(B73,1) -> 45067 | C74: =C73 -> 0.062 | D74: =D73 -> 0.005025 | E74: =E73 -> 2171.2615 | F74: =(O73*'AP02'!$P74)*'AP02'!$D74 -> 1302.3888 | G74: =(O73*'AP02'!$P74)/($I$5-A73) -> 861.0693 | H74: =H73 -> 0 | I74: =I73 -> 0 | J74: =J73 -> 25 | K74: =K73 -> 0 | L74: =L73 -> 0 | M74: =SUM('AP02'!$F74:$L74) -> 2188.4581 | N74: =O73*('AP02'!$P74-1) -> 289.95893 | O74: =(O73*'AP02'!$P74)-'AP02'!$G74 -> 258320.79 | P74: 1.00112
... A76: =A75+1 -> 62 | B76: =EDATE(B75,1) -> 45128 | C76: =C75 -> 0.062 | D76: =D75 -> 0.005025 | E76: =E75 -> 2171.2615 | F76: =(O75*'AP02'!$P76)*'AP02'!$D76 -> 1298.6482 | G76: =(O75*'AP02'!$P76)/($I$5-A75) -> 864.33928 | H76: =H75 -> 0 | I76: =I75 -> 0 | J76: =J75 -> 25 | K76: =K75 -> 0 | L76: =L75 -> 0 | M76: =SUM('AP02'!$F76:$L76) -> 2187.9874 | N76: =O75*('AP02'!$P76-1) -> 516.61542 | O76: =(O75*'AP02'!$P76)-'AP02'!$G76 -> 257573.11 | P76: 1.002003
A77: =A76+1 -> 63 | B77: =EDATE(B76,1) -> 45159 | C77: =I7 -> 0.0775 | D77: =I6 -> 0.0062 | E77: =E76 -> 2171.2615 | F77: =(O76*'AP02'!$P77)*'AP02'!$D77 -> 1599.4764 | G77: =(O76*'AP02'!$P77)/($I$5-A76) -> 865.70494 | H77: =H76 -> 0 | I77: =I76 -> 0 | J77: =J76 -> 25 | K77: =K76 -> 0 | L77: =L76 -> 0 | M77: =SUM('AP02'!$F77:$L77) -> 2490.1814 | N77: =O76*('AP02'!$P77-1) -> 406.96551 | O77: =(O76*'AP02'!$P77)-'AP02'!$G77 -> 257114.37 | P77: 1.00158
A78: =A77+1 -> 64 | B78: =EDATE(B77,1) -> 45190 | C78: =C77 -> 0.0775 | D78: =D77 -> 0.0062 | E78: =E77 -> 2171.2615 | F78: =(O77*'AP02'!$P78)*'AP02'!$D78 -> 1596.9434 | G78: =(O77*'AP02'!$P78)/($I$5-A77) -> 867.24416 | H78: =H77 -> 0 | I78: =I77 -> 0 | J78: =J77 -> 25 | K78: =K77 -> 0 | L78: =L77 -> 0 | M78: =SUM('AP02'!$F78:$L78) -> 2489.1876 | N78: =O77*('AP02'!$P78-1) -> 457.14934 | O78: =(O77*'AP02'!$P78)-'AP02'!$G78 -> 256704.27 | P78: 1.001778
A79: =A78+1 -> 65 | B79: =EDATE(B78,1) -> 45220 | C79: =C78 -> 0.0775 | D79: =((1+'AP02'!$C79)^(1/12))-1 -> 0.0062396815 | E79: =E78 -> 2171.2615 | F79: =(O78*'AP02'!$P79)*'AP02'!$D79 -> 1603.5949 | G79: =(O78*'AP02'!$P79)/($I$5-A78) -> 868.24149 | H79: =H78 -> 0 | I79: =I78 -> 0 | J79: =J78 -> 25 | K79: =K78 -> 0 | L79: =L78 -> 0 | M79: =SUM('AP02'!$F79:$L79) -> 2496.8364 | N79: =O78*('AP02'!$P79-1) -> 295.20991 | O79: =(O78*'AP02'!$P79)-'AP02'!$G79 -> 256131.24 | P79: 1.00115
A80: =A79+1 -> 66 | B80: =EDATE(B79,1) -> 45251 | C80: =C79 -> 0.0775 | D80: =((1+'AP02'!$C80)^(1/12))-1 -> 0.0062396815 | E80: =E79 -> 2171.2615 | F80: =(O79*'AP02'!$P80)*'AP02'!$D80 -> 1598.9716 | G80: =(O79*'AP02'!$P80)/($I$5-A79) -> 868.67301 | H80: =H79 -> 0 | I80: =I79 -> 0 | J80: =J79 -> 25 | K80: =K79 -> 0 | L80: =L79 -> 0 | M80: =SUM('AP02'!$F80:$L80) -> 2492.6447 | N80: =O79*('AP02'!$P80-1) -> 127.29723 | O80: =(O79*'AP02'!$P80)-'AP02'!$G80 -> 255389.86 | P80: 1.000497
A81: =A80+1 -> 67 | B81: =EDATE(B80,1) -> 45281 | C81: =C80 -> 0.0775 | D81: =((1+'AP02'!$C81)^(1/12))-1 -> 0.0062396815 | E81: =E80 -> 2171.2615 | F81: =(O80*'AP02'!$P81)*'AP02'!$D81 -> 1595.5864 | G81: =(O80*'AP02'!$P81)/($I$5-A80) -> 869.7823 | H81: =H80 -> 0 | I81: =I80 -> 0 | J81: =J80 -> 25 | K81: =K80 -> 0 | L81: =L80 -> 0 | M81: =SUM('AP02'!$F81:$L81) -> 2490.3687 | N81: =O80*('AP02'!$P81-1) -> 326.13286 | O81: =(O80*'AP02'!$P81)-'AP02'!$G81 -> 254846.21 | P81: 1.001277
A82: =A81+1 -> 68 | B82: =EDATE(B81,1) -> 45312 | C82: =C81 -> 0.0775 | D82: =((1+'AP02'!$C82)^(1/12))-1 -> 0.0062396815 | E82: =E81 -> 2171.2615 | F82: =(O81*'AP02'!$P82)*'AP02'!$D82 -> 1590.897 | G82: =(O81*'AP02'!$P82)/($I$5-A81) -> 870.18588 | H82: =H81 -> 0 | I82: =I81 -> 0 | J82: =J81 -> 25 | K82: =K81 -> 0 | L82: =L81 -> 0 | M82: =SUM('AP02'!$F82:$L82) -> 2486.0829 | N82: =O81*('AP02'!$P82-1) -> 118.24864 | O82: =(O81*'AP02'!$P82)-'AP02'!$G82 -> 254094.28 | P82: 1.000464
A83: =A82+1 -> 69 | B83: =EDATE(B82,1) -> 45343 | C83: =C82 -> 0.0775 | D83: =((1+'AP02'!$C83)^(1/12))-1 -> 0.0062396815 | E83: =E82 -> 2171.2615 | F83: =(O82*'AP02'!$P83)*'AP02'!$D83 -> 1586.0651 | G83: =(O82*'AP02'!$P83)/($I$5-A82) -> 870.51394 | H83: =H82 -> 0 | I83: =I82 -> 0 | J83: =J82 -> 25 | K83: =K82 -> 0 | L83: =L82 -> 0 | M83: =SUM('AP02'!$F83:$L83) -> 2481.579 | N83: =O82*('AP02'!$P83-1) -> 95.793543 | O83: =(O82*'AP02'!$P83)-'AP02'!$G83 -> 253319.56 | P83: 1.000377
A84: =A83+1 -> 70 | B84: =EDATE(B83,1) -> 45372 | C84: =C83 -> 0.0775 | D84: =((1+'AP02'!$C84)^(1/12))-1 -> 0.0062396815 | E84: =E83 -> 2171.2615 | F84: =(O83*'AP02'!$P84)*'AP02'!$D84 -> 1581.6576 | G84: =(O83*'AP02'!$P84)/($I$5-A83) -> 871.07804 | H84: =H83 -> 0 | I84: =I83 -> 0 | J84: =J83 -> 25 | K84: =K83 -> 0 | L84: =L83 -> 0 | M84: =SUM('AP02'!$F84:$L84) -> 2477.7356 | N84: =O83*('AP02'!$P84-1) -> 164.15107 | O84: =(O83*'AP02'!$P84)-'AP02'!$G84 -> 252612.63 | P84: 1.000648 | R84: ='AP02'!$O84+0.02 -> 252612.65 | S84: 3103.77 | T84: =R84+S84-'AP02'!$G84 -> 254845.34
A85: =A84+1 -> 71 | B85: =EDATE(B84,1) -> 45403 | C85: =C84 -> 0.0775 | D85: =((1+'AP02'!$C85)^(1/12))-1 -> 0.0062396815 | E85: =E84 -> 2171.2615 | F85: =(O84*'AP02'!$P85)*'AP02'!$D85 -> 1577.2122 | G85: =(O84*'AP02'!$P85)/($I$5-A84) -> 871.62507 | H85: =H84 -> 0 | I85: =I84 -> 0 | J85: =J84 -> 25 | K85: =K84 -> 0 | L85: =L84 -> 0 | M85: =SUM('AP02'!$F85:$L85) -> 2473.8373 | N85: =O84*('AP02'!$P85-1) -> 158.64073 | O85: =(O84*'AP02'!$P85)+'AP02'!$F85 -> 254348.48 | P85: 1.000628 | R85: =(R84*'AP02'!$P85)+(S84*'AP02'!$P85) -> 255877.01 | S85: =2115.97+871.08+51.45+40.27+25 -> 3103.77
A86: =A85+1 -> 72 | B86: =EDATE(B85,1) -> 45433 | C86: =C85 -> 0.0775 | D86: =((1+'AP02'!$C86)^(1/12))-1 -> 0.0062396815 | E86: =E85 -> 2171.2615 | F86: =(O85*'AP02'!$P86)*'AP02'!$D86 -> 1587.6296 | G86: =(O85*'AP02'!$P86)/($I$5-A85) -> 880.41803 | H86: =H85 -> 0 | I86: =I85 -> 0 | J86: =J85 -> 25 | K86: =K85 -> 0 | L86: =L85 -> 0 | M86: =SUM('AP02'!$F86:$L86) -> 2493.0477 | N86: =O85*('AP02'!$P86-1) -> 92.328499 | O86: =(O85*'AP02'!$P86)+'AP02'!$F86 -> 256028.44 | P86: 1.000363
A87: =A86+1 -> 73 | B87: =EDATE(B86,1) -> 45464 | C87: =C86 -> 0.0775 | D87: =((1+'AP02'!$C87)^(1/12))-1 -> 0.0062396815 | E87: =E86 -> 2171.2615 | F87: =(O86*'AP02'!$P87)*'AP02'!$D87 -> 1599.0073 | G87: =(O86*'AP02'!$P87)/($I$5-A86) -> 889.8064 | H87: =H86 -> 0 | I87: =I86 -> 0 | J87: =J86 -> 25 | K87: =K86 -> 0 | L87: =L86 -> 0 | M87: =SUM('AP02'!$F87:$L87) -> 2513.8137 | N87: =O86*('AP02'!$P87-1) -> 235.80219 | O87: =(O86*'AP02'!$P87)-'AP02'!$G87 -> 255374.44 | P87: 1.000921 | R87: 254994.68
A88: =A87+1 -> 74 | B88: =EDATE(B87,1) -> 45494 | C88: =C87 -> 0.0775 | D88: =((1+'AP02'!$C88)^(1/12))-1 -> 0.0062396815 | E88: =E87 -> 2171.2615 | F88: =(O87*'AP02'!$P88)*'AP02'!$D88 -> 1594.4957 | G88: =(O87*'AP02'!$P88)/($I$5-A87) -> 890.38745 | H88: =H87 -> 0 | I88: =I87 -> 0 | J88: =J87 -> 25 | K88: =K87 -> 0 | L88: =L87 -> 0 | M88: =SUM('AP02'!$F88:$L88) -> 2509.8831 | N88: =O87*('AP02'!$P88-1) -> 166.75951 | O88: =(O87*'AP02'!$P88)-'AP02'!$G88 -> 254650.81 | P88: 1.000653 | R88: =R87-R84 -> 2382.0296
A89: =A88+1 -> 75 | B89: =EDATE(B88,1) -> 45525 | C89: =C88 -> 0.0775 | D89: =((1+'AP02'!$C89)^(1/12))-1 -> 0.0062396815 | E89: =E88 -> 2171.2615 | F89: =(O88*'AP02'!$P89)*'AP02'!$D89 -> 1590.0649 | G89: =(O88*'AP02'!$P89)/($I$5-A88) -> 891.01784 | H89: =H88 -> 0 | I89: =I88 -> 0 | J89: =J88 -> 25 | K89: =K88 -> 0 | L89: =L88 -> 0 | M89: =SUM('AP02'!$F89:$L89) -> 2506.0827 | N89: =O88*('AP02'!$P89-1) -> 180.29277 | O89: =(O88*'AP02'!$P89)-'AP02'!$G89 -> 253940.08 | P89: 1.000708 | R89: =R88-2115.97 -> 266.05959
A90: =A89+1 -> 76 | B90: =EDATE(B89,1) -> 45556 | C90: =C89 -> 0.0775 | D90: =((1+'AP02'!$C90)^(1/12))-1 -> 0.0062396815 | E90: =E89 -> 2171.2615 | F90: =(O89*'AP02'!$P90)*'AP02'!$D90 -> 1585.6857 | G90: =(O89*'AP02'!$P90)/($I$5-A89) -> 891.68165 | H90: =H89 -> 0 | I90: =I89 -> 0 | J90: =J89 -> 25 | K90: =K89 -> 0 | L90: =L89 -> 0 | M90: =SUM('AP02'!$F90:$L90) -> 2502.3673 | N90: =O89*('AP02'!$P90-1) -> 189.18536 | O90: =(O89*'AP02'!$P90)-'AP02'!$G90 -> 253237.59 | P90: 1.000745 | R90: =51.45+40.27+51.94+40.3+50 -> 233.96
A91: =A90+1 -> 77 | B91: =EDATE(B90,1) -> 45586 | C91: =C90 -> 0.0775 | D91: =((1+'AP02'!$C91)^(1/12))-1 -> 0.0062396815 | E91: =E90 -> 2171.2615 | F91: =(O90*'AP02'!$P91)*'AP02'!$D91 -> 1581.1727 | G91: =(O90*'AP02'!$P91)/($I$5-A90) -> 892.27462 | H91: =H90 -> 0 | I91: =I90 -> 0 | J91: =J90 -> 25 | K91: =K90 -> 0 | L91: =L90 -> 0 | M91: =SUM('AP02'!$F91:$L91) -> 2498.4473 | N91: =O90*('AP02'!$P91-1) -> 168.403 | O91: =(O90*'AP02'!$P91)-'AP02'!$G91 -> 252513.72 | P91: 1.000665
A92: =A91+1 -> 78 | B92: =EDATE(B91,1) -> 45617 | C92: =C91 -> 0.0775 | D92: =((1+'AP02'!$C92)^(1/12))-1 -> 0.0062396815 | E92: =E91 -> 2171.2615 | F92: =(O91*'AP02'!$P92)*'AP02'!$D92 -> 1576.7443 | G92: =(O91*'AP02'!$P92)/($I$5-A91) -> 892.91973 | H92: =H91 -> 0 | I92: =I91 -> 0 | J92: =J91 -> 25 | K92: =K91 -> 0 | L92: =L91 -> 0 | M92: =SUM('AP02'!$F92:$L92) -> 2494.664 | N92: =O91*('AP02'!$P92-1) -> 182.56742 | O92: =(O91*'AP02'!$P92)-'AP02'!$G92 -> 251803.36 | P92: 1.000723
A93: =A92+1 -> 79 | B93: =EDATE(B92,1) -> 45647 | C93: =C92 -> 0.0775 | D93: =((1+'AP02'!$C93)^(1/12))-1 -> 0.0062396815 | E93: =E92 -> 2171.2615 | F93: =(O92*'AP02'!$P93)*'AP02'!$D93 -> 1572.7424 | G93: =(O92*'AP02'!$P93)/($I$5-A92) -> 893.81176 | H93: =H92 -> 0 | I93: =I92 -> 0 | J93: =J92 -> 25 | K93: =K92 -> 0 | L93: =L92 -> 0 | M93: =SUM('AP02'!$F93:$L93) -> 2491.5541 | N93: =O92*('AP02'!$P93-1) -> 251.55156 | O93: =(O92*'AP02'!$P93)-'AP02'!$G93 -> 251161.1 | P93: 1.000999
A94: =A93+1 -> 80 | B94: =EDATE(B93,1) -> 45678 | C94: =C93 -> 0.0775 | D94: =((1+'AP02'!$C94)^(1/12))-1 -> 0.0062396815 | E94: =E93 -> 2171.2615 | F94: =(O93*'AP02'!$P94)*'AP02'!$D94 -> 1568.419 | G94: =(O93*'AP02'!$P94)/($I$5-A93) -> 894.52681 | H94: =H93 -> 0 | I94: =I93 -> 0 | J94: =J93 -> 25 | K94: =K93 -> 0 | L94: =L93 -> 0 | M94: =SUM('AP02'!$F94:$L94) -> 2487.9458 | N94: =O93*('AP02'!$P94-1) -> 200.92888 | O94: =(O93*'AP02'!$P94)-'AP02'!$G94 -> 250467.51 | P94: 1.0008
A95: =A94+1 -> 81 | B95: =EDATE(B94,1) -> 45709 | C95: =C94 -> 0.0775 | D95: =((1+'AP02'!$C95)^(1/12))-1 -> 0.0062396815 | E95: =E94 -> 2171.2615 | F95: =(O94*'AP02'!$P95)*'AP02'!$D95 -> 1565.513 | G95: =(O94*'AP02'!$P95)/($I$5-A94) -> 896.05824 | H95: =H94 -> 0 | I95: =I94 -> 0 | J95: =J94 -> 25 | K95: =K94 -> 0 | L95: =L94 -> 0 | M95: =SUM('AP02'!$F95:$L95) -> 2486.5713 | N95: =O94*('AP02'!$P95-1) -> 428.80037 | O95: =(O94*'AP02'!$P95)-'AP02'!$G95 -> 250000.25 | P95: 1.001712
A96: =A95+1 -> 82 | B96: =EDATE(B95,1) -> 45737 | C96: =C95 -> 0.0775 | D96: =((1+'AP02'!$C96)^(1/12))-1 -> 0.0062396815 | E96: =E95 -> 2171.2615 | F96: =(O95*'AP02'!$P96)*'AP02'!$D96 -> 1561.0809 | G96: =(O95*'AP02'!$P96)/($I$5-A95) -> 896.72401 | H96: =H95 -> 0 | I96: =I95 -> 0 | J96: =J95 -> 25 | K96: =K95 -> 0 | L96: =L95 -> 0 | M96: =SUM('AP02'!$F96:$L96) -> 2482.8049 | N96: =O95*('AP02'!$P96-1) -> 185.75018 | O96: =(O95*'AP02'!$P96)-'AP02'!$G96 -> 249289.27 | P96: 1.000743
A97: =A96+1 -> 83 | B97: =EDATE(B96,1) -> 45768 | C97: =C96 -> 0.0775 | D97: =((1+'AP02'!$C97)^(1/12))-1 -> 0.0062396815 | E97: =E96 -> 2171.2615 | F97: =(O96*'AP02'!$P97)*'AP02'!$D97 -> 1558.1113 | G97: =(O96*'AP02'!$P97)/($I$5-A96) -> 898.23768 | H97: =H96 -> 0 | I97: =I96 -> 0 | J97: =J96 -> 25 | K97: =K96 -> 0 | L97: =L96 -> 0 | M97: =SUM('AP02'!$F97:$L97) -> 2481.349 | N97: =O96*('AP02'!$P97-1) -> 420.80029 | O97: =(O96*'AP02'!$P97)-'AP02'!$G97 -> 248811.84 | P97: 1.001688
A98: =A97+1 -> 84 | B98: =EDATE(B97,1) -> 45798 | C98: =C97 -> 0.0775 | D98: =((1+'AP02'!$C98)^(1/12))-1 -> 0.0062396815 | E98: =E97 -> 2171.2615 | F98: =(O97*'AP02'!$P98)*'AP02'!$D98 -> 1552.5066 | G98: =(O97*'AP02'!$P98)/($I$5-A97) -> 898.23768 | H98: =H97 -> 0 | I98: =I97 -> 0 | J98: =J97 -> 25 | K98: =K97 -> 0 | L98: =L97 -> 0 | M98: =SUM('AP02'!$F98:$L98) -> 2475.7443 | N98: =O97*('AP02'!$P98-1) -> 0 | O98: =(O97*'AP02'!$P98)-'AP02'!$G98 -> 247913.6 | P98: 1
A99: =A98+1 -> 85 | B99: =EDATE(B98,1) -> 45829 | C99: =C98 -> 0.0775 | D99: =((1+'AP02'!$C99)^(1/12))-1 -> 0.0062396815 | E99: =E98 -> 2171.2615 | F99: =(O98*'AP02'!$P99)*'AP02'!$D99 -> 1546.9019 | G99: =(O98*'AP02'!$P99)/($I$5-A98) -> 898.23768 | H99: =H98 -> 0 | I99: =I98 -> 0 | J99: =J98 -> 25 | K99: =K98 -> 0 | L99: =L98 -> 0 | M99: =SUM('AP02'!$F99:$L99) -> 2470.1396 | N99: =O98*('AP02'!$P99-1) -> 0 | O99: =(O98*'AP02'!$P99)-'AP02'!$G99 -> 247015.36 | P99: =P98 -> 1
A100: =A99+1 -> 86 | B100: =EDATE(B99,1) -> 45859 | C100: =C99 -> 0.0775 | D100: =((1+'AP02'!$C100)^(1/12))-1 -> 0.0062396815 | E100: =E99 -> 2171.2615 | F100: =(O99*'AP02'!$P100)*'AP02'!$D100 -> 1541.2972 | G100: =(O99*'AP02'!$P100)/($I$5-A99) -> 898.23768 | H100: =H99 -> 0 | I100: =I99 -> 0 | J100: =J99 -> 25 | K100: =K99 -> 0 | L100: =L99 -> 0 | M100: =SUM('AP02'!$F100:$L100) -> 2464.5349 | N100: =O99*('AP02'!$P100-1) -> 0 | O100: =(O99*'AP02'!$P100)-'AP02'!$G100 -> 246117.12 | P100: =P99 -> 1
A101: =A100+1 -> 87 | B101: =EDATE(B100,1) -> 45890 | C101: =C100 -> 0.0775 | D101: =((1+'AP02'!$C101)^(1/12))-1 -> 0.0062396815 | E101: =E100 -> 2171.2615 | F101: =(O100*'AP02'!$P101)*'AP02'!$D101 -> 1535.6925 | G101: =(O100*'AP02'!$P101)/($I$5-A100) -> 898.23768 | H101: =H100 -> 0 | I101: =I100 -> 0 | J101: =J100 -> 25 | K101: =K100 -> 0 | L101: =L100 -> 0 | M101: =SUM('AP02'!$F101:$L101) -> 2458.9301 | N101: =O100*('AP02'!$P101-1) -> 0 | O101: =(O100*'AP02'!$P101)-'AP02'!$G101 -> 245218.89 | P101: =P100 -> 1
A102: =A101+1 -> 88 | B102: =EDATE(B101,1) -> 45921 | C102: =C101 -> 0.0775 | D102: =((1+'AP02'!$C102)^(1/12))-1 -> 0.0062396815 | E102: =E101 -> 2171.2615 | F102: =(O101*'AP02'!$P102)*'AP02'!$D102 -> 1530.0877 | G102: =(O101*'AP02'!$P102)/($I$5-A101) -> 898.23768 | H102: =H101 -> 0 | I102: =I101 -> 0 | J102: =J101 -> 25 | K102: =K101 -> 0 | L102: =L101 -> 0 | M102: =SUM('AP02'!$F102:$L102) -> 2453.3254 | N102: =O101*('AP02'!$P102-1) -> 0 | O102: =(O101*'AP02'!$P102)-'AP02'!$G102 -> 244320.65 | P102: =P101 -> 1
A103: =A102+1 -> 89 | B103: =EDATE(B102,1) -> 45951 | C103: =C102 -> 0.0775 | D103: =((1+'AP02'!$C103)^(1/12))-1 -> 0.0062396815 | E103: =E102 -> 2171.2615 | F103: =(O102*'AP02'!$P103)*'AP02'!$D103 -> 1524.483 | G103: =(O102*'AP02'!$P103)/($I$5-A102) -> 898.23768 | H103: =H102 -> 0 | I103: =I102 -> 0 | J103: =J102 -> 25 | K103: =K102 -> 0 | L103: =L102 -> 0 | M103: =SUM('AP02'!$F103:$L103) -> 2447.7207 | N103: =O102*('AP02'!$P103-1) -> 0 | O103: =(O102*'AP02'!$P103)-'AP02'!$G103 -> 243422.41 | P103: =P102 -> 1
A104: =A103+1 -> 90 | B104: =EDATE(B103,1) -> 45982 | C104: =C103 -> 0.0775 | D104: =((1+'AP02'!$C104)^(1/12))-1 -> 0.0062396815 | E104: =E103 -> 2171.2615 | F104: =(O103*'AP02'!$P104)*'AP02'!$D104 -> 1518.8783 | G104: =(O103*'AP02'!$P104)/($I$5-A103) -> 898.23768 | H104: =H103 -> 0 | I104: =I103 -> 0 | J104: =J103 -> 25 | K104: =K103 -> 0 | L104: =L103 -> 0 | M104: =SUM('AP02'!$F104:$L104) -> 2442.116 | N104: =O103*('AP02'!$P104-1) -> 0 | O104: =(O103*'AP02'!$P104)-'AP02'!$G104 -> 242524.17 | P104: =P103 -> 1
A105: =A104+1 -> 91 | B105: =EDATE(B104,1) -> 46012 | C105: =C104 -> 0.0775 | D105: =((1+'AP02'!$C105)^(1/12))-1 -> 0.0062396815 | E105: =E104 -> 2171.2615 | F105: =(O104*'AP02'!$P105)*'AP02'!$D105 -> 1513.2736 | G105: =(O104*'AP02'!$P105)/($I$5-A104) -> 898.23768 | H105: =H104 -> 0 | I105: =I104 -> 0 | J105: =J104 -> 25 | K105: =K104 -> 0 | L105: =L104 -> 0 | M105: =SUM('AP02'!$F105:$L105) -> 2436.5113 | N105: =O104*('AP02'!$P105-1) -> 0 | O105: =(O104*'AP02'!$P105)-'AP02'!$G105 -> 241625.94 | P105: =P104 -> 1
A106: =A105+1 -> 92 | B106: =EDATE(B105,1) -> 46043 | C106: =C105 -> 0.0775 | D106: =((1+'AP02'!$C106)^(1/12))-1 -> 0.0062396815 | E106: =E105 -> 2171.2615 | F106: =(O105*'AP02'!$P106)*'AP02'!$D106 -> 1507.6689 | G106: =(O105*'AP02'!$P106)/($I$5-A105) -> 898.23768 | H106: =H105 -> 0 | I106: =I105 -> 0 | J106: =J105 -> 25 | K106: =K105 -> 0 | L106: =L105 -> 0 | M106: =SUM('AP02'!$F106:$L106) -> 2430.9065 | N106: =O105*('AP02'!$P106-1) -> 0 | O106: =(O105*'AP02'!$P106)-'AP02'!$G106 -> 240727.7 | P106: =P105 -> 1
A107: =A106+1 -> 93 | B107: =EDATE(B106,1) -> 46074 | C107: =C106 -> 0.0775 | D107: =((1+'AP02'!$C107)^(1/12))-1 -> 0.0062396815 | E107: =E106 -> 2171.2615 | F107: =(O106*'AP02'!$P107)*'AP02'!$D107 -> 1502.0642 | G107: =(O106*'AP02'!$P107)/($I$5-A106) -> 898.23768 | H107: =H106 -> 0 | I107: =I106 -> 0 | J107: =J106 -> 25 | K107: =K106 -> 0 | L107: =L106 -> 0 | M107: =SUM('AP02'!$F107:$L107) -> 2425.3018 | N107: =O106*('AP02'!$P107-1) -> 0 | O107: =(O106*'AP02'!$P107)-'AP02'!$G107 -> 239829.46 | P107: =P106 -> 1
A108: =A107+1 -> 94 | B108: =EDATE(B107,1) -> 46102 | C108: =C107 -> 0.0775 | D108: =((1+'AP02'!$C108)^(1/12))-1 -> 0.0062396815 | E108: =E107 -> 2171.2615 | F108: =(O107*'AP02'!$P108)*'AP02'!$D108 -> 1496.4594 | G108: =(O107*'AP02'!$P108)/($I$5-A107) -> 898.23768 | H108: =H107 -> 0 | I108: =I107 -> 0 | J108: =J107 -> 25 | K108: =K107 -> 0 | L108: =L107 -> 0 | M108: =SUM('AP02'!$F108:$L108) -> 2419.6971 | N108: =O107*('AP02'!$P108-1) -> 0 | O108: =(O107*'AP02'!$P108)-'AP02'!$G108 -> 238931.22 | P108: =P107 -> 1
A109: =A108+1 -> 95 | B109: =EDATE(B108,1) -> 46133 | C109: =C108 -> 0.0775 | D109: =((1+'AP02'!$C109)^(1/12))-1 -> 0.0062396815 | E109: =E108 -> 2171.2615 | F109: =(O108*'AP02'!$P109)*'AP02'!$D109 -> 1490.8547 | G109: =(O108*'AP02'!$P109)/($I$5-A108) -> 898.23768 | H109: =H108 -> 0 | I109: =I108 -> 0 | J109: =J108 -> 25 | K109: =K108 -> 0 | L109: =L108 -> 0 | M109: =SUM('AP02'!$F109:$L109) -> 2414.0924 | N109: =O108*('AP02'!$P109-1) -> 0 | O109: =(O108*'AP02'!$P109)-'AP02'!$G109 -> 238032.98 | P109: =P108 -> 1
A110: =A109+1 -> 96 | B110: =EDATE(B109,1) -> 46163 | C110: =C109 -> 0.0775 | D110: =((1+'AP02'!$C110)^(1/12))-1 -> 0.0062396815 | E110: =E109 -> 2171.2615 | F110: =(O109*'AP02'!$P110)*'AP02'!$D110 -> 1485.25 | G110: =(O109*'AP02'!$P110)/($I$5-A109) -> 898.23768 | H110: =H109 -> 0 | I110: =I109 -> 0 | J110: =J109 -> 25 | K110: =K109 -> 0 | L110: =L109 -> 0 | M110: =SUM('AP02'!$F110:$L110) -> 2408.4877 | N110: =O109*('AP02'!$P110-1) -> 0 | O110: =(O109*'AP02'!$P110)-'AP02'!$G110 -> 237134.75 | P110: =P109 -> 1
... A374: =A373+1 -> 360 | B374: =EDATE(B373,1) -> 54199 | C374: =C373 -> 0.0775 | D374: =((1+'AP02'!$C374)^(1/12))-1 -> 0.0062396815 | E374: =E373 -> 2171.2615 | F374: =(O373*'AP02'!$P374)*'AP02'!$D374 -> 5.604717 | G374: =(O373*'AP02'!$P374)/($I$5-A373) -> 898.23768 | H374: =H373 -> 0 | I374: =I373 -> 0 | J374: =J373 -> 25 | K374: =K373 -> 0 | L374: =L373 -> 0 | M374: =SUM('AP02'!$F374:$L374) -> 928.8424 | N374: =O373*('AP02'!$P374-1) -> 0 | O374: =(O373*'AP02'!$P374)-'AP02'!$G374 -> 0 | P374: =P373 -> 1
A376: Este apêndice retrata a evolução do financiamento com taxa MÉDIA do BACEN, expurgando os seguros e afastando a mora, já que ficou cabalmente demonstrado a abusividade no período da normalidade contratual.

Sheet AP03
A1: APÊNDICE 03: DEMONSTRATIVO DAS DIFERENÇAS EXCEDENTES A RESTITUIR
A3: ='AP01'!A3 -> Requerente: ADRIANA MELO DE OLIVEIRA
A4: ='AP01'!A4 -> Requerido: ITAÚ UNIBANCO
A6: Qtde | B6: Data Vencimento | C6: Situação da Parcela | D6: Valor Pago / Prestação Cobrada | E6: Valor Devido / Prestação Devida | F6: Diferença Mensal | G6: TOTAL NOMINAL A RESTITUIR
A7: 0 | B7: ='AP01'!B14 -> 43241 | G7: 0
A8: =A7+1 -> 1 | B8: ='AP01'!B15 -> 43272 | C8: Paga | D8: 2714.96 | E8: ='AP02'!M15 -> 2574.7696 | F8: =D8-E8 -> 140.1904 | G8: =G7+'AP03'!$F8 -> 140.1904
A9: =A8+1 -> 2 | B9: ='AP01'!B16 -> 43302 | C9: Paga | D9: 2640.04 | E9: ='AP02'!M16 -> 2570.0202 | F9: =F8 -> 140.1904 | G9: =G8+'AP03'!$F9 -> 280.3808
A10: =A9+1 -> 3 | B10: ='AP01'!B17 -> 43333 | C10: Paga | D10: 2635.2 | E10: ='AP02'!M17 -> 2565.2709 | F10: =D10-E10 -> 69.92912 | G10: =G9+'AP03'!$F10 -> 350.30992
A11: =A10+1 -> 4 | B11: ='AP01'!B18 -> 43364 | C11: Paga | D11: 2630.36 | E11: ='AP02'!M18 -> 2560.5215 | F11: =D11-E11 -> 69.83848 | G11: =G10+'AP03'!$F11 -> 420.1484
A12: =A11+1 -> 5 | B12: ='AP01'!B19 -> 43394 | C12: Paga | D12: 2625.52 | E12: ='AP02'!M19 -> 2555.7722 | F12: =D12-E12 -> 69.74784 | G12: =G11+'AP03'!$F12 -> 489.89624
A13: =A12+1 -> 6 | B13: ='AP01'!B20 -> 43425 | C13: Paga | D13: 2620.69 | E13: ='AP02'!M20 -> 2551.0228 | F13: =D13-E13 -> 69.6672 | G13: =G12+'AP03'!$F13 -> 559.56344
A14: =A13+1 -> 7 | B14: ='AP01'!B21 -> 43455 | C14: Paga | D14: 2616.41 | E14: ='AP02'!M21 -> 2546.2734 | F14: =D14-E14 -> 70.13656 | G14: =G13+'AP03'!$F14 -> 629.7
A15: =A14+1 -> 8 | B15: ='AP01'!B22 -> 43486 | C15: Paga | D15: 2611.57 | E15: ='AP02'!M22 -> 2541.5241 | F15: =D15-E15 -> 70.04592 | G15: =G14+'AP03'!$F15 -> 699.74592
A16: =A15+1 -> 9 | B16: ='AP01'!B23 -> 43517 | C16: Paga | D16: 2606.73 | E16: ='AP02'!M23 -> 2536.7747 | F16: =D16-E16 -> 69.95528 | G16: =G15+'AP03'!$F16 -> 769.7012
A17: =A16+1 -> 10 | B17: ='AP01'!B24 -> 43545 | C17: Paga | D17: 2601.89 | E17: ='AP02'!M24 -> 2532.0254 | F17: =D17-E17 -> 69.86464 | G17: =G16+'AP03'!$F17 -> 839.56584
A18: =A17+1 -> 11 | B18: ='AP01'!B25 -> 43576 | C18: Paga | D18: 2597.05 | E18: ='AP02'!M25 -> 2527.276 | F18: =D18-E18 -> 69.774 | G18: =G17+'AP03'!$F18 -> 909.33984
A19: =A18+1 -> 12 | B19: ='AP01'!B26 -> 43606 | C19: Paga | D19: 2592.21 | E19: ='AP02'!M26 -> 2522.5266 | F19: =D19-E19 -> 69.68336 | G19: =G18+'AP03'!$F19 -> 979.0232
A20: =A19+1 -> 13 | B20: ='AP01'!B27 -> 43637 | C20: Paga | D20: 2587.38 | E20: ='AP02'!M27 -> 2517.7773 | F20: =D20-E20 -> 69.60272 | G20: =G19+'AP03'!$F20 -> 1048.6259
A21: =A20+1 -> 14 | B21: ='AP01'!B28 -> 43667 | C21: Paga | D21: 2582.54 | E21: ='AP02'!M28 -> 2513.0279 | F21: =D21-E21 -> 69.51208 | G21: =G20+'AP03'!$F21 -> 1118.138
... A90: =A89+1 -> 83 | B90: ='AP01'!B97 -> 45768 | C90: Paga | D90: 3127.79 | E90: ='AP02'!M97 -> 2481.349 | F90: =D90-E90 -> 646.441 | G90: =G89+'AP03'!$F90 -> 23584.045
A91: =A90+1 -> 84 | B91: ='AP01'!B98 -> 45798 | D91: ='AP01'!M98 -> 3120.0187 | E91: ='AP02'!M98 -> 2475.7443 | F91: =D91-E91 -> 644.27437 | G91: =G90+'AP03'!$F91 -> 24228.319
A92: =A91+1 -> 85 | B92: ='AP01'!B99 -> 45829 | D92: ='AP01'!M99 -> 3112.2516 | E92: ='AP02'!M99 -> 2470.1396 | F92: =D92-E92 -> 642.11201 | G92: =G91+'AP03'!$F92 -> 24870.431
A93: =A92+1 -> 86 | B93: ='AP01'!B100 -> 45859 | D93: ='AP01'!M100 -> 3104.4845 | E93: ='AP02'!M100 -> 2464.5349 | F93: =D93-E93 -> 639.94966 | G93: =G92+'AP03'!$F93 -> 25510.381
A94: =A93+1 -> 87 | B94: ='AP01'!B101 -> 45890 | D94: ='AP01'!M101 -> 3096.7174 | E94: ='AP02'!M101 -> 2458.9301 | F94: =D94-E94 -> 637.7873 | G94: =G93+'AP03'!$F94 -> 26148.168
A95: =A94+1 -> 88 | B95: ='AP01'!B102 -> 45921 | D95: ='AP01'!M102 -> 3088.9504 | E95: ='AP02'!M102 -> 2453.3254 | F95: =D95-E95 -> 635.62494 | G95: =G94+'AP03'!$F95 -> 26783.793
A96: =A95+1 -> 89 | B96: ='AP01'!B103 -> 45951 | D96: ='AP01'!M103 -> 3081.1833 | E96: ='AP02'!M103 -> 2447.7207 | F96: =D96-E96 -> 633.46258 | G96: =G95+'AP03'!$F96 -> 27417.256
A97: =A96+1 -> 90 | B97: ='AP01'!B104 -> 45982 | D97: ='AP01'!M104 -> 3073.4162 | E97: ='AP02'!M104 -> 2442.116 | F97: =D97-E97 -> 631.30022 | G97: =G96+'AP03'!$F97 -> 28048.556
A98: =A97+1 -> 91 | B98: ='AP01'!B105 -> 46012 | D98: ='AP01'!M105 -> 3078.2227 | E98: ='AP02'!M105 -> 2436.5113 | F98: =D98-E98 -> 641.71143 | G98: =G97+'AP03'!$F98 -> 28690.267
A99: =A98+1 -> 92 | B99: ='AP01'!B106 -> 46043 | D99: ='AP01'!M106 -> 3070.409 | E99: ='AP02'!M106 -> 2430.9065 | F99: =D99-E99 -> 639.5025 | G99: =G98+'AP03'!$F99 -> 29329.77
A100: =A99+1 -> 93 | B100: ='AP01'!B107 -> 46074 | D100: ='AP01'!M107 -> 3062.5954 | E100: ='AP02'!M107 -> 2425.3018 | F100: =D100-E100 -> 637.29357 | G100: =G99+'AP03'!$F100 -> 29967.063
A101: =A100+1 -> 94 | B101: ='AP01'!B108 -> 46102 | D101: ='AP01'!M108 -> 3054.7818 | E101: ='AP02'!M108 -> 2419.6971 | F101: =D101-E101 -> 635.08464 | G101: =G100+'AP03'!$F101 -> 30602.148
A102: =A101+1 -> 95 | B102: ='AP01'!B109 -> 46133 | D102: ='AP01'!M109 -> 3046.9681 | E102: ='AP02'!M109 -> 2414.0924 | F102: =D102-E102 -> 632.87571 | G102: =G101+'AP03'!$F102 -> 31235.024
... A366: =A365+1 -> 359 | B366: ='AP01'!B373 -> 54169 | D366: ='AP01'!M373 -> 989.09681 | E366: ='AP02'!M373 -> 934.44711 | F366: =D366-E366 -> 54.649696 | G366: =G365+'AP03'!$F366 -> 132897.78
A367: =A366+1 -> 360 | B367: ='AP01'!B374 -> 54199 | D367: ='AP01'!M374 -> 978.8176 | E367: ='AP02'!M374 -> 928.8424 | F367: =D367-E367 -> 49.975206 | G367: =G366+'AP03'!$F367 -> 132947.75 | I367: ='AP03'!$G367/'AP01'!D7 -> 0.43964204
A369: Este apêndice retrata a diferença excessiva cobrada mensalmente, a serem restituídas em DOBRO e na forma SIMPLES, conforme retratados nos apêndices 04 e 05.

Sheet AP04
A1: APÊNDICE 04: EVOLUÇÃO DO FINANCIAMENTO COM TAXA MÉDIA E EXPURGO DOS SEGUROS => COM REST. EM DOBRO
A3: ='AP01'!A3 -> Requerente: ADRIANA MELO DE OLIVEIRA
A4: ='AP01'!A4 -> Requerido: ITAÚ UNIBANCO
A5: Valor do Bem | D5: ='AP01'!D5 -> 432000 | F5: Qtde Prestações | I5: ='AP01'!I5 -> 360
A6: Entrada/Descontos | D6: ='AP01'!D6 -> 129600 | F6: Taxa MÉDIA Efetiva (a.m.) | I6: 0.0062
A7: Valor Financiado | D7: =D5-D6 -> 302400 | F7: Taxa MÉDIA Efetiva (a.a.) | I7: 0.0775
A8: Data do Contrato | D8: ='AP01'!D8 -> 43241 | F8: Taxa de Juros Efetiva (a.a.) | I8: ='AP01'!I7 -> 0.117
A9: 1° Vencimento | D9: ='AP01'!D9 -> 43272 | F9: (%) Excesso Taxa Média | I9: =(I8/I7)-1 -> 0.50967742
A10: Sistema de Amortização | D10: ='AP01'!D10 -> SAC | F10: Prestação Mensal | I10: ='AP01'!I10 -> 2549.8136
A11: Índice Correção | D11: ='AP01'!D11 -> TR | F11: Enquadramento | I11: ='AP01'!I11 -> SFH
A13: Qtde | B13: Data Vencimento | C13: Taxa Efetiva a.a. | D13: Taxa Efetiva a.m. | E13: Prestação (a+j) | F13: Juros | G13: (1) Amortização | H13: Seguro MIP | I13: Seguro DFI | J13: TCA | K13: Multa | L13: Mora | M13: (2) Valor Pago | N13: (3) Total da Parcela Devida | O13: (4) Diferença a Compensar [2-3] | P13: Correção Monetária | Q13: (5) Saldo Devedor [(5*TR)-1-4*2] | R13: Índice Correção
A14: 0 | B14: =D8 -> 43241 | Q14: =D7 -> 302400
A15: =A14+1 -> 1 | B15: =D9 -> 43272 | C15: 0.07 | D15: 0.005654 | E15: ='AP04'!$F15+'AP04'!$G15 -> 2549.7696 | F15: =(Q14*'AP04'!$R15)*'AP04'!$D15 -> 1709.7696 | G15: =(Q14*'AP04'!$R15)/($I$5-A14) -> 840 | H15: 0 | I15: 0 | J15: 25 | K15: 0 | L15: 0 | M15: ='AP03'!D8 -> 2714.96 | N15: =SUM('AP04'!$F15:$L15) -> 2574.7696 | O15: ='AP04'!$M15-'AP04'!$N15 -> 140.1904 | P15: =Q14*('AP04'!$R15-1) -> 0 | Q15: =(Q14*'AP04'!$R15)-'AP04'!$G15-'AP04'!$O15*2 -> 301279.62 | R15: 1
A16: =A15+1 -> 2 | B16: =EDATE(B15,1) -> 43302 | C16: =C15 -> 0.07 | D16: =D15 -> 0.005654 | E16: ='AP04'!$F16+'AP04'!$G16 -> 2542.654 | F16: =(Q15*'AP04'!$R16)*'AP04'!$D16 -> 1703.435 | G16: =(Q15*'AP04'!$R16)/($I$5-A15) -> 839.21899 | H16: =H15 -> 0 | I16: =I15 -> 0 | J16: =J15 -> 25 | K16: =K15 -> 0 | L16: =L15 -> 0 | M16: ='AP03'!D9 -> 2640.04 | N16: =SUM('AP04'!$F16:$L16) -> 2567.654 | O16: ='AP04'!$M16-'AP04'!$N16 -> 72.386038 | P16: =Q15*('AP04'!$R16-1) -> 0 | Q16: =(Q15*'AP04'!$R16)-'AP04'!$G16-'AP04'!$O16*2 -> 300295.63 | R16: =R15 -> 1
A17: =A16+1 -> 3 | B17: =EDATE(B16,1) -> 43333 | C17: =C16 -> 0.07 | D17: =D16 -> 0.005654 | E17: ='AP04'!$F17+'AP04'!$G17 -> 2536.6861 | F17: =(Q16*'AP04'!$R17)*'AP04'!$D17 -> 1697.8715 | G17: =(Q16*'AP04'!$R17)/($I$5-A16) -> 838.8146 | H17: =H16 -> 0 | I17: =I16 -> 0 | J17: =J16 -> 25 | K17: =K16 -> 0 | L17: =L16 -> 0 | M17: ='AP03'!D10 -> 2635.2 | N17: =SUM('AP04'!$F17:$L17) -> 2561.6861 | O17: ='AP04'!$M17-'AP04'!$N17 -> 73.513915 | P17: =Q16*('AP04'!$R17-1) -> 0 | Q17: =(Q16*'AP04'!$R17)-'AP04'!$G17-'AP04'!$O17*2 -> 299309.79 | R17: =R16 -> 1
A18: =A17+1 -> 4 | B18: =EDATE(B17,1) -> 43364 | C18: =C17 -> 0.07 | D18: =D17 -> 0.005654 | E18: ='AP04'!$F18+'AP04'!$G18 -> 2530.7003 | F18: =(Q17*'AP04'!$R18)*'AP04'!$D18 -> 1692.2975 | G18: =(Q17*'AP04'!$R18)/($I$5-A17) -> 838.40276 | H18: =H17 -> 0 | I18: =I17 -> 0 | J18: =J17 -> 25 | K18: =K17 -> 0 | L18: =L17 -> 0 | M18: ='AP03'!D11 -> 2630.36 | N18: =SUM('AP04'!$F18:$L18) -> 2555.7003 | O18: ='AP04'!$M18-'AP04'!$N18 -> 74.659711 | P18: =Q17*('AP04'!$R18-1) -> 0 | Q18: =(Q17*'AP04'!$R18)-'AP04'!$G18-'AP04'!$O18*2 -> 298322.06 | R18: =R17 -> 1
A19: =A18+1 -> 5 | B19: =EDATE(B18,1) -> 43394 | C19: =C18 -> 0.07 | D19: =D18 -> 0.005654 | E19: ='AP04'!$F19+'AP04'!$G19 -> 2524.6963 | F19: =(Q18*'AP04'!$R19)*'AP04'!$D19 -> 1686.7129 | G19: =(Q18*'AP04'!$R19)/($I$5-A18) -> 837.98332 | H19: =H18 -> 0 | I19: =I18 -> 0 | J19: =J18 -> 25 | K19: =K18 -> 0 | L19: =L18 -> 0 | M19: ='AP03'!D12 -> 2625.52 | N19: =SUM('AP04'!$F19:$L19) -> 2549.6963 | O19: ='AP04'!$M19-'AP04'!$N19 -> 75.823728 | P19: =Q18*('AP04'!$R19-1) -> 0 | Q19: =(Q18*'AP04'!$R19)-'AP04'!$G19-'AP04'!$O19*2 -> 297332.43 | R19: =R18 -> 1
A20: =A19+1 -> 6 | B20: =EDATE(B19,1) -> 43425 | C20: =C19 -> 0.07 | D20: =D19 -> 0.005654 | E20: ='AP04'!$F20+'AP04'!$G20 -> 2518.6737 | F20: =(Q19*'AP04'!$R20)*'AP04'!$D20 -> 1681.1176 | G20: =(Q19*'AP04'!$R20)/($I$5-A19) -> 837.55615 | H20: =H19 -> 0 | I20: =I19 -> 0 | J20: =J19 -> 25 | K20: =K19 -> 0 | L20: =L19 -> 0 | M20: ='AP03'!D13 -> 2620.69 | N20: =SUM('AP04'!$F20:$L20) -> 2543.6737 | O20: ='AP04'!$M20-'AP04'!$N20 -> 77.016277 | P20: =Q19*('AP04'!$R20-1) -> 0 | Q20: =(Q19*'AP04'!$R20)-'AP04'!$G20-'AP04'!$O20*2 -> 296340.84 | R20: =R19 -> 1
A21: =A20+1 -> 7 | B21: =EDATE(B20,1) -> 43455 | C21: =C20 -> 0.07 | D21: =D20 -> 0.005654 | E21: ='AP04'!$F21+'AP04'!$G21 -> 2512.6322 | F21: =(Q20*'AP04'!$R21)*'AP04'!$D21 -> 1675.5111 | G21: =(Q20*'AP04'!$R21)/($I$5-A20) -> 837.12103 | H21: =H20 -> 0 | I21: =I20 -> 0 | J21: =J20 -> 25 | K21: =K20 -> 0 | L21: =L20 -> 0 | M21: ='AP03'!D14 -> 2616.41 | N21: =SUM('AP04'!$F21:$L21) -> 2537.6322 | O21: ='AP04'!$M21-'AP04'!$N21 -> 78.77784 | P21: =Q20*('AP04'!$R21-1) -> 0 | Q21: =(Q20*'AP04'!$R21)-'AP04'!$G21-'AP04'!$O21*2 -> 295346.17 | R21: =R20 -> 1
A22: =A21+1 -> 8 | B22: =EDATE(B21,1) -> 43486 | C22: =C21 -> 0.07 | D22: =D21 -> 0.005654 | E22: ='AP04'!$F22+'AP04'!$G22 -> 2506.5619 | F22: =(Q21*'AP04'!$R22)*'AP04'!$D22 -> 1669.8872 | G22: =(Q21*'AP04'!$R22)/($I$5-A21) -> 836.6747 | H22: =H21 -> 0 | I22: =I21 -> 0 | J22: =J21 -> 25 | K22: =K21 -> 0 | L22: =L21 -> 0 | M22: ='AP03'!D15 -> 2611.57 | N22: =SUM('AP04'!$F22:$L22) -> 2531.5619 | O22: ='AP04'!$M22-'AP04'!$N22 -> 80.008075 | P22: =Q21*('AP04'!$R22-1) -> 0 | Q22: =(Q21*'AP04'!$R22)-'AP04'!$G22-'AP04'!$O22*2 -> 294349.48 | R22: =R21 -> 1
A23: =A22+1 -> 9 | B23: =EDATE(B22,1) -> 43517 | C23: =C22 -> 0.07 | D23: =D22 -> 0.005654 | E23: ='AP04'!$F23+'AP04'!$G23 -> 2500.472 | F23: =(Q22*'AP04'!$R23)*'AP04'!$D23 -> 1664.2519 | G23: =(Q22*'AP04'!$R23)/($I$5-A22) -> 836.2201 | H23: =H22 -> 0 | I23: =I22 -> 0 | J23: =J22 -> 25 | K23: =K22 -> 0 | L23: =L22 -> 0 | M23: ='AP03'!D16 -> 2606.73 | N23: =SUM('AP04'!$F23:$L23) -> 2525.472 | O23: ='AP04'!$M23-'AP04'!$N23 -> 81.257956 | P23: =Q22*('AP04'!$R23-1) -> 0 | Q23: =(Q22*'AP04'!$R23)-'AP04'!$G23-'AP04'!$O23*2 -> 293350.74 | R23: =R22 -> 1
A24: =A23+1 -> 10 | B24: =EDATE(B23,1) -> 43545 | C24: =C23 -> 0.07 | D24: =D23 -> 0.005654 | E24: ='AP04'!$F24+'AP04'!$G24 -> 2494.3622 | F24: =(Q23*'AP04'!$R24)*'AP04'!$D24 -> 1658.6051 | G24: =(Q23*'AP04'!$R24)/($I$5-A23) -> 835.7571 | H24: =H23 -> 0 | I24: =I23 -> 0 | J24: =J23 -> 25 | K24: =K23 -> 0 | L24: =L23 -> 0 | M24: ='AP03'!D17 -> 2601.89 | N24: =SUM('AP04'!$F24:$L24) -> 2519.3622 | O24: ='AP04'!$M24-'AP04'!$N24 -> 82.527818 | P24: =Q23*('AP04'!$R24-1) -> 0 | Q24: =(Q23*'AP04'!$R24)-'AP04'!$G24-'AP04'!$O24*2 -> 292349.93 | R24: =R23 -> 1
A25: =A24+1 -> 11 | B25: =EDATE(B24,1) -> 43576 | C25: =C24 -> 0.07 | D25: =D24 -> 0.005654 | E25: ='AP04'!$F25+'AP04'!$G25 -> 2488.232 | F25: =(Q24*'AP04'!$R25)*'AP04'!$D25 -> 1652.9465 | G25: =(Q24*'AP04'!$R25)/($I$5-A24) -> 835.28551 | H25: =H24 -> 0 | I25: =I24 -> 0 | J25: =J24 -> 25 | K25: =K24 -> 0 | L25: =L24 -> 0 | M25: ='AP03'!D18 -> 2597.05 | N25: =SUM('AP04'!$F25:$L25) -> 2513.232 | O25: ='AP04'!$M25-'AP04'!$N25 -> 83.818001 | P25: =Q24*('AP04'!$R25-1) -> 0 | Q25: =(Q24*'AP04'!$R25)-'AP04'!$G25-'AP04'!$O25*2 -> 291347.01 | R25: =R24 -> 1
A26: =A25+1 -> 12 | B26: =EDATE(B25,1) -> 43606 | C26: =C25 -> 0.07 | D26: =D25 -> 0.005654 | E26: ='AP04'!$F26+'AP04'!$G26 -> 2482.0811 | F26: =(Q25*'AP04'!$R26)*'AP04'!$D26 -> 1647.276 | G26: =(Q25*'AP04'!$R26)/($I$5-A25) -> 834.80518 | H26: =H25 -> 0 | I26: =I25 -> 0 | J26: =J25 -> 25 | K26: =K25 -> 0 | L26: =L25 -> 0 | M26: ='AP03'!D19 -> 2592.21 | N26: =SUM('AP04'!$F26:$L26) -> 2507.0811 | O26: ='AP04'!$M26-'AP04'!$N26 -> 85.128851 | P26: =Q25*('AP04'!$R26-1) -> 0 | Q26: =(Q25*'AP04'!$R26)-'AP04'!$G26-'AP04'!$O26*2 -> 290341.94 | R26: =R25 -> 1
A27: =A26+1 -> 13 | B27: =EDATE(B26,1) -> 43637 | C27: =C26 -> 0.07 | D27: =D26 -> 0.005654 | E27: ='AP04'!$F27+'AP04'!$G27 -> 2475.9093 | F27: =(Q26*'AP04'!$R27)*'AP04'!$D27 -> 1641.5933 | G27: =(Q26*'AP04'!$R27)/($I$5-A26) -> 834.31593 | H27: =H26 -> 0 | I27: =I26 -> 0 | J27: =J26 -> 25 | K27: =K26 -> 0 | L27: =L26 -> 0 | M27: ='AP03'!D20 -> 2587.38 | N27: =SUM('AP04'!$F27:$L27) -> 2500.9093 | O27: ='AP04'!$M27-'AP04'!$N27 -> 86.470723 | P27: =Q26*('AP04'!$R27-1) -> 0 | Q27: =(Q26*'AP04'!$R27)-'AP04'!$G27-'AP04'!$O27*2 -> 289334.69 | R27: =R26 -> 1
... A35: =A34+1 -> 21 | B35: =EDATE(B34,1) -> 43882 | C35: =C34 -> 0.07 | D35: =D34 -> 0.005654 | E35: ='AP04'!$F35+'AP04'!$G35 -> 2425.7091 | F35: =(Q34*'AP04'!$R35)*'AP04'!$D35 -> 1595.6577 | G35: =(Q34*'AP04'!$R35)/($I$5-A34) -> 830.05144 | H35: =H34 -> 0 | I35: =I34 -> 0 | J35: =J34 -> 25 | K35: =K34 -> 0 | L35: =L34 -> 0 | M35: ='AP03'!D28 -> 2558.55 | N35: =SUM('AP04'!$F35:$L35) -> 2450.7091 | O35: ='AP04'!$M35-'AP04'!$N35 -> 107.84086 | P35: =Q34*('AP04'!$R35-1) -> 0 | Q35: =(Q34*'AP04'!$R35)-'AP04'!$G35-'AP04'!$O35*2 -> 281171.76 | R35: =R34 -> 1
A36: =A35+1 -> 22 | B36: =EDATE(B35,1) -> 43911 | C36: 0.062 | D36: 0.005025 | E36: ='AP04'!$F36+'AP04'!$G36 -> 2242.3033 | F36: =(Q35*'AP04'!$R36)*'AP04'!$D36 -> 1412.8881 | G36: =(Q35*'AP04'!$R36)/($I$5-A35) -> 829.41522 | H36: =H35 -> 0 | I36: =I35 -> 0 | J36: =J35 -> 25 | K36: =K35 -> 0 | L36: =L35 -> 0 | M36: ='AP03'!D29 -> 2374.56 | N36: =SUM('AP04'!$F36:$L36) -> 2267.3033 | O36: ='AP04'!$M36-'AP04'!$N36 -> 107.2567 | P36: =Q35*('AP04'!$R36-1) -> 0 | Q36: =(Q35*'AP04'!$R36)-'AP04'!$G36-'AP04'!$O36*2 -> 280127.83 | R36: =R35 -> 1
A37: =A36+1 -> 23 | B37: =EDATE(B36,1) -> 43942 | C37: 0.062 | D37: =D36 -> 0.005025 | E37: ='AP04'!$F37+'AP04'!$G37 -> 2236.4229 | F37: =(Q36*'AP04'!$R37)*'AP04'!$D37 -> 1407.6423 | G37: =(Q36*'AP04'!$R37)/($I$5-A36) -> 828.78056 | H37: =H36 -> 0 | I37: =I36 -> 0 | J37: =J36 -> 25 | K37: =K36 -> 0 | L37: =L36 -> 0 | M37: ='AP03'!D30 -> 2370.23 | N37: =SUM('AP04'!$F37:$L37) -> 2261.4229 | O37: ='AP04'!$M37-'AP04'!$N37 -> 108.8071 | P37: =Q36*('AP04'!$R37-1) -> 0 | Q37: =(Q36*'AP04'!$R37)-'AP04'!$G37-'AP04'!$O37*2 -> 279081.43 | R37: =R36 -> 1
A38: =A37+1 -> 24 | B38: =EDATE(B37,1) -> 43972 | C38: 0.062 | D38: =D37 -> 0.005025 | E38: ='AP04'!$F38+'AP04'!$G38 -> 2230.519 | F38: =(Q37*'AP04'!$R38)*'AP04'!$D38 -> 1402.3842 | G38: =(Q37*'AP04'!$R38)/($I$5-A37) -> 828.13482 | H38: =H37 -> 0 | I38: =I37 -> 0 | J38: =J37 -> 25 | K38: =K37 -> 0 | L38: =L37 -> 0 | M38: ='AP03'!D31 -> 2365.89 | N38: =SUM('AP04'!$F38:$L38) -> 2255.519 | O38: ='AP04'!$M38-'AP04'!$N38 -> 110.37097 | P38: =Q37*('AP04'!$R38-1) -> 0 | Q38: =(Q37*'AP04'!$R38)-'AP04'!$G38-'AP04'!$O38*2 -> 278032.56 | R38: =R37 -> 1
A39: =A38+1 -> 25 | B39: =EDATE(B38,1) -> 44003 | C39: 0.062 | D39: =D38 -> 0.005025 | E39: ='AP04'!$F39+'AP04'!$G39 -> 2224.5915 | F39: =(Q38*'AP04'!$R39)*'AP04'!$D39 -> 1397.1136 | G39: =(Q38*'AP04'!$R39)/($I$5-A38) -> 827.47785 | H39: =H38 -> 0 | I39: =I38 -> 0 | J39: =J38 -> 25 | K39: =K38 -> 0 | L39: =L38 -> 0 | M39: ='AP03'!D32 -> 2361.55 | N39: =SUM('AP04'!$F39:$L39) -> 2249.5915 | O39: ='AP04'!$M39-'AP04'!$N39 -> 111.95855 | P39: =Q38*('AP04'!$R39-1) -> 0 | Q39: =(Q38*'AP04'!$R39)-'AP04'!$G39-'AP04'!$O39*2 -> 276981.16 | R39: =R38 -> 1
A40: =A39+1 -> 26 | B40: =EDATE(B39,1) -> 44033 | C40: 0.062 | D40: =D39 -> 0.005025 | E40: ='AP04'!$F40+'AP04'!$G40 -> 2218.6398 | F40: =(Q39*'AP04'!$R40)*'AP04'!$D40 -> 1391.8303 | G40: =(Q39*'AP04'!$R40)/($I$5-A39) -> 826.80944 | H40: =H39 -> 0 | I40: =I39 -> 0 | J40: =J39 -> 25 | K40: =K39 -> 0 | L40: =L39 -> 0 | M40: ='AP03'!D33 -> 2357.21 | N40: =SUM('AP04'!$F40:$L40) -> 2243.6398 | O40: ='AP04'!$M40-'AP04'!$N40 -> 113.57021 | P40: =Q39*('AP04'!$R40-1) -> 0 | Q40: =(Q39*'AP04'!$R40)-'AP04'!$G40-'AP04'!$O40*2 -> 275927.21 | R40: =R39 -> 1
A41: =A40+1 -> 27 | B41: =EDATE(B40,1) -> 44064 | C41: 0.062 | D41: =D40 -> 0.005025 | E41: ='AP04'!$F41+'AP04'!$G41 -> 2212.6636 | F41: =(Q40*'AP04'!$R41)*'AP04'!$D41 -> 1386.5342 | G41: =(Q40*'AP04'!$R41)/($I$5-A40) -> 826.12938 | H41: =H40 -> 0 | I41: =I40 -> 0 | J41: =J40 -> 25 | K41: =K40 -> 0 | L41: =L40 -> 0 | M41: ='AP03'!D34 -> 2352.88 | N41: =SUM('AP04'!$F41:$L41) -> 2237.6636 | O41: ='AP04'!$M41-'AP04'!$N41 -> 115.21637 | P41: =Q40*('AP04'!$R41-1) -> 0 | Q41: =(Q40*'AP04'!$R41)-'AP04'!$G41-'AP04'!$O41*2 -> 274870.65 | R41: =R40 -> 1
A42: =A41+1 -> 28 | B42: =EDATE(B41,1) -> 44095 | C42: =C41 -> 0.062 | D42: =D41 -> 0.005025 | E42: ='AP04'!$F42+'AP04'!$G42 -> 2206.6624 | F42: =(Q41*'AP04'!$R42)*'AP04'!$D42 -> 1381.225 | G42: =(Q41*'AP04'!$R42)/($I$5-A41) -> 825.43739 | H42: =H41 -> 0 | I42: =I41 -> 0 | J42: =J41 -> 25 | K42: =K41 -> 0 | L42: =L41 -> 0 | M42: ='AP03'!D35 -> 2348.54 | N42: =SUM('AP04'!$F42:$L42) -> 2231.6624 | O42: ='AP04'!$M42-'AP04'!$N42 -> 116.87759 | P42: =Q41*('AP04'!$R42-1) -> 0 | Q42: =(Q41*'AP04'!$R42)-'AP04'!$G42-'AP04'!$O42*2 -> 273811.46 | R42: =R41 -> 1
A43: =A42+1 -> 29 | B43: =EDATE(B42,1) -> 44125 | C43: =C42 -> 0.062 | D43: =D42 -> 0.005025 | E43: ='AP04'!$F43+'AP04'!$G43 -> 2200.6359 | F43: =(Q42*'AP04'!$R43)*'AP04'!$D43 -> 1375.9026 | G43: =(Q42*'AP04'!$R43)/($I$5-A42) -> 824.73331 | H43: =H42 -> 0 | I43: =I42 -> 0 | J43: =J42 -> 25 | K43: =K42 -> 0 | L43: =L42 -> 0 | M43: ='AP03'!D36 -> 2344.34 | N43: =SUM('AP04'!$F43:$L43) -> 2225.6359 | O43: ='AP04'!$M43-'AP04'!$N43 -> 118.70411 | P43: =Q42*('AP04'!$R43-1) -> 0 | Q43: =(Q42*'AP04'!$R43)-'AP04'!$G43-'AP04'!$O43*2 -> 272749.32 | R43: =R42 -> 1
A44: =A43+1 -> 30 | B44: =EDATE(B43,1) -> 44156 | C44: =C43 -> 0.062 | D44: =D43 -> 0.005025 | E44: ='AP04'!$F44+'AP04'!$G44 -> 2194.5814 | F44: =(Q43*'AP04'!$R44)*'AP04'!$D44 -> 1370.5653 | G44: =(Q43*'AP04'!$R44)/($I$5-A43) -> 824.01606 | H44: =H43 -> 0 | I44: =I43 -> 0 | J44: =J43 -> 25 | K44: =K43 -> 0 | L44: =L43 -> 0 | M44: ='AP03'!D37 -> 2340 | N44: =SUM('AP04'!$F44:$L44) -> 2219.5814 | O44: ='AP04'!$M44-'AP04'!$N44 -> 120.41862 | P44: =Q43*('AP04'!$R44-1) -> 0 | Q44: =(Q43*'AP04'!$R44)-'AP04'!$G44-'AP04'!$O44*2 -> 271684.46 | R44: =R43 -> 1
A45: =A44+1 -> 31 | B45: =EDATE(B44,1) -> 44186 | C45: =C44 -> 0.062 | D45: =D44 -> 0.005025 | E45: ='AP04'!$F45+'AP04'!$G45 -> 2188.5007 | F45: =(Q44*'AP04'!$R45)*'AP04'!$D45 -> 1365.2144 | G45: =(Q44*'AP04'!$R45)/($I$5-A44) -> 823.28625 | H45: =H44 -> 0 | I45: =I44 -> 0 | J45: =J44 -> 25 | K45: =K44 -> 0 | L45: =L44 -> 0 | M45: ='AP03'!D38 -> 2336.59 | N45: =SUM('AP04'!$F45:$L45) -> 2213.5007 | O45: ='AP04'!$M45-'AP04'!$N45 -> 123.08932 | P45: =Q44*('AP04'!$R45-1) -> 0 | Q45: =(Q44*'AP04'!$R45)-'AP04'!$G45-'AP04'!$O45*2 -> 270615 | R45: =R44 -> 1
A46: =A45+1 -> 32 | B46: =EDATE(B45,1) -> 44217 | C46: =C45 -> 0.062 | D46: =D45 -> 0.005025 | E46: ='AP04'!$F46+'AP04'!$G46 -> 2182.3784 | F46: =(Q45*'AP04'!$R46)*'AP04'!$D46 -> 1359.8404 | G46: =(Q45*'AP04'!$R46)/($I$5-A45) -> 822.53799 | H46: =H45 -> 0 | I46: =I45 -> 0 | J46: =J45 -> 25 | K46: =K45 -> 0 | L46: =L45 -> 0 | M46: ='AP03'!D39 -> 2332.25 | N46: =SUM('AP04'!$F46:$L46) -> 2207.3784 | O46: ='AP04'!$M46-'AP04'!$N46 -> 124.87164 | P46: =Q45*('AP04'!$R46-1) -> 0 | Q46: =(Q45*'AP04'!$R46)-'AP04'!$G46-'AP04'!$O46*2 -> 269542.72 | R46: =R45 -> 1
A47: =A46+1 -> 33 | B47: =EDATE(B46,1) -> 44248 | C47: =C46 -> 0.062 | D47: =D46 -> 0.005025 | E47: ='AP04'!$F47+'AP04'!$G47 -> 2176.2287 | F47: =(Q46*'AP04'!$R47)*'AP04'!$D47 -> 1354.4522 | G47: =(Q46*'AP04'!$R47)/($I$5-A46) -> 821.77658 | H47: =H46 -> 0 | I47: =I46 -> 0 | J47: =J46 -> 25 | K47: =K46 -> 0 | L47: =L46 -> 0 | M47: ='AP03'!D40 -> 2328.53 | N47: =SUM('AP04'!$F47:$L47) -> 2201.2287 | O47: ='AP04'!$M47-'AP04'!$N47 -> 127.30127 | P47: =Q46*('AP04'!$R47-1) -> 0 | Q47: =(Q46*'AP04'!$R47)-'AP04'!$G47-'AP04'!$O47*2 -> 268466.34 | R47: =R46 -> 1
A48: =A47+1 -> 34 | B48: =EDATE(B47,1) -> 44276 | C48: =C47 -> 0.062 | D48: =D47 -> 0.005025 | E48: ='AP04'!$F48+'AP04'!$G48 -> 2170.0413 | F48: =(Q47*'AP04'!$R48)*'AP04'!$D48 -> 1349.0433 | G48: =(Q47*'AP04'!$R48)/($I$5-A47) -> 820.99798 | H48: =H47 -> 0 | I48: =I47 -> 0 | J48: =J47 -> 25 | K48: =K47 -> 0 | L48: =L47 -> 0 | M48: ='AP03'!D41 -> 2324.19 | N48: =SUM('AP04'!$F48:$L48) -> 2195.0413 | O48: ='AP04'!$M48-'AP04'!$N48 -> 129.14867 | P48: =Q47*('AP04'!$R48-1) -> 0 | Q48: =(Q47*'AP04'!$R48)-'AP04'!$G48-'AP04'!$O48*2 -> 267387.04 | R48: =R47 -> 1
A49: =A48+1 -> 35 | B49: =EDATE(B48,1) -> 44307 | C49: =C48 -> 0.062 | D49: =D48 -> 0.005025 | E49: ='AP04'!$F49+'AP04'!$G49 -> 2163.8255 | F49: =(Q48*'AP04'!$R49)*'AP04'!$D49 -> 1343.6199 | G49: =(Q48*'AP04'!$R49)/($I$5-A48) -> 820.20565 | H49: =H48 -> 0 | I49: =I48 -> 0 | J49: =J48 -> 25 | K49: =K48 -> 0 | L49: =L48 -> 0 | M49: ='AP03'!D42 -> 2319.85 | N49: =SUM('AP04'!$F49:$L49) -> 2188.8255 | O49: ='AP04'!$M49-'AP04'!$N49 -> 131.02446 | P49: =Q48*('AP04'!$R49-1) -> 0 | Q49: =(Q48*'AP04'!$R49)-'AP04'!$G49-'AP04'!$O49*2 -> 266304.79 | R49: =R48 -> 1
A50: =A49+1 -> 36 | B50: =EDATE(B49,1) -> 44337 | C50: =C49 -> 0.062 | D50: =D49 -> 0.005025 | E50: ='AP04'!$F50+'AP04'!$G50 -> 2157.5809 | F50: =(Q49*'AP04'!$R50)*'AP04'!$D50 -> 1338.1816 | G50: =(Q49*'AP04'!$R50)/($I$5-A49) -> 819.39935 | H50: =H49 -> 0 | I50: =I49 -> 0 | J50: =J49 -> 25 | K50: =K49 -> 0 | L50: =L49 -> 0 | M50: ='AP03'!D43 -> 2315.51 | N50: =SUM('AP04'!$F50:$L50) -> 2182.5809 | O50: ='AP04'!$M50-'AP04'!$N50 -> 132.92909 | P50: =Q49*('AP04'!$R50-1) -> 0 | Q50: =(Q49*'AP04'!$R50)-'AP04'!$G50-'AP04'!$O50*2 -> 265219.53 | R50: =R49 -> 1
A51: =A50+1 -> 37 | B51: =EDATE(B50,1) -> 44368 | C51: =C50 -> 0.062 | D51: =D50 -> 0.005025 | E51: ='AP04'!$F51+'AP04'!$G51 -> 2151.3069 | F51: =(Q50*'AP04'!$R51)*'AP04'!$D51 -> 1332.7281 | G51: =(Q50*'AP04'!$R51)/($I$5-A50) -> 818.5788 | H51: =H50 -> 0 | I51: =I50 -> 0 | J51: =J50 -> 25 | K51: =K50 -> 0 | L51: =L50 -> 0 | M51: ='AP03'!D44 -> 2311.16 | N51: =SUM('AP04'!$F51:$L51) -> 2176.3069 | O51: ='AP04'!$M51-'AP04'!$N51 -> 134.85306 | P51: =Q50*('AP04'!$R51-1) -> 0 | Q51: =(Q50*'AP04'!$R51)-'AP04'!$G51-'AP04'!$O51*2 -> 264131.25 | R51: =R50 -> 1
A52: =A51+1 -> 38 | B52: =EDATE(B51,1) -> 44398 | C52: =C51 -> 0.062 | D52: =D51 -> 0.005025 | E52: ='AP04'!$F52+'AP04'!$G52 -> 2145.0033 | F52: =(Q51*'AP04'!$R52)*'AP04'!$D52 -> 1327.2595 | G52: =(Q51*'AP04'!$R52)/($I$5-A51) -> 817.7438 | H52: =H51 -> 0 | I52: =I51 -> 0 | J52: =J51 -> 25 | K52: =K51 -> 0 | L52: =L51 -> 0 | M52: ='AP03'!D45 -> 2306.81 | N52: =SUM('AP04'!$F52:$L52) -> 2170.0033 | O52: ='AP04'!$M52-'AP04'!$N52 -> 136.80669 | P52: =Q51*('AP04'!$R52-1) -> 0 | Q52: =(Q51*'AP04'!$R52)-'AP04'!$G52-'AP04'!$O52*2 -> 263039.89 | R52: =R51 -> 1
A53: =A52+1 -> 39 | B53: =EDATE(B52,1) -> 44429 | C53: =C52 -> 0.062 | D53: =D52 -> 0.005025 | E53: ='AP04'!$F53+'AP04'!$G53 -> 2138.6695 | F53: =(Q52*'AP04'!$R53)*'AP04'!$D53 -> 1321.7754 | G53: =(Q52*'AP04'!$R53)/($I$5-A52) -> 816.89406 | H53: =H52 -> 0 | I53: =I52 -> 0 | J53: =J52 -> 25 | K53: =K52 -> 0 | L53: =L52 -> 0 | M53: ='AP03'!D46 -> 2302.47 | N53: =SUM('AP04'!$F53:$L53) -> 2163.6695 | O53: ='AP04'!$M53-'AP04'!$N53 -> 138.80049 | P53: =Q52*('AP04'!$R53-1) -> 0 | Q53: =(Q52*'AP04'!$R53)-'AP04'!$G53-'AP04'!$O53*2 -> 261945.39 | R53: =R52 -> 1
... A57: =A56+1 -> 43 | B57: =EDATE(B56,1) -> 44551 | C57: =C56 -> 0.062 | D57: =D56 -> 0.005025 | E57: ='AP04'!$F57+'AP04'!$G57 -> 2113.0208 | F57: =(Q56*'AP04'!$R57)*'AP04'!$D57 -> 1299.6792 | G57: =(Q56*'AP04'!$R57)/($I$5-A56) -> 813.34161 | H57: =H56 -> 0 | I57: =I56 -> 0 | J57: =J56 -> 25 | K57: =K56 -> 0 | L57: =L56 -> 0 | M57: ='AP03'!D50 -> 2294.47 | N57: =SUM('AP04'!$F57:$L57) -> 2138.0208 | O57: ='AP04'!$M57-'AP04'!$N57 -> 156.44917 | P57: =Q56*('AP04'!$R57-1) -> 0 | Q57: =(Q56*'AP04'!$R57)-'AP04'!$G57-'AP04'!$O57*2 -> 257516.39 | R57: =R56 -> 1
A58: =A57+1 -> 44 | B58: =EDATE(B57,1) -> 44582 | C58: =C57 -> 0.062 | D58: =D57 -> 0.005025 | E58: ='AP04'!$F58+'AP04'!$G58 -> 2108.8915 | F58: =(Q57*'AP04'!$R58)*'AP04'!$D58 -> 1295.5662 | G58: =(Q57*'AP04'!$R58)/($I$5-A57) -> 813.32531 | H58: =H57 -> 0 | I58: =I57 -> 0 | J58: =J57 -> 25 | K58: =K57 -> 0 | L58: =L57 -> 0 | M58: ='AP03'!D51 -> 2292.79 | N58: =SUM('AP04'!$F58:$L58) -> 2133.8915 | O58: ='AP04'!$M58-'AP04'!$N58 -> 158.89847 | P58: =Q57*('AP04'!$R58-1) -> 307.73209 | Q58: =(Q57*'AP04'!$R58)-'AP04'!$G58-'AP04'!$O58*2 -> 256693 | R58: 1.001195
A59: =A58+1 -> 45 | B59: =EDATE(B58,1) -> 44613 | C59: =C58 -> 0.062 | D59: =D58 -> 0.005025 | E59: ='AP04'!$F59+'AP04'!$G59 -> 2103.9699 | F59: =(Q58*'AP04'!$R59)*'AP04'!$D59 -> 1290.9671 | G59: =(Q58*'AP04'!$R59)/($I$5-A58) -> 813.00279 | H59: =H58 -> 0 | I59: =I58 -> 0 | J59: =J58 -> 25 | K59: =K58 -> 0 | L59: =L58 -> 0 | M59: ='AP03'!D52 -> 2290.94 | N59: =SUM('AP04'!$F59:$L59) -> 2128.9699 | O59: ='AP04'!$M59-'AP04'!$N59 -> 161.97009 | P59: =Q58*('AP04'!$R59-1) -> 215.87881 | Q59: =(Q58*'AP04'!$R59)-'AP04'!$G59-'AP04'!$O59*2 -> 255771.94 | R59: 1.000841
A60: =A59+1 -> 46 | B60: =EDATE(B59,1) -> 44641 | C60: =C59 -> 0.062 | D60: =D59 -> 0.005025 | E60: ='AP04'!$F60+'AP04'!$G60 -> 2097.2284 | F60: =(Q59*'AP04'!$R60)*'AP04'!$D60 -> 1285.254 | G60: =(Q59*'AP04'!$R60)/($I$5-A59) -> 811.9744 | H60: =H59 -> 0 | I60: =I59 -> 0 | J60: =J59 -> 25 | K60: =K59 -> 0 | L60: =L59 -> 0 | M60: ='AP03'!D53 -> 2286.56 | N60: =SUM('AP04'!$F60:$L60) -> 2122.2284 | O60: ='AP04'!$M60-'AP04'!$N60 -> 164.33161 | P60: =Q59*('AP04'!$R60-1) -> 0 | Q60: =(Q59*'AP04'!$R60)-'AP04'!$G60-'AP04'!$O60*2 -> 254631.3 | R60: 1
A61: =A60+1 -> 47 | B61: =EDATE(B60,1) -> 44672 | C61: =C60 -> 0.062 | D61: =D60 -> 0.005025 | E61: ='AP04'!$F61+'AP04'!$G61 -> 2093.2136 | F61: =(Q60*'AP04'!$R61)*'AP04'!$D61 -> 1281.2138 | G61: =(Q60*'AP04'!$R61)/($I$5-A60) -> 811.99975 | H61: =H60 -> 0 | I61: =I60 -> 0 | J61: =J60 -> 25 | K61: =K60 -> 0 | L61: =L60 -> 0 | M61: ='AP03'!D54 -> 2282.17 | N61: =SUM('AP04'!$F61:$L61) -> 2118.2136 | O61: ='AP04'!$M61-'AP04'!$N61 -> 163.95644 | P61: =Q60*('AP04'!$R61-1) -> 336.62258 | Q61: =(Q60*'AP04'!$R61)-'AP04'!$G61-'AP04'!$O61*2 -> 253828.01 | R61: 1.001322
A62: =A61+1 -> 48 | B62: =EDATE(B61,1) -> 44702 | C62: =C61 -> 0.062 | D62: =D61 -> 0.005025 | E62: ='AP04'!$F62+'AP04'!$G62 -> 2089.1544 | F62: =(Q61*'AP04'!$R62)*'AP04'!$D62 -> 1277.1464 | G62: =(Q61*'AP04'!$R62)/($I$5-A61) -> 812.00797 | H62: =H61 -> 0 | I62: =I61 -> 0 | J62: =J61 -> 25 | K62: =K61 -> 0 | L62: =L61 -> 0 | M62: ='AP03'!D55 -> 2283.71 | N62: =SUM('AP04'!$F62:$L62) -> 2114.1544 | O62: ='AP04'!$M62-'AP04'!$N62 -> 169.5556 | P62: =Q61*('AP04'!$R62-1) -> 330.48407 | Q62: =(Q61*'AP04'!$R62)-'AP04'!$G62-'AP04'!$O62*2 -> 253007.37 | R62: 1.001302
A63: =A62+1 -> 49 | B63: =EDATE(B62,1) -> 44733 | C63: =C62 -> 0.062 | D63: =D62 -> 0.005025 | E63: =E62 -> 2089.1544 | F63: =(Q62*'AP04'!$R63)*'AP04'!$D63 -> 1272.7122 | G63: =(Q62*'AP04'!$R63)/($I$5-A62) -> 811.78227 | H63: =H62 -> 0 | I63: =I62 -> 0 | J63: =J62 -> 25 | K63: =K62 -> 0 | L63: =L62 -> 0 | M63: ='AP03'!D56 -> 2284.69 | N63: =SUM('AP04'!$F63:$L63) -> 2109.4945 | O63: ='AP04'!$M63-'AP04'!$N63 -> 175.19549 | P63: =Q62*('AP04'!$R63-1) -> 268.69383 | Q63: =(Q62*'AP04'!$R63)-'AP04'!$G63-'AP04'!$O63*2 -> 252113.9 | R63: 1.001062
A64: =A63+1 -> 50 | B64: =EDATE(B63,1) -> 44763 | C64: =C63 -> 0.062 | D64: =D63 -> 0.005025 | E64: =E63 -> 2089.1544 | F64: =(Q63*'AP04'!$R64)*'AP04'!$D64 -> 1269.3085 | G64: =(Q63*'AP04'!$R64)/($I$5-A63) -> 812.2145 | H64: =H63 -> 0 | I64: =I63 -> 0 | J64: =J63 -> 25 | K64: =K63 -> 0 | L64: =L63 -> 0 | M64: ='AP03'!D57 -> 2281.63 | N64: =SUM('AP04'!$F64:$L64) -> 2106.523 | O64: ='AP04'!$M64-'AP04'!$N64 -> 175.10698 | P64: =Q63*('AP04'!$R64-1) -> 484.81502 | Q64: =(Q63*'AP04'!$R64)-'AP04'!$G64-'AP04'!$O64*2 -> 251436.28 | R64: 1.001923
A65: =A64+1 -> 51 | B65: =EDATE(B64,1) -> 44794 | C65: =C64 -> 0.062 | D65: =D64 -> 0.005025 | E65: =E64 -> 2089.1544 | F65: =(Q64*'AP04'!$R65)*'AP04'!$D65 -> 1266.108 | G65: =(Q64*'AP04'!$R65)/($I$5-A64) -> 812.77995 | H65: =H64 -> 0 | I65: =I64 -> 0 | J65: =J64 -> 25 | K65: =K64 -> 0 | L65: =L64 -> 0 | M65: ='AP03'!D58 -> 2281.94 | N65: =SUM('AP04'!$F65:$L65) -> 2103.8879 | O65: ='AP04'!$M65-'AP04'!$N65 -> 178.05209 | P65: =Q64*('AP04'!$R65-1) -> 525.50183 | Q65: =(Q64*'AP04'!$R65)-'AP04'!$G65-'AP04'!$O65*2 -> 250792.9 | R65: 1.00209
A66: =A65+1 -> 52 | B66: =EDATE(B65,1) -> 44825 | C66: =C65 -> 0.062 | D66: =D65 -> 0.005025 | E66: =E65 -> 2089.1544 | F66: =(Q65*'AP04'!$R66)*'AP04'!$D66 -> 1262.4927 | G66: =(Q65*'AP04'!$R66)/($I$5-A65) -> 813.08194 | H66: =H65 -> 0 | I66: =I65 -> 0 | J66: =J65 -> 25 | K66: =K65 -> 0 | L66: =L65 -> 0 | M66: ='AP03'!D59 -> 2281.56 | N66: =SUM('AP04'!$F66:$L66) -> 2100.5746 | O66: ='AP04'!$M66-'AP04'!$N66 -> 180.9854 | P66: =Q65*('AP04'!$R66-1) -> 449.42088 | Q66: =(Q65*'AP04'!$R66)-'AP04'!$G66-'AP04'!$O66*2 -> 250067.27 | R66: 1.001792
A67: =A66+1 -> 53 | B67: =EDATE(B66,1) -> 44855 | C67: =C66 -> 0.062 | D67: =D66 -> 0.005025 | E67: =E66 -> 2089.1544 | F67: =(Q66*'AP04'!$R67)*'AP04'!$D67 -> 1258.8951 | G67: =(Q66*'AP04'!$R67)/($I$5-A66) -> 813.39737 | H67: =H66 -> 0 | I67: =I66 -> 0 | J67: =J66 -> 25 | K67: =K66 -> 0 | L67: =L66 -> 0 | M67: ='AP03'!D60 -> 2281.26 | N67: =SUM('AP04'!$F67:$L67) -> 2097.2925 | O67: ='AP04'!$M67-'AP04'!$N67 -> 183.96751 | P67: =Q66*('AP04'!$R67-1) -> 459.1235 | Q67: =(Q66*'AP04'!$R67)-'AP04'!$G67-'AP04'!$O67*2 -> 249345.06 | R67: 1.001836
A68: =A67+1 -> 54 | B68: =EDATE(B67,1) -> 44886 | C68: =C67 -> 0.062 | D68: =D67 -> 0.005025 | E68: =E67 -> 2089.1544 | F68: =(Q67*'AP04'!$R68)*'AP04'!$D68 -> 1254.3835 | G68: =(Q67*'AP04'!$R68)/($I$5-A67) -> 813.12236 | H68: =H67 -> 0 | I68: =I67 -> 0 | J68: =J67 -> 25 | K68: =K67 -> 0 | L68: =L67 -> 0 | M68: ='AP03'!D61 -> 2279.39 | N68: =SUM('AP04'!$F68:$L68) -> 2092.5059 | O68: ='AP04'!$M68-'AP04'!$N68 -> 186.88411 | P68: =Q67*('AP04'!$R68-1) -> 283.50533 | Q68: =(Q67*'AP04'!$R68)-'AP04'!$G68-'AP04'!$O68*2 -> 248441.67 | R68: 1.001137
A69: =A68+1 -> 55 | B69: =EDATE(B68,1) -> 44916 | C69: =C68 -> 0.062 | D69: =D68 -> 0.005025 | E69: =E68 -> 2089.1544 | F69: =(Q68*'AP04'!$R69)*'AP04'!$D69 -> 1251.0323 | G69: =(Q68*'AP04'!$R69)/($I$5-A68) -> 813.6002 | H69: =H68 -> 0 | I69: =I68 -> 0 | J69: =J68 -> 25 | K69: =K68 -> 0 | L69: =L68 -> 0 | M69: ='AP03'!D62 -> 2281.2 | N69: =SUM('AP04'!$F69:$L69) -> 2089.6326 | O69: ='AP04'!$M69-'AP04'!$N69 -> 191.56745 | P69: =Q68*('AP04'!$R69-1) -> 519.98842 | Q69: =(Q68*'AP04'!$R69)-'AP04'!$G69-'AP04'!$O69*2 -> 247764.93 | R69: 1.002093
A70: =A69+1 -> 56 | B70: =EDATE(B69,1) -> 44947 | C70: =C69 -> 0.062 | D70: =D69 -> 0.005025 | E70: =E69 -> 2089.1544 | F70: =(Q69*'AP04'!$R70)*'AP04'!$D70 -> 1248.0193 | G70: =(Q69*'AP04'!$R70)/($I$5-A69) -> 814.30177 | H70: =H69 -> 0 | I70: =I69 -> 0 | J70: =J69 -> 25 | K70: =K69 -> 0 | L70: =L69 -> 0 | M70: ='AP03'!D63 -> 2282.16 | N70: =SUM('AP04'!$F70:$L70) -> 2087.321 | O70: ='AP04'!$M70-'AP04'!$N70 -> 194.83898 | P70: =Q69*('AP04'!$R70-1) -> 597.11347 | Q70: =(Q69*'AP04'!$R70)-'AP04'!$G70-'AP04'!$O70*2 -> 247158.06 | R70: 1.00241
A71: =A70+1 -> 57 | B71: =EDATE(B70,1) -> 44978 | C71: =C70 -> 0.062 | D71: =D70 -> 0.005025 | E71: =E70 -> 2089.1544 | F71: =(Q70*'AP04'!$R71)*'AP04'!$D71 -> 1243.8173 | G71: =(Q70*'AP04'!$R71)/($I$5-A70) -> 814.22971 | H71: =H70 -> 0 | I71: =I70 -> 0 | J71: =J70 -> 25 | K71: =K70 -> 0 | L71: =L70 -> 0 | M71: ='AP03'!D64 -> 2281.76 | N71: =SUM('AP04'!$F71:$L71) -> 2083.047 | O71: ='AP04'!$M71-'AP04'!$N71 -> 198.71299 | P71: =Q70*('AP04'!$R71-1) -> 367.77119 | Q71: =(Q70*'AP04'!$R71)-'AP04'!$G71-'AP04'!$O71*2 -> 246314.18 | R71: 1.001488
A72: =A71+1 -> 58 | B72: =EDATE(B71,1) -> 45006 | C72: =C71 -> 0.062 | D72: =D71 -> 0.005025 | E72: =E71 -> 2089.1544 | F72: =(Q71*'AP04'!$R72)*'AP04'!$D72 -> 1239.0828 | G72: =(Q71*'AP04'!$R72)/($I$5-A71) -> 813.8074 | H72: =H71 -> 0 | I72: =I71 -> 0 | J72: =J71 -> 25 | K72: =K71 -> 0 | L72: =L71 -> 0 | M72: ='AP03'!D65 -> 2279.74 | N72: =SUM('AP04'!$F72:$L72) -> 2077.8902 | O72: ='AP04'!$M72-'AP04'!$N72 -> 201.84979 | P72: =Q71*('AP04'!$R72-1) -> 269.46771 | Q72: =(Q71*'AP04'!$R72)-'AP04'!$G72-'AP04'!$O72*2 -> 245366.14 | R72: 1.001094
A73: =A72+1 -> 59 | B73: =EDATE(B72,1) -> 45037 | C73: =C72 -> 0.062 | D73: =D72 -> 0.005025 | E73: =E72 -> 2089.1544 | F73: =(Q72*'AP04'!$R73)*'AP04'!$D73 -> 1235.5405 | G73: =(Q72*'AP04'!$R73)/($I$5-A72) -> 814.1679 | H73: =H72 -> 0 | I73: =I72 -> 0 | J73: =J72 -> 25 | K73: =K72 -> 0 | L73: =L72 -> 0 | M73: ='AP03'!D66 -> 2279.98 | N73: =SUM('AP04'!$F73:$L73) -> 2074.7084 | O73: ='AP04'!$M73-'AP04'!$N73 -> 205.2716 | P73: =Q72*('AP04'!$R73-1) -> 512.56986 | Q73: =(Q72*'AP04'!$R73)-'AP04'!$G73-'AP04'!$O73*2 -> 244654 | R73: 1.002089
A74: =A73+1 -> 60 | B74: =EDATE(B73,1) -> 45067 | C74: =C73 -> 0.062 | D74: =D73 -> 0.005025 | E74: =E73 -> 2089.1544 | F74: =(Q73*'AP04'!$R74)*'AP04'!$D74 -> 1230.7632 | G74: =(Q73*'AP04'!$R74)/($I$5-A73) -> 813.71431 | H74: =H73 -> 0 | I74: =I73 -> 0 | J74: =J73 -> 25 | K74: =K73 -> 0 | L74: =L73 -> 0 | M74: ='AP03'!D67 -> 2278.01 | N74: =SUM('AP04'!$F74:$L74) -> 2069.4776 | O74: ='AP04'!$M74-'AP04'!$N74 -> 208.53245 | P74: =Q73*('AP04'!$R74-1) -> 274.01247 | Q74: =(Q73*'AP04'!$R74)-'AP04'!$G74-'AP04'!$O74*2 -> 243697.23 | R74: 1.00112
... A76: =A75+1 -> 62 | B76: =EDATE(B75,1) -> 45128 | C76: =C75 -> 0.062 | D76: =D75 -> 0.005025 | E76: =E75 -> 2089.1544 | F76: =(Q75*'AP04'!$R76)*'AP04'!$D76 -> 1222.9968 | G76: =(Q75*'AP04'!$R76)/($I$5-A75) -> 813.98814 | H76: =H75 -> 0 | I76: =I75 -> 0 | J76: =J75 -> 25 | K76: =K75 -> 0 | L76: =L75 -> 0 | M76: ='AP03'!D69 -> 2277.54 | N76: =SUM('AP04'!$F76:$L76) -> 2061.985 | O76: ='AP04'!$M76-'AP04'!$N76 -> 215.55503 | P76: =Q75*('AP04'!$R76-1) -> 486.52055 | Q76: =(Q75*'AP04'!$R76)-'AP04'!$G76-'AP04'!$O76*2 -> 242137.36 | R76: 1.002003
A77: =A76+1 -> 63 | B77: =EDATE(B76,1) -> 45159 | C77: =I7 -> 0.0775 | D77: =I6 -> 0.0062 | E77: =E76 -> 2089.1544 | F77: =(Q76*'AP04'!$R77)*'AP04'!$D77 -> 1503.6236 | G77: =(Q76*'AP04'!$R77)/($I$5-A76) -> 813.82528 | H77: =H76 -> 0 | I77: =I76 -> 0 | J77: =J76 -> 25 | K77: =K76 -> 0 | L77: =L76 -> 0 | M77: ='AP03'!D70 -> 3133.63 | N77: =SUM('AP04'!$F77:$L77) -> 2342.4489 | O77: ='AP04'!$M77-'AP04'!$N77 -> 791.18114 | P77: =Q76*('AP04'!$R77-1) -> 382.57702 | Q77: =(Q76*'AP04'!$R77)-'AP04'!$G77-'AP04'!$O77*2 -> 240123.74 | R77: 1.00158
A78: =A77+1 -> 64 | B78: =EDATE(B77,1) -> 45190 | C78: =C77 -> 0.0775 | D78: =D77 -> 0.0062 | E78: =E77 -> 2089.1544 | F78: =(Q77*'AP04'!$R78)*'AP04'!$D78 -> 1491.4142 | G78: =(Q77*'AP04'!$R78)/($I$5-A77) -> 809.93497 | H78: =H77 -> 0 | I78: =I77 -> 0 | J78: =J77 -> 25 | K78: =K77 -> 0 | L78: =L77 -> 0 | M78: ='AP03'!D71 -> 3131.76 | N78: =SUM('AP04'!$F78:$L78) -> 2326.3492 | O78: ='AP04'!$M78-'AP04'!$N78 -> 805.41079 | P78: =Q77*('AP04'!$R78-1) -> 426.94002 | Q78: =(Q77*'AP04'!$R78)-'AP04'!$G78-'AP04'!$O78*2 -> 238129.93 | R78: 1.001778
A79: =A78+1 -> 65 | B79: =EDATE(B78,1) -> 45220 | C79: =C78 -> 0.0775 | D79: =((1+'AP04'!$C79)^(1/12))-1 -> 0.0062396815 | E79: =E78 -> 2089.1544 | F79: =(Q78*'AP04'!$R79)*'AP04'!$D79 -> 1487.5636 | G79: =(Q78*'AP04'!$R79)/($I$5-A78) -> 805.41817 | H79: =H78 -> 0 | I79: =I78 -> 0 | J79: =J78 -> 25 | K79: =K78 -> 0 | L79: =L78 -> 0 | M79: ='AP03'!D72 -> 3127.92 | N79: =SUM('AP04'!$F79:$L79) -> 2317.9818 | O79: ='AP04'!$M79-'AP04'!$N79 -> 809.9382 | P79: =Q78*('AP04'!$R79-1) -> 273.84942 | Q79: =(Q78*'AP04'!$R79)-'AP04'!$G79-'AP04'!$O79*2 -> 235978.48 | R79: 1.00115
A80: =A79+1 -> 66 | B80: =EDATE(B79,1) -> 45251 | C80: =C79 -> 0.0775 | D80: =((1+'AP04'!$C80)^(1/12))-1 -> 0.0062396815 | E80: =E79 -> 2089.1544 | F80: =(Q79*'AP04'!$R80)*'AP04'!$D80 -> 1473.1624 | G80: =(Q79*'AP04'!$R80)/($I$5-A79) -> 800.32463 | H80: =H79 -> 0 | I80: =I79 -> 0 | J80: =J79 -> 25 | K80: =K79 -> 0 | L80: =L79 -> 0 | M80: ='AP03'!D73 -> 3122.04 | N80: =SUM('AP04'!$F80:$L80) -> 2298.487 | O80: ='AP04'!$M80-'AP04'!$N80 -> 823.55301 | P80: =Q79*('AP04'!$R80-1) -> 117.28131 | Q80: =(Q79*'AP04'!$R80)-'AP04'!$G80-'AP04'!$O80*2 -> 233648.33 | R80: 1.000497
A81: =A80+1 -> 67 | B81: =EDATE(B80,1) -> 45281 | C81: =C80 -> 0.0775 | D81: =((1+'AP04'!$C81)^(1/12))-1 -> 0.0062396815 | E81: =E80 -> 2089.1544 | F81: =(Q80*'AP04'!$R81)*'AP04'!$D81 -> 1459.7529 | G81: =(Q80*'AP04'!$R81)/($I$5-A80) -> 795.73708 | H81: =H80 -> 0 | I81: =I80 -> 0 | J81: =J80 -> 25 | K81: =K80 -> 0 | L81: =L80 -> 0 | M81: ='AP03'!D74 -> 3120.41 | N81: =SUM('AP04'!$F81:$L81) -> 2280.49 | O81: ='AP04'!$M81-'AP04'!$N81 -> 839.92001 | P81: =Q80*('AP04'!$R81-1) -> 298.36892 | Q81: =(Q80*'AP04'!$R81)-'AP04'!$G81-'AP04'!$O81*2 -> 231471.13 | R81: 1.001277
A82: =A81+1 -> 68 | B82: =EDATE(B81,1) -> 45312 | C82: =C81 -> 0.0775 | D82: =((1+'AP04'!$C82)^(1/12))-1 -> 0.0062396815 | E82: =E81 -> 2089.1544 | F82: =(Q81*'AP04'!$R82)*'AP04'!$D82 -> 1444.9762 | G82: =(Q81*'AP04'!$R82)/($I$5-A81) -> 790.3704 | H82: =H81 -> 0 | I82: =I81 -> 0 | J82: =J81 -> 25 | K82: =K81 -> 0 | L82: =L81 -> 0 | M82: ='AP03'!D75 -> 3114.42 | N82: =SUM('AP04'!$F82:$L82) -> 2260.3467 | O82: ='AP04'!$M82-'AP04'!$N82 -> 854.07335 | P82: =Q81*('AP04'!$R82-1) -> 107.4026 | Q82: =(Q81*'AP04'!$R82)-'AP04'!$G82-'AP04'!$O82*2 -> 229080.01 | R82: 1.000464
A83: =A82+1 -> 69 | B83: =EDATE(B82,1) -> 45343 | C83: =C82 -> 0.0775 | D83: =((1+'AP04'!$C83)^(1/12))-1 -> 0.0062396815 | E83: =E82 -> 2089.1544 | F83: =(Q82*'AP04'!$R83)*'AP04'!$D83 -> 1429.9252 | G83: =(Q82*'AP04'!$R83)/($I$5-A82) -> 784.81635 | H83: =H82 -> 0 | I83: =I82 -> 0 | J83: =J82 -> 25 | K83: =K82 -> 0 | L83: =L82 -> 0 | M83: ='AP03'!D76 -> 3109.21 | N83: =SUM('AP04'!$F83:$L83) -> 2239.7415 | O83: ='AP04'!$M83-'AP04'!$N83 -> 869.46847 | P83: =Q82*('AP04'!$R83-1) -> 86.363164 | Q83: =(Q82*'AP04'!$R83)-'AP04'!$G83-'AP04'!$O83*2 -> 226642.62 | R83: 1.000377
A84: =A83+1 -> 70 | B84: =EDATE(B83,1) -> 45372 | C84: =C83 -> 0.0775 | D84: =((1+'AP04'!$C84)^(1/12))-1 -> 0.0062396815 | E84: =E83 -> 2089.1544 | F84: =(Q83*'AP04'!$R84)*'AP04'!$D84 -> 1415.0941 | G84: =(Q83*'AP04'!$R84)/($I$5-A83) -> 779.34531 | H84: =H83 -> 0 | I84: =I83 -> 0 | J84: =J83 -> 25 | K84: =K83 -> 0 | L84: =L83 -> 0 | M84: ='AP03'!D77 -> 3103.77 | N84: =SUM('AP04'!$F84:$L84) -> 2219.4395 | O84: ='AP04'!$M84-'AP04'!$N84 -> 884.33054 | P84: =Q83*('AP04'!$R84-1) -> 146.86442 | Q84: =(Q83*'AP04'!$R84)-'AP04'!$G84-'AP04'!$O84*2 -> 224241.48 | R84: 1.000648 | T84: ='AP04'!$Q84+0.02 -> 224241.5 | U84: 3103.77 | V84: =T84+U84-'AP04'!$G84 -> 226565.92
A85: =A84+1 -> 71 | B85: =EDATE(B84,1) -> 45403 | C85: =C84 -> 0.0775 | D85: =((1+'AP04'!$C85)^(1/12))-1 -> 0.0062396815 | E85: =E84 -> 2089.1544 | F85: =(Q84*'AP04'!$R85)*'AP04'!$D85 -> 1400.0741 | G85: =(Q84*'AP04'!$R85)/($I$5-A84) -> 773.73208 | H85: =H84 -> 0 | I85: =I84 -> 0 | J85: =J84 -> 25 | K85: =K84 -> 0 | L85: =L84 -> 0 | M85: ='AP03'!D78 -> 3135.52 | N85: =SUM('AP04'!$F85:$L85) -> 2198.8062 | O85: ='AP04'!$M85-'AP04'!$N85 -> 936.71383 | P85: =Q84*('AP04'!$R85-1) -> 140.82365 | Q85: =(Q84*'AP04'!$R85)+'AP04'!$F85 -> 225782.38 | R85: 1.000628 | T85: =(T84*'AP04'!$R85)+(U84*'AP04'!$R85) -> 227488.04 | U85: =2115.97+871.08+51.45+40.27+25 -> 3103.77
A86: =A85+1 -> 72 | B86: =EDATE(B85,1) -> 45433 | C86: =C85 -> 0.0775 | D86: =((1+'AP04'!$C86)^(1/12))-1 -> 0.0062396815 | E86: =E85 -> 2089.1544 | F86: =(Q85*'AP04'!$R86)*'AP04'!$D86 -> 1409.3215 | G86: =(Q85*'AP04'!$R86)/($I$5-A85) -> 781.53749 | H86: =H85 -> 0 | I86: =I85 -> 0 | J86: =J85 -> 25 | K86: =K85 -> 0 | L86: =L85 -> 0 | M86: ='AP03'!D79 -> 3977.85 | N86: =SUM('AP04'!$F86:$L86) -> 2215.859 | O86: ='AP04'!$M86-'AP04'!$N86 -> 1761.991 | P86: =Q85*('AP04'!$R86-1) -> 81.959003 | Q86: =(Q85*'AP04'!$R86)+'AP04'!$F86 -> 227273.66 | R86: 1.000363
A87: =A86+1 -> 73 | B87: =EDATE(B86,1) -> 45464 | C87: =C86 -> 0.0775 | D87: =((1+'AP04'!$C87)^(1/12))-1 -> 0.0062396815 | E87: =E86 -> 2089.1544 | F87: =(Q86*'AP04'!$R87)*'AP04'!$D87 -> 1419.4213 | G87: =(Q86*'AP04'!$R87)/($I$5-A86) -> 789.87145 | H87: =H86 -> 0 | I87: =I86 -> 0 | J87: =J86 -> 25 | K87: =K86 -> 0 | L87: =L86 -> 0 | M87: ='AP03'!D80 -> 3898.81 | N87: =SUM('AP04'!$F87:$L87) -> 2234.2928 | O87: ='AP04'!$M87-'AP04'!$N87 -> 1664.5172 | P87: =Q86*('AP04'!$R87-1) -> 209.31904 | Q87: =(Q86*'AP04'!$R87)-'AP04'!$G87-'AP04'!$O87*2 -> 223364.07 | R87: 1.000921 | T87: 254994.68
A88: =A87+1 -> 74 | B88: =EDATE(B87,1) -> 45494 | C88: =C87 -> 0.0775 | D88: =((1+'AP04'!$C88)^(1/12))-1 -> 0.0062396815 | E88: =E87 -> 2089.1544 | F88: =(Q87*'AP04'!$R88)*'AP04'!$D88 -> 1394.6307 | G88: =(Q87*'AP04'!$R88)/($I$5-A87) -> 778.78023 | H88: =H87 -> 0 | I88: =I87 -> 0 | J88: =J87 -> 25 | K88: =K87 -> 0 | L88: =L87 -> 0 | M88: ='AP03'!D81 -> 3822.16 | N88: =SUM('AP04'!$F88:$L88) -> 2198.411 | O88: ='AP04'!$M88-'AP04'!$N88 -> 1623.749 | P88: =Q87*('AP04'!$R88-1) -> 145.85674 | Q88: =(Q87*'AP04'!$R88)-'AP04'!$G88-'AP04'!$O88*2 -> 219483.65 | R88: 1.000653 | T88: =T87-T84 -> 30753.181
A89: =A88+1 -> 75 | B89: =EDATE(B88,1) -> 45525 | C89: =C88 -> 0.0775 | D89: =((1+'AP04'!$C89)^(1/12))-1 -> 0.0062396815 | E89: =E88 -> 2089.1544 | F89: =(Q88*'AP04'!$R89)*'AP04'!$D89 -> 1370.4777 | G89: =(Q88*'AP04'!$R89)/($I$5-A88) -> 767.96868 | H89: =H88 -> 0 | I89: =I88 -> 0 | J89: =J88 -> 25 | K89: =K88 -> 0 | L89: =L88 -> 0 | M89: ='AP03'!D82 -> 3745.51 | N89: =SUM('AP04'!$F89:$L89) -> 2163.4463 | O89: ='AP04'!$M89-'AP04'!$N89 -> 1582.0637 | P89: =Q88*('AP04'!$R89-1) -> 155.39442 | Q89: =(Q88*'AP04'!$R89)-'AP04'!$G89-'AP04'!$O89*2 -> 215706.95 | R89: 1.000708 | T89: =T88-2115.97 -> 28637.211
A90: =A89+1 -> 76 | B90: =EDATE(B89,1) -> 45556 | C90: =C89 -> 0.0775 | D90: =((1+'AP04'!$C90)^(1/12))-1 -> 0.0062396815 | E90: =E89 -> 2089.1544 | F90: =(Q89*'AP04'!$R90)*'AP04'!$D90 -> 1346.9454 | G90: =(Q89*'AP04'!$R90)/($I$5-A89) -> 757.43035 | H90: =H89 -> 0 | I90: =I89 -> 0 | J90: =J89 -> 25 | K90: =K89 -> 0 | L90: =L89 -> 0 | M90: ='AP03'!D83 -> 3670.04 | N90: =SUM('AP04'!$F90:$L90) -> 2129.3757 | O90: ='AP04'!$M90-'AP04'!$N90 -> 1540.6643 | P90: =Q89*('AP04'!$R90-1) -> 160.70168 | Q90: =(Q89*'AP04'!$R90)-'AP04'!$G90-'AP04'!$O90*2 -> 212028.89 | R90: 1.000745 | T90: =51.45+40.27+51.94+40.3+50 -> 233.96
A91: =A90+1 -> 77 | B91: =EDATE(B90,1) -> 45586 | C91: =C90 -> 0.0775 | D91: =((1+'AP04'!$C91)^(1/12))-1 -> 0.0062396815 | E91: =E90 -> 2089.1544 | F91: =(Q90*'AP04'!$R91)*'AP04'!$D91 -> 1323.8725 | G91: =(Q90*'AP04'!$R91)/($I$5-A90) -> 747.07707 | H91: =H90 -> 0 | I91: =I90 -> 0 | J91: =J90 -> 25 | K91: =K90 -> 0 | L91: =L90 -> 0 | M91: ='AP03'!D84 -> 3596.87 | N91: =SUM('AP04'!$F91:$L91) -> 2095.9496 | O91: ='AP04'!$M91-'AP04'!$N91 -> 1500.9204 | P91: =Q90*('AP04'!$R91-1) -> 140.99921 | Q91: =(Q90*'AP04'!$R91)-'AP04'!$G91-'AP04'!$O91*2 -> 208420.97 | R91: 1.000665
A92: =A91+1 -> 78 | B92: =EDATE(B91,1) -> 45617 | C92: =C91 -> 0.0775 | D92: =((1+'AP04'!$C92)^(1/12))-1 -> 0.0062396815 | E92: =E91 -> 2089.1544 | F92: =(Q91*'AP04'!$R92)*'AP04'!$D92 -> 1301.4207 | G92: =(Q91*'AP04'!$R92)/($I$5-A91) -> 737.00233 | H92: =H91 -> 0 | I92: =I91 -> 0 | J92: =J91 -> 25 | K92: =K91 -> 0 | L92: =L91 -> 0 | M92: ='AP03'!D85 -> 3523.71 | N92: =SUM('AP04'!$F92:$L92) -> 2063.423 | O92: ='AP04'!$M92-'AP04'!$N92 -> 1460.287 | P92: =Q91*('AP04'!$R92-1) -> 150.68836 | Q92: =(Q91*'AP04'!$R92)-'AP04'!$G92-'AP04'!$O92*2 -> 204914.08 | R92: 1.000723
A93: =A92+1 -> 79 | B93: =EDATE(B92,1) -> 45647 | C93: =C92 -> 0.0775 | D93: =((1+'AP04'!$C93)^(1/12))-1 -> 0.0062396815 | E93: =E92 -> 2089.1544 | F93: =(Q92*'AP04'!$R93)*'AP04'!$D93 -> 1279.8759 | G93: =(Q92*'AP04'!$R93)/($I$5-A92) -> 727.37161 | H93: =H92 -> 0 | I93: =I92 -> 0 | J93: =J92 -> 25 | K93: =K92 -> 0 | L93: =L92 -> 0 | M93: ='AP03'!D86 -> 3455.26 | N93: =SUM('AP04'!$F93:$L93) -> 2032.2475 | O93: ='AP04'!$M93-'AP04'!$N93 -> 1423.0125 | P93: =Q92*('AP04'!$R93-1) -> 204.70917 | Q93: =(Q92*'AP04'!$R93)-'AP04'!$G93-'AP04'!$O93*2 -> 201545.4 | R93: 1.000999
A94: =A93+1 -> 80 | B94: =EDATE(B93,1) -> 45678 | C94: =C93 -> 0.0775 | D94: =((1+'AP04'!$C94)^(1/12))-1 -> 0.0062396815 | E94: =E93 -> 2089.1544 | F94: =(Q93*'AP04'!$R94)*'AP04'!$D94 -> 1258.5851 | G94: =(Q93*'AP04'!$R94)/($I$5-A93) -> 717.8172 | H94: =H93 -> 0 | I94: =I93 -> 0 | J94: =J93 -> 25 | K94: =K93 -> 0 | L94: =L93 -> 0 | M94: ='AP03'!D87 -> 3384.28 | N94: =SUM('AP04'!$F94:$L94) -> 2001.4023 | O94: ='AP04'!$M94-'AP04'!$N94 -> 1382.8777 | P94: =Q93*('AP04'!$R94-1) -> 161.23632 | Q94: =(Q93*'AP04'!$R94)-'AP04'!$G94-'AP04'!$O94*2 -> 198223.06 | R94: 1.0008
A95: =A94+1 -> 81 | B95: =EDATE(B94,1) -> 45709 | C95: =C94 -> 0.0775 | D95: =((1+'AP04'!$C95)^(1/12))-1 -> 0.0062396815 | E95: =E94 -> 2089.1544 | F95: =(Q94*'AP04'!$R95)*'AP04'!$D95 -> 1238.9662 | G95: =(Q94*'AP04'!$R95)/($I$5-A94) -> 709.15149 | H95: =H94 -> 0 | I95: =I94 -> 0 | J95: =J94 -> 25 | K95: =K94 -> 0 | L95: =L94 -> 0 | M95: ='AP03'!D88 -> 3326.09 | N95: =SUM('AP04'!$F95:$L95) -> 1973.1177 | O95: ='AP04'!$M95-'AP04'!$N95 -> 1352.9723 | P95: =Q94*('AP04'!$R95-1) -> 339.35788 | Q95: =(Q94*'AP04'!$R95)-'AP04'!$G95-'AP04'!$O95*2 -> 195147.32 | R95: 1.001712
A96: =A95+1 -> 82 | B96: =EDATE(B95,1) -> 45737 | C96: =C95 -> 0.0775 | D96: =((1+'AP04'!$C96)^(1/12))-1 -> 0.0062396815 | E96: =E95 -> 2089.1544 | F96: =(Q95*'AP04'!$R96)*'AP04'!$D96 -> 1218.5618 | G96: =(Q95*'AP04'!$R96)/($I$5-A95) -> 699.97246 | H96: =H95 -> 0 | I96: =I95 -> 0 | J96: =J95 -> 25 | K96: =K95 -> 0 | L96: =L95 -> 0 | M96: ='AP03'!D89 -> 3260.28 | N96: =SUM('AP04'!$F96:$L96) -> 1943.5343 | O96: ='AP04'!$M96-'AP04'!$N96 -> 1316.7457 | P96: =Q95*('AP04'!$R96-1) -> 144.99446 | Q96: =(Q95*'AP04'!$R96)-'AP04'!$G96-'AP04'!$O96*2 -> 191958.85 | R96: 1.000743
A97: =A96+1 -> 83 | B97: =EDATE(B96,1) -> 45768 | C97: =C96 -> 0.0775 | D97: =((1+'AP04'!$C97)^(1/12))-1 -> 0.0062396815 | E97: =E96 -> 2089.1544 | F97: =(Q96*'AP04'!$R97)*'AP04'!$D97 -> 1199.7839 | G97: =(Q96*'AP04'!$R97)/($I$5-A96) -> 691.66503 | H97: =H96 -> 0 | I97: =I96 -> 0 | J97: =J96 -> 25 | K97: =K96 -> 0 | L97: =L96 -> 0 | M97: ='AP03'!D90 -> 3127.79 | N97: =SUM('AP04'!$F97:$L97) -> 1916.4489 | O97: ='AP04'!$M97-'AP04'!$N97 -> 1211.3411 | P97: =Q96*('AP04'!$R97-1) -> 324.02654 | Q97: =(Q96*'AP04'!$R97)-'AP04'!$G97-'AP04'!$O97*2 -> 189168.53 | R97: 1.001688 | T97: =360-'AP04'!$A97 -> 277
A98: =A97+1 -> 84 | B98: =EDATE(B97,1) -> 45798 | C98: =C97 -> 0.0775 | D98: =((1+'AP04'!$C98)^(1/12))-1 -> 0.0062396815 | E98: =E97 -> 2089.1544 | F98: =(Q97*'AP04'!$R98)*'AP04'!$D98 -> 1180.3514 | G98: =(Q97*'AP04'!$R98)/($I$5-A97) -> 682.91889 | H98: =H97 -> 0 | I98: =I97 -> 0 | J98: =J97 -> 25 | K98: =K97 -> 0 | L98: =L97 -> 0 | N98: =SUM('AP04'!$F98:$L98) -> 1888.2703 | P98: =Q97*('AP04'!$R98-1) -> 0 | Q98: =(Q97*'AP04'!$R98)-'AP04'!$G98 -> 188485.61 | R98: 1
A99: =A98+1 -> 85 | B99: =EDATE(B98,1) -> 45829 | C99: =C98 -> 0.0775 | D99: =((1+'AP04'!$C99)^(1/12))-1 -> 0.0062396815 | E99: =E98 -> 2089.1544 | F99: =(Q98*'AP04'!$R99)*'AP04'!$D99 -> 1176.0902 | G99: =(Q98*'AP04'!$R99)/($I$5-A98) -> 682.91889 | H99: =H98 -> 0 | I99: =I98 -> 0 | J99: =J98 -> 25 | K99: =K98 -> 0 | L99: =L98 -> 0 | N99: =SUM('AP04'!$F99:$L99) -> 1884.0091 | P99: =Q98*('AP04'!$R99-1) -> 0 | Q99: =(Q98*'AP04'!$R99)-'AP04'!$G99 -> 187802.69 | R99: =R98 -> 1
A100: =A99+1 -> 86 | B100: =EDATE(B99,1) -> 45859 | C100: =C99 -> 0.0775 | D100: =((1+'AP04'!$C100)^(1/12))-1 -> 0.0062396815 | E100: =E99 -> 2089.1544 | F100: =(Q99*'AP04'!$R100)*'AP04'!$D100 -> 1171.829 | G100: =(Q99*'AP04'!$R100)/($I$5-A99) -> 682.91889 | H100: =H99 -> 0 | I100: =I99 -> 0 | J100: =J99 -> 25 | K100: =K99 -> 0 | L100: =L99 -> 0 | N100: =SUM('AP04'!$F100:$L100) -> 1879.7479 | P100: =Q99*('AP04'!$R100-1) -> 0 | Q100: =(Q99*'AP04'!$R100)-'AP04'!$G100 -> 187119.78 | R100: =R99 -> 1
A101: =A100+1 -> 87 | B101: =EDATE(B100,1) -> 45890 | C101: =C100 -> 0.0775 | D101: =((1+'AP04'!$C101)^(1/12))-1 -> 0.0062396815 | E101: =E100 -> 2089.1544 | F101: =(Q100*'AP04'!$R101)*'AP04'!$D101 -> 1167.5678 | G101: =(Q100*'AP04'!$R101)/($I$5-A100) -> 682.91889 | H101: =H100 -> 0 | I101: =I100 -> 0 | J101: =J100 -> 25 | K101: =K100 -> 0 | L101: =L100 -> 0 | N101: =SUM('AP04'!$F101:$L101) -> 1875.4867 | P101: =Q100*('AP04'!$R101-1) -> 0 | Q101: =(Q100*'AP04'!$R101)-'AP04'!$G101 -> 186436.86 | R101: =R100 -> 1
A102: =A101+1 -> 88 | B102: =EDATE(B101,1) -> 45921 | C102: =C101 -> 0.0775 | D102: =((1+'AP04'!$C102)^(1/12))-1 -> 0.0062396815 | E102: =E101 -> 2089.1544 | F102: =(Q101*'AP04'!$R102)*'AP04'!$D102 -> 1163.3066 | G102: =(Q101*'AP04'!$R102)/($I$5-A101) -> 682.91889 | H102: =H101 -> 0 | I102: =I101 -> 0 | J102: =J101 -> 25 | K102: =K101 -> 0 | L102: =L101 -> 0 | N102: =SUM('AP04'!$F102:$L102) -> 1871.2255 | P102: =Q101*('AP04'!$R102-1) -> 0 | Q102: =(Q101*'AP04'!$R102)-'AP04'!$G102 -> 185753.94 | R102: =R101 -> 1
A103: =A102+1 -> 89 | B103: =EDATE(B102,1) -> 45951 | C103: =C102 -> 0.0775 | D103: =((1+'AP04'!$C103)^(1/12))-1 -> 0.0062396815 | E103: =E102 -> 2089.1544 | F103: =(Q102*'AP04'!$R103)*'AP04'!$D103 -> 1159.0454 | G103: =(Q102*'AP04'!$R103)/($I$5-A102) -> 682.91889 | H103: =H102 -> 0 | I103: =I102 -> 0 | J103: =J102 -> 25 | K103: =K102 -> 0 | L103: =L102 -> 0 | N103: =SUM('AP04'!$F103:$L103) -> 1866.9643 | P103: =Q102*('AP04'!$R103-1) -> 0 | Q103: =(Q102*'AP04'!$R103)-'AP04'!$G103 -> 185071.02 | R103: =R102 -> 1
A104: =A103+1 -> 90 | B104: =EDATE(B103,1) -> 45982 | C104: =C103 -> 0.0775 | D104: =((1+'AP04'!$C104)^(1/12))-1 -> 0.0062396815 | E104: =E103 -> 2089.1544 | F104: =(Q103*'AP04'!$R104)*'AP04'!$D104 -> 1154.7842 | G104: =(Q103*'AP04'!$R104)/($I$5-A103) -> 682.91889 | H104: =H103 -> 0 | I104: =I103 -> 0 | J104: =J103 -> 25 | K104: =K103 -> 0 | L104: =L103 -> 0 | N104: =SUM('AP04'!$F104:$L104) -> 1862.7031 | P104: =Q103*('AP04'!$R104-1) -> 0 | Q104: =(Q103*'AP04'!$R104)-'AP04'!$G104 -> 184388.1 | R104: =R103 -> 1
A105: =A104+1 -> 91 | B105: =EDATE(B104,1) -> 46012 | C105: =C104 -> 0.0775 | D105: =((1+'AP04'!$C105)^(1/12))-1 -> 0.0062396815 | E105: =E104 -> 2089.1544 | F105: =(Q104*'AP04'!$R105)*'AP04'!$D105 -> 1150.523 | G105: =(Q104*'AP04'!$R105)/($I$5-A104) -> 682.91889 | H105: =H104 -> 0 | I105: =I104 -> 0 | J105: =J104 -> 25 | K105: =K104 -> 0 | L105: =L104 -> 0 | N105: =SUM('AP04'!$F105:$L105) -> 1858.4419 | P105: =Q104*('AP04'!$R105-1) -> 0 | Q105: =(Q104*'AP04'!$R105)-'AP04'!$G105 -> 183705.18 | R105: =R104 -> 1
A106: =A105+1 -> 92 | B106: =EDATE(B105,1) -> 46043 | C106: =C105 -> 0.0775 | D106: =((1+'AP04'!$C106)^(1/12))-1 -> 0.0062396815 | E106: =E105 -> 2089.1544 | F106: =(Q105*'AP04'!$R106)*'AP04'!$D106 -> 1146.2618 | G106: =(Q105*'AP04'!$R106)/($I$5-A105) -> 682.91889 | H106: =H105 -> 0 | I106: =I105 -> 0 | J106: =J105 -> 25 | K106: =K105 -> 0 | L106: =L105 -> 0 | N106: =SUM('AP04'!$F106:$L106) -> 1854.1807 | P106: =Q105*('AP04'!$R106-1) -> 0 | Q106: =(Q105*'AP04'!$R106)-'AP04'!$G106 -> 183022.26 | R106: =R105 -> 1
A107: =A106+1 -> 93 | B107: =EDATE(B106,1) -> 46074 | C107: =C106 -> 0.0775 | D107: =((1+'AP04'!$C107)^(1/12))-1 -> 0.0062396815 | E107: =E106 -> 2089.1544 | F107: =(Q106*'AP04'!$R107)*'AP04'!$D107 -> 1142.0006 | G107: =(Q106*'AP04'!$R107)/($I$5-A106) -> 682.91889 | H107: =H106 -> 0 | I107: =I106 -> 0 | J107: =J106 -> 25 | K107: =K106 -> 0 | L107: =L106 -> 0 | N107: =SUM('AP04'!$F107:$L107) -> 1849.9195 | P107: =Q106*('AP04'!$R107-1) -> 0 | Q107: =(Q106*'AP04'!$R107)-'AP04'!$G107 -> 182339.34 | R107: =R106 -> 1
A108: =A107+1 -> 94 | B108: =EDATE(B107,1) -> 46102 | C108: =C107 -> 0.0775 | D108: =((1+'AP04'!$C108)^(1/12))-1 -> 0.0062396815 | E108: =E107 -> 2089.1544 | F108: =(Q107*'AP04'!$R108)*'AP04'!$D108 -> 1137.7394 | G108: =(Q107*'AP04'!$R108)/($I$5-A107) -> 682.91889 | H108: =H107 -> 0 | I108: =I107 -> 0 | J108: =J107 -> 25 | K108: =K107 -> 0 | L108: =L107 -> 0 | N108: =SUM('AP04'!$F108:$L108) -> 1845.6583 | P108: =Q107*('AP04'!$R108-1) -> 0 | Q108: =(Q107*'AP04'!$R108)-'AP04'!$G108 -> 181656.42 | R108: =R107 -> 1
A109: =A108+1 -> 95 | B109: =EDATE(B108,1) -> 46133 | C109: =C108 -> 0.0775 | D109: =((1+'AP04'!$C109)^(1/12))-1 -> 0.0062396815 | E109: =E108 -> 2089.1544 | F109: =(Q108*'AP04'!$R109)*'AP04'!$D109 -> 1133.4782 | G109: =(Q108*'AP04'!$R109)/($I$5-A108) -> 682.91889 | H109: =H108 -> 0 | I109: =I108 -> 0 | J109: =J108 -> 25 | K109: =K108 -> 0 | L109: =L108 -> 0 | N109: =SUM('AP04'!$F109:$L109) -> 1841.3971 | P109: =Q108*('AP04'!$R109-1) -> 0 | Q109: =(Q108*'AP04'!$R109)-'AP04'!$G109 -> 180973.51 | R109: =R108 -> 1
A110: =A109+1 -> 96 | B110: =EDATE(B109,1) -> 46163 | C110: =C109 -> 0.0775 | D110: =((1+'AP04'!$C110)^(1/12))-1 -> 0.0062396815 | E110: =E109 -> 2089.1544 | F110: =(Q109*'AP04'!$R110)*'AP04'!$D110 -> 1129.217 | G110: =(Q109*'AP04'!$R110)/($I$5-A109) -> 682.91889 | H110: =H109 -> 0 | I110: =I109 -> 0 | J110: =J109 -> 25 | K110: =K109 -> 0 | L110: =L109 -> 0 | N110: =SUM('AP04'!$F110:$L110) -> 1837.1359 | P110: =Q109*('AP04'!$R110-1) -> 0 | Q110: =(Q109*'AP04'!$R110)-'AP04'!$G110 -> 180290.59 | R110: =R109 -> 1
... A374: =A373+1 -> 360 | B374: =EDATE(B373,1) -> 54199 | C374: =C373 -> 0.0775 | D374: =((1+'AP04'!$C374)^(1/12))-1 -> 0.0062396815 | E374: =E373 -> 2089.1544 | F374: =(Q373*'AP04'!$R374)*'AP04'!$D374 -> 4.2611963 | G374: =(Q373*'AP04'!$R374)/($I$5-A373) -> 682.91889 | H374: =H373 -> 0 | I374: =I373 -> 0 | J374: =J373 -> 25 | K374: =K373 -> 0 | L374: =L373 -> 0 | N374: =SUM('AP04'!$F374:$L374) -> 712.18008 | P374: =Q373*('AP04'!$R374-1) -> 0 | Q374: =(Q373*'AP04'!$R374)-'AP04'!$G374 -> 0 | R374: =R373 -> 1
A376: Este apêndice retrata a evolução do financiamento com taxa MÉDIA do BACEN, expurgando os seguros e afastando a mora, realizando a compensação do crédito apurado mensalmente no APÊNDICE 03, na mesma data em que ocorreu, respeitando a regra do valor do dinheiro no tempo e do art. 368 do CC, de forma DOBRADA com base no art. 42 do CDC, encontrando o novo saldo devedor na data do último pagamento e refinanciando com as parcelas vincendas a serem pagas a partir de então.

Sheet AP05
A1: APÊNDICE 05: EVOLUÇÃO DO FINANCIAMENTO COM TAXA MÉDIA E EXPURGO DOS SEGUROS => COM REST. SIMPLES
A3: ='AP01'!A3 -> Requerente: ADRIANA MELO DE OLIVEIRA
A4: ='AP01'!A4 -> Requerido: ITAÚ UNIBANCO
A5: Valor do Bem | D5: ='AP01'!D5 -> 432000 | F5: Qtde Prestações | I5: ='AP01'!I5 -> 360
A6: Entrada/Descontos | D6: ='AP01'!D6 -> 129600 | F6: Taxa MÉDIA Efetiva (a.m.) | I6: 0.0062
A7: Valor Financiado | D7: =D5-D6 -> 302400 | F7: Taxa MÉDIA Efetiva (a.a.) | I7: 0.0775
A8: Data do Contrato | D8: ='AP01'!D8 -> 43241 | F8: Taxa de Juros Efetiva (a.a.) | I8: ='AP01'!I7 -> 0.117
A9: 1° Vencimento | D9: ='AP01'!D9 -> 43272 | F9: (%) Excesso Taxa Média | I9: =(I8/I7)-1 -> 0.50967742
A10: Sistema de Amortização | D10: ='AP01'!D10 -> SAC | F10: Prestação Mensal | I10: ='AP01'!I10 -> 2549.8136
A11: Índice Correção | D11: ='AP01'!D11 -> TR | F11: Enquadramento | I11: ='AP01'!I11 -> SFH
A13: Qtde | B13: Data Vencimento | C13: Taxa Efetiva a.a. | D13: Taxa Efetiva a.m. | E13: Prestação (a+j) | F13: Juros | G13: (1) Amortização | H13: Seguro MIP | I13: Seguro DFI | J13: TCA | K13: Multa | L13: Mora | M13: (2) Valor Pago | N13: (3) Total da Parcela Devida | O13: (4) Diferença a Compensar [2-3] | P13: Correção Monetária | Q13: (5) Saldo Devedor [(5*TR)-1-4] | R13: Índice Correção
A14: 0 | B14: =D8 -> 43241 | Q14: =D7 -> 302400
A15: =A14+1 -> 1 | B15: =D9 -> 43272 | C15: 0.07 | D15: 0.005654 | E15: ='AP05'!$F15+'AP05'!$G15 -> 2549.7696 | F15: =(Q14*'AP05'!$R15)*'AP05'!$D15 -> 1709.7696 | G15: =(Q14*'AP05'!$R15)/($I$5-A14) -> 840 | H15: 0 | I15: 0 | J15: 25 | K15: 0 | L15: 0 | M15: ='AP03'!D8 -> 2714.96 | N15: =SUM('AP05'!$F15:$L15) -> 2574.7696 | O15: ='AP05'!$M15-'AP05'!$N15 -> 140.1904 | P15: =Q14*('AP05'!$R15-1) -> 0 | Q15: =(Q14*'AP05'!$R15)-'AP05'!$G15-'AP05'!$O15 -> 301419.81 | R15: 1
A16: =A15+1 -> 2 | B16: =EDATE(B15,1) -> 43302 | C16: =C15 -> 0.07 | D16: =D15 -> 0.005654 | E16: ='AP05'!$F16+'AP05'!$G16 -> 2543.8371 | F16: =(Q15*'AP05'!$R16)*'AP05'!$D16 -> 1704.2276 | G16: =(Q15*'AP05'!$R16)/($I$5-A15) -> 839.6095 | H16: =H15 -> 0 | I16: =I15 -> 0 | J16: =J15 -> 25 | K16: =K15 -> 0 | L16: =L15 -> 0 | M16: ='AP03'!D9 -> 2640.04 | N16: =SUM('AP05'!$F16:$L16) -> 2568.8371 | O16: ='AP05'!$M16-'AP05'!$N16 -> 71.202899 | P16: =Q15*('AP05'!$R16-1) -> 0 | Q16: =(Q15*'AP05'!$R16)-'AP05'!$G16-'AP05'!$O16 -> 300509 | R16: =R15 -> 1
A17: =A16+1 -> 3 | B17: =EDATE(B16,1) -> 43333 | C17: =C16 -> 0.07 | D17: =D16 -> 0.005654 | E17: ='AP05'!$F17+'AP05'!$G17 -> 2538.4885 | F17: =(Q16*'AP05'!$R17)*'AP05'!$D17 -> 1699.0779 | G17: =(Q16*'AP05'!$R17)/($I$5-A16) -> 839.41061 | H17: =H16 -> 0 | I17: =I16 -> 0 | J17: =J16 -> 25 | K17: =K16 -> 0 | L17: =L16 -> 0 | M17: ='AP03'!D10 -> 2635.2 | N17: =SUM('AP05'!$F17:$L17) -> 2563.4885 | O17: ='AP05'!$M17-'AP05'!$N17 -> 71.711523 | P17: =Q16*('AP05'!$R17-1) -> 0 | Q17: =(Q16*'AP05'!$R17)-'AP05'!$G17-'AP05'!$O17 -> 299597.88 | R17: =R16 -> 1
A18: =A17+1 -> 4 | B18: =EDATE(B17,1) -> 43364 | C18: =C17 -> 0.07 | D18: =D17 -> 0.005654 | E18: ='AP05'!$F18+'AP05'!$G18 -> 2533.1361 | F18: =(Q17*'AP05'!$R18)*'AP05'!$D18 -> 1693.9264 | G18: =(Q17*'AP05'!$R18)/($I$5-A17) -> 839.20973 | H18: =H17 -> 0 | I18: =I17 -> 0 | J18: =J17 -> 25 | K18: =K17 -> 0 | L18: =L17 -> 0 | M18: ='AP03'!D11 -> 2630.36 | N18: =SUM('AP05'!$F18:$L18) -> 2558.1361 | O18: ='AP05'!$M18-'AP05'!$N18 -> 72.22388 | P18: =Q17*('AP05'!$R18-1) -> 0 | Q18: =(Q17*'AP05'!$R18)-'AP05'!$G18-'AP05'!$O18 -> 298686.44 | R18: =R17 -> 1
A19: =A18+1 -> 5 | B19: =EDATE(B18,1) -> 43394 | C19: =C18 -> 0.07 | D19: =D18 -> 0.005654 | E19: ='AP05'!$F19+'AP05'!$G19 -> 2527.78 | F19: =(Q18*'AP05'!$R19)*'AP05'!$D19 -> 1688.7731 | G19: =(Q18*'AP05'!$R19)/($I$5-A18) -> 839.00686 | H19: =H18 -> 0 | I19: =I18 -> 0 | J19: =J18 -> 25 | K19: =K18 -> 0 | L19: =L18 -> 0 | M19: ='AP03'!D12 -> 2625.52 | N19: =SUM('AP05'!$F19:$L19) -> 2552.78 | O19: ='AP05'!$M19-'AP05'!$N19 -> 72.740002 | P19: =Q18*('AP05'!$R19-1) -> 0 | Q19: =(Q18*'AP05'!$R19)-'AP05'!$G19-'AP05'!$O19 -> 297774.69 | R19: =R18 -> 1
A20: =A19+1 -> 6 | B20: =EDATE(B19,1) -> 43425 | C20: =C19 -> 0.07 | D20: =D19 -> 0.005654 | E20: ='AP05'!$F20+'AP05'!$G20 -> 2522.4201 | F20: =(Q19*'AP05'!$R20)*'AP05'!$D20 -> 1683.6181 | G20: =(Q19*'AP05'!$R20)/($I$5-A19) -> 838.80196 | H20: =H19 -> 0 | I20: =I19 -> 0 | J20: =J19 -> 25 | K20: =K19 -> 0 | L20: =L19 -> 0 | M20: ='AP03'!D13 -> 2620.69 | N20: =SUM('AP05'!$F20:$L20) -> 2547.4201 | O20: ='AP05'!$M20-'AP05'!$N20 -> 73.26992 | P20: =Q19*('AP05'!$R20-1) -> 0 | Q20: =(Q19*'AP05'!$R20)-'AP05'!$G20-'AP05'!$O20 -> 296862.62 | R20: =R19 -> 1
A21: =A20+1 -> 7 | B21: =EDATE(B20,1) -> 43455 | C21: =C20 -> 0.07 | D21: =D20 -> 0.005654 | E21: ='AP05'!$F21+'AP05'!$G21 -> 2517.0562 | F21: =(Q20*'AP05'!$R21)*'AP05'!$D21 -> 1678.4613 | G21: =(Q20*'AP05'!$R21)/($I$5-A20) -> 838.59498 | H21: =H20 -> 0 | I21: =I20 -> 0 | J21: =J20 -> 25 | K21: =K20 -> 0 | L21: =L20 -> 0 | M21: ='AP03'!D14 -> 2616.41 | N21: =SUM('AP05'!$F21:$L21) -> 2542.0562 | O21: ='AP05'!$M21-'AP05'!$N21 -> 74.353752 | P21: =Q20*('AP05'!$R21-1) -> 0 | Q21: =(Q20*'AP05'!$R21)-'AP05'!$G21-'AP05'!$O21 -> 295949.67 | R21: =R20 -> 1
A22: =A21+1 -> 8 | B22: =EDATE(B21,1) -> 43486 | C22: =C21 -> 0.07 | D22: =D21 -> 0.005654 | E22: ='AP05'!$F22+'AP05'!$G22 -> 2511.6838 | F22: =(Q21*'AP05'!$R22)*'AP05'!$D22 -> 1673.2995 | G22: =(Q21*'AP05'!$R22)/($I$5-A21) -> 838.38435 | H22: =H21 -> 0 | I22: =I21 -> 0 | J22: =J21 -> 25 | K22: =K21 -> 0 | L22: =L21 -> 0 | M22: ='AP03'!D15 -> 2611.57 | N22: =SUM('AP05'!$F22:$L22) -> 2536.6838 | O22: ='AP05'!$M22-'AP05'!$N22 -> 74.886198 | P22: =Q21*('AP05'!$R22-1) -> 0 | Q22: =(Q21*'AP05'!$R22)-'AP05'!$G22-'AP05'!$O22 -> 295036.4 | R22: =R21 -> 1
A23: =A22+1 -> 9 | B23: =EDATE(B22,1) -> 43517 | C23: =C22 -> 0.07 | D23: =D22 -> 0.005654 | E23: ='AP05'!$F23+'AP05'!$G23 -> 2506.3074 | F23: =(Q22*'AP05'!$R23)*'AP05'!$D23 -> 1668.1358 | G23: =(Q22*'AP05'!$R23)/($I$5-A22) -> 838.1716 | H23: =H22 -> 0 | I23: =I22 -> 0 | J23: =J22 -> 25 | K23: =K22 -> 0 | L23: =L22 -> 0 | M23: ='AP03'!D16 -> 2606.73 | N23: =SUM('AP05'!$F23:$L23) -> 2531.3074 | O23: ='AP05'!$M23-'AP05'!$N23 -> 75.422574 | P23: =Q22*('AP05'!$R23-1) -> 0 | Q23: =(Q22*'AP05'!$R23)-'AP05'!$G23-'AP05'!$O23 -> 294122.81 | R23: =R22 -> 1
A24: =A23+1 -> 10 | B24: =EDATE(B23,1) -> 43545 | C24: =C23 -> 0.07 | D24: =D23 -> 0.005654 | E24: ='AP05'!$F24+'AP05'!$G24 -> 2500.9271 | F24: =(Q23*'AP05'!$R24)*'AP05'!$D24 -> 1662.9704 | G24: =(Q23*'AP05'!$R24)/($I$5-A23) -> 837.95672 | H24: =H23 -> 0 | I24: =I23 -> 0 | J24: =J23 -> 25 | K24: =K23 -> 0 | L24: =L23 -> 0 | M24: ='AP03'!D17 -> 2601.89 | N24: =SUM('AP05'!$F24:$L24) -> 2525.9271 | O24: ='AP05'!$M24-'AP05'!$N24 -> 75.962915 | P24: =Q23*('AP05'!$R24-1) -> 0 | Q24: =(Q23*'AP05'!$R24)-'AP05'!$G24-'AP05'!$O24 -> 293208.89 | R24: =R23 -> 1
A25: =A24+1 -> 11 | B25: =EDATE(B24,1) -> 43576 | C25: =C24 -> 0.07 | D25: =D24 -> 0.005654 | E25: ='AP05'!$F25+'AP05'!$G25 -> 2495.5427 | F25: =(Q24*'AP05'!$R25)*'AP05'!$D25 -> 1657.8031 | G25: =(Q24*'AP05'!$R25)/($I$5-A24) -> 837.73968 | H25: =H24 -> 0 | I25: =I24 -> 0 | J25: =J24 -> 25 | K25: =K24 -> 0 | L25: =L24 -> 0 | M25: ='AP03'!D18 -> 2597.05 | N25: =SUM('AP05'!$F25:$L25) -> 2520.5427 | O25: ='AP05'!$M25-'AP05'!$N25 -> 76.507253 | P25: =Q24*('AP05'!$R25-1) -> 0 | Q25: =(Q24*'AP05'!$R25)-'AP05'!$G25-'AP05'!$O25 -> 292294.64 | R25: =R24 -> 1
A26: =A25+1 -> 12 | B26: =EDATE(B25,1) -> 43606 | C26: =C25 -> 0.07 | D26: =D25 -> 0.005654 | E26: ='AP05'!$F26+'AP05'!$G26 -> 2490.1544 | F26: =(Q25*'AP05'!$R26)*'AP05'!$D26 -> 1652.6339 | G26: =(Q25*'AP05'!$R26)/($I$5-A25) -> 837.52047 | H26: =H25 -> 0 | I26: =I25 -> 0 | J26: =J25 -> 25 | K26: =K25 -> 0 | L26: =L25 -> 0 | M26: ='AP03'!D19 -> 2592.21 | N26: =SUM('AP05'!$F26:$L26) -> 2515.1544 | O26: ='AP05'!$M26-'AP05'!$N26 -> 77.055624 | P26: =Q25*('AP05'!$R26-1) -> 0 | Q26: =(Q25*'AP05'!$R26)-'AP05'!$G26-'AP05'!$O26 -> 291380.07 | R26: =R25 -> 1
A27: =A26+1 -> 13 | B27: =EDATE(B26,1) -> 43637 | C27: =C26 -> 0.07 | D27: =D26 -> 0.005654 | E27: ='AP05'!$F27+'AP05'!$G27 -> 2484.7619 | F27: =(Q26*'AP05'!$R27)*'AP05'!$D27 -> 1647.4629 | G27: =(Q26*'AP05'!$R27)/($I$5-A26) -> 837.29904 | H27: =H26 -> 0 | I27: =I26 -> 0 | J27: =J26 -> 25 | K27: =K26 -> 0 | L27: =L26 -> 0 | M27: ='AP03'!D20 -> 2587.38 | N27: =SUM('AP05'!$F27:$L27) -> 2509.7619 | O27: ='AP05'!$M27-'AP05'!$N27 -> 77.618061 | P27: =Q26*('AP05'!$R27-1) -> 0 | Q27: =(Q26*'AP05'!$R27)-'AP05'!$G27-'AP05'!$O27 -> 290465.15 | R27: =R26 -> 1
... A35: =A34+1 -> 21 | B35: =EDATE(B34,1) -> 43882 | C35: =C34 -> 0.07 | D35: =D34 -> 0.005654 | E35: ='AP05'!$F35+'AP05'!$G35 -> 2441.4599 | F35: =(Q34*'AP05'!$R35)*'AP05'!$D35 -> 1606.0187 | G35: =(Q34*'AP05'!$R35)/($I$5-A34) -> 835.4412 | H35: =H34 -> 0 | I35: =I34 -> 0 | J35: =J34 -> 25 | K35: =K34 -> 0 | L35: =L34 -> 0 | M35: ='AP03'!D28 -> 2558.55 | N35: =SUM('AP05'!$F35:$L35) -> 2466.4599 | O35: ='AP05'!$M35-'AP05'!$N35 -> 92.090059 | P35: =Q34*('AP05'!$R35-1) -> 0 | Q35: =(Q34*'AP05'!$R35)-'AP05'!$G35-'AP05'!$O35 -> 283122.48 | R35: =R34 -> 1
A36: =A35+1 -> 22 | B36: =EDATE(B35,1) -> 43911 | C36: 0.062 | D36: 0.005025 | E36: ='AP05'!$F36+'AP05'!$G36 -> 2257.86 | F36: =(Q35*'AP05'!$R36)*'AP05'!$D36 -> 1422.6904 | G36: =(Q35*'AP05'!$R36)/($I$5-A35) -> 835.16955 | H36: =H35 -> 0 | I36: =I35 -> 0 | J36: =J35 -> 25 | K36: =K35 -> 0 | L36: =L35 -> 0 | M36: ='AP03'!D29 -> 2374.56 | N36: =SUM('AP05'!$F36:$L36) -> 2282.86 | O36: ='AP05'!$M36-'AP05'!$N36 -> 91.70001 | P36: =Q35*('AP05'!$R36-1) -> 0 | Q36: =(Q35*'AP05'!$R36)-'AP05'!$G36-'AP05'!$O36 -> 282195.61 | R36: =R35 -> 1
A37: =A36+1 -> 23 | B37: =EDATE(B36,1) -> 43942 | C37: 0.062 | D37: =D36 -> 0.005025 | E37: ='AP05'!$F37+'AP05'!$G37 -> 2252.9312 | F37: =(Q36*'AP05'!$R37)*'AP05'!$D37 -> 1418.0329 | G37: =(Q36*'AP05'!$R37)/($I$5-A36) -> 834.89824 | H37: =H36 -> 0 | I37: =I36 -> 0 | J37: =J36 -> 25 | K37: =K36 -> 0 | L37: =L36 -> 0 | M37: ='AP03'!D30 -> 2370.23 | N37: =SUM('AP05'!$F37:$L37) -> 2277.9312 | O37: ='AP05'!$M37-'AP05'!$N37 -> 92.298832 | P37: =Q36*('AP05'!$R37-1) -> 0 | Q37: =(Q36*'AP05'!$R37)-'AP05'!$G37-'AP05'!$O37 -> 281268.41 | R37: =R36 -> 1
A38: =A37+1 -> 24 | B38: =EDATE(B37,1) -> 43972 | C38: 0.062 | D38: =D37 -> 0.005025 | E38: ='AP05'!$F38+'AP05'!$G38 -> 2247.9981 | F38: =(Q37*'AP05'!$R38)*'AP05'!$D38 -> 1413.3738 | G38: =(Q37*'AP05'!$R38)/($I$5-A37) -> 834.62436 | H38: =H37 -> 0 | I38: =I37 -> 0 | J38: =J37 -> 25 | K38: =K37 -> 0 | L38: =L37 -> 0 | M38: ='AP03'!D31 -> 2365.89 | N38: =SUM('AP05'!$F38:$L38) -> 2272.9981 | O38: ='AP05'!$M38-'AP05'!$N38 -> 92.891881 | P38: =Q37*('AP05'!$R38-1) -> 0 | Q38: =(Q37*'AP05'!$R38)-'AP05'!$G38-'AP05'!$O38 -> 280340.89 | R38: =R37 -> 1
A39: =A38+1 -> 25 | B39: =EDATE(B38,1) -> 44003 | C39: 0.062 | D39: =D38 -> 0.005025 | E39: ='AP05'!$F39+'AP05'!$G39 -> 2243.0609 | F39: =(Q38*'AP05'!$R39)*'AP05'!$D39 -> 1408.713 | G39: =(Q38*'AP05'!$R39)/($I$5-A38) -> 834.3479 | H39: =H38 -> 0 | I39: =I38 -> 0 | J39: =J38 -> 25 | K39: =K38 -> 0 | L39: =L38 -> 0 | M39: ='AP03'!D32 -> 2361.55 | N39: =SUM('AP05'!$F39:$L39) -> 2268.0609 | O39: ='AP05'!$M39-'AP05'!$N39 -> 93.489114 | P39: =Q38*('AP05'!$R39-1) -> 0 | Q39: =(Q38*'AP05'!$R39)-'AP05'!$G39-'AP05'!$O39 -> 279413.06 | R39: =R38 -> 1
A40: =A39+1 -> 26 | B40: =EDATE(B39,1) -> 44033 | C40: 0.062 | D40: =D39 -> 0.005025 | E40: ='AP05'!$F40+'AP05'!$G40 -> 2238.1194 | F40: =(Q39*'AP05'!$R40)*'AP05'!$D40 -> 1404.0506 | G40: =(Q39*'AP05'!$R40)/($I$5-A39) -> 834.06882 | H40: =H39 -> 0 | I40: =I39 -> 0 | J40: =J39 -> 25 | K40: =K39 -> 0 | L40: =L39 -> 0 | M40: ='AP03'!D33 -> 2357.21 | N40: =SUM('AP05'!$F40:$L40) -> 2263.1194 | O40: ='AP05'!$M40-'AP05'!$N40 -> 94.090567 | P40: =Q39*('AP05'!$R40-1) -> 0 | Q40: =(Q39*'AP05'!$R40)-'AP05'!$G40-'AP05'!$O40 -> 278484.9 | R40: =R39 -> 1
A41: =A40+1 -> 27 | B41: =EDATE(B40,1) -> 44064 | C41: 0.062 | D41: =D40 -> 0.005025 | E41: ='AP05'!$F41+'AP05'!$G41 -> 2233.1737 | F41: =(Q40*'AP05'!$R41)*'AP05'!$D41 -> 1399.3866 | G41: =(Q40*'AP05'!$R41)/($I$5-A40) -> 833.78712 | H41: =H40 -> 0 | I41: =I40 -> 0 | J41: =J40 -> 25 | K41: =K40 -> 0 | L41: =L40 -> 0 | M41: ='AP03'!D34 -> 2352.88 | N41: =SUM('AP05'!$F41:$L41) -> 2258.1737 | O41: ='AP05'!$M41-'AP05'!$N41 -> 94.706276 | P41: =Q40*('AP05'!$R41-1) -> 0 | Q41: =(Q40*'AP05'!$R41)-'AP05'!$G41-'AP05'!$O41 -> 277556.4 | R41: =R40 -> 1
A42: =A41+1 -> 28 | B42: =EDATE(B41,1) -> 44095 | C42: =C41 -> 0.062 | D42: =D41 -> 0.005025 | E42: ='AP05'!$F42+'AP05'!$G42 -> 2228.2236 | F42: =(Q41*'AP05'!$R42)*'AP05'!$D42 -> 1394.7209 | G42: =(Q41*'AP05'!$R42)/($I$5-A41) -> 833.50271 | H42: =H41 -> 0 | I42: =I41 -> 0 | J42: =J41 -> 25 | K42: =K41 -> 0 | L42: =L41 -> 0 | M42: ='AP03'!D35 -> 2348.54 | N42: =SUM('AP05'!$F42:$L42) -> 2253.2236 | O42: ='AP05'!$M42-'AP05'!$N42 -> 95.316358 | P42: =Q41*('AP05'!$R42-1) -> 0 | Q42: =(Q41*'AP05'!$R42)-'AP05'!$G42-'AP05'!$O42 -> 276627.58 | R42: =R41 -> 1
A43: =A42+1 -> 29 | B43: =EDATE(B42,1) -> 44125 | C43: =C42 -> 0.062 | D43: =D42 -> 0.005025 | E43: ='AP05'!$F43+'AP05'!$G43 -> 2223.2692 | F43: =(Q42*'AP05'!$R43)*'AP05'!$D43 -> 1390.0536 | G43: =(Q42*'AP05'!$R43)/($I$5-A42) -> 833.21562 | H43: =H42 -> 0 | I43: =I42 -> 0 | J43: =J42 -> 25 | K43: =K42 -> 0 | L43: =L42 -> 0 | M43: ='AP03'!D36 -> 2344.34 | N43: =SUM('AP05'!$F43:$L43) -> 2248.2692 | O43: ='AP05'!$M43-'AP05'!$N43 -> 96.070772 | P43: =Q42*('AP05'!$R43-1) -> 0 | Q43: =(Q42*'AP05'!$R43)-'AP05'!$G43-'AP05'!$O43 -> 275698.3 | R43: =R42 -> 1
A44: =A43+1 -> 30 | B44: =EDATE(B43,1) -> 44156 | C44: =C43 -> 0.062 | D44: =D43 -> 0.005025 | E44: ='AP05'!$F44+'AP05'!$G44 -> 2218.3093 | F44: =(Q43*'AP05'!$R44)*'AP05'!$D44 -> 1385.3839 | G44: =(Q43*'AP05'!$R44)/($I$5-A43) -> 832.92537 | H44: =H43 -> 0 | I44: =I43 -> 0 | J44: =J43 -> 25 | K44: =K43 -> 0 | L44: =L43 -> 0 | M44: ='AP03'!D37 -> 2340 | N44: =SUM('AP05'!$F44:$L44) -> 2243.3093 | O44: ='AP05'!$M44-'AP05'!$N44 -> 96.69068 | P44: =Q43*('AP05'!$R44-1) -> 0 | Q44: =(Q43*'AP05'!$R44)-'AP05'!$G44-'AP05'!$O44 -> 274768.68 | R44: =R43 -> 1
A45: =A44+1 -> 31 | B45: =EDATE(B44,1) -> 44186 | C45: =C44 -> 0.062 | D45: =D44 -> 0.005025 | E45: ='AP05'!$F45+'AP05'!$G45 -> 2213.345 | F45: =(Q44*'AP05'!$R45)*'AP05'!$D45 -> 1380.7126 | G45: =(Q44*'AP05'!$R45)/($I$5-A44) -> 832.63237 | H45: =H44 -> 0 | I45: =I44 -> 0 | J45: =J44 -> 25 | K45: =K44 -> 0 | L45: =L44 -> 0 | M45: ='AP03'!D38 -> 2336.59 | N45: =SUM('AP05'!$F45:$L45) -> 2238.345 | O45: ='AP05'!$M45-'AP05'!$N45 -> 98.245003 | P45: =Q44*('AP05'!$R45-1) -> 0 | Q45: =(Q44*'AP05'!$R45)-'AP05'!$G45-'AP05'!$O45 -> 273837.8 | R45: =R44 -> 1
A46: =A45+1 -> 32 | B46: =EDATE(B45,1) -> 44217 | C46: =C45 -> 0.062 | D46: =D45 -> 0.005025 | E46: ='AP05'!$F46+'AP05'!$G46 -> 2208.3687 | F46: =(Q45*'AP05'!$R46)*'AP05'!$D46 -> 1376.035 | G46: =(Q45*'AP05'!$R46)/($I$5-A45) -> 832.33375 | H46: =H45 -> 0 | I46: =I45 -> 0 | J46: =J45 -> 25 | K46: =K45 -> 0 | L46: =L45 -> 0 | M46: ='AP03'!D39 -> 2332.25 | N46: =SUM('AP05'!$F46:$L46) -> 2233.3687 | O46: ='AP05'!$M46-'AP05'!$N46 -> 98.881278 | P46: =Q45*('AP05'!$R46-1) -> 0 | Q46: =(Q45*'AP05'!$R46)-'AP05'!$G46-'AP05'!$O46 -> 272906.59 | R46: =R45 -> 1
A47: =A46+1 -> 33 | B47: =EDATE(B46,1) -> 44248 | C47: =C46 -> 0.062 | D47: =D46 -> 0.005025 | E47: ='AP05'!$F47+'AP05'!$G47 -> 2203.3879 | F47: =(Q46*'AP05'!$R47)*'AP05'!$D47 -> 1371.3556 | G47: =(Q46*'AP05'!$R47)/($I$5-A46) -> 832.03229 | H47: =H46 -> 0 | I47: =I46 -> 0 | J47: =J46 -> 25 | K47: =K46 -> 0 | L47: =L46 -> 0 | M47: ='AP03'!D40 -> 2328.53 | N47: =SUM('AP05'!$F47:$L47) -> 2228.3879 | O47: ='AP05'!$M47-'AP05'!$N47 -> 100.1421 | P47: =Q46*('AP05'!$R47-1) -> 0 | Q47: =(Q46*'AP05'!$R47)-'AP05'!$G47-'AP05'!$O47 -> 271974.42 | R47: =R46 -> 1
A48: =A47+1 -> 34 | B48: =EDATE(B47,1) -> 44276 | C48: =C47 -> 0.062 | D48: =D47 -> 0.005025 | E48: ='AP05'!$F48+'AP05'!$G48 -> 2198.3975 | F48: =(Q47*'AP05'!$R48)*'AP05'!$D48 -> 1366.6714 | G48: =(Q47*'AP05'!$R48)/($I$5-A47) -> 831.72604 | H48: =H47 -> 0 | I48: =I47 -> 0 | J48: =J47 -> 25 | K48: =K47 -> 0 | L48: =L47 -> 0 | M48: ='AP03'!D41 -> 2324.19 | N48: =SUM('AP05'!$F48:$L48) -> 2223.3975 | O48: ='AP05'!$M48-'AP05'!$N48 -> 100.79252 | P48: =Q47*('AP05'!$R48-1) -> 0 | Q48: =(Q47*'AP05'!$R48)-'AP05'!$G48-'AP05'!$O48 -> 271041.9 | R48: =R47 -> 1
A49: =A48+1 -> 35 | B49: =EDATE(B48,1) -> 44307 | C49: =C48 -> 0.062 | D49: =D48 -> 0.005025 | E49: ='AP05'!$F49+'AP05'!$G49 -> 2193.4024 | F49: =(Q48*'AP05'!$R49)*'AP05'!$D49 -> 1361.9855 | G49: =(Q48*'AP05'!$R49)/($I$5-A48) -> 831.41686 | H49: =H48 -> 0 | I49: =I48 -> 0 | J49: =J48 -> 25 | K49: =K48 -> 0 | L49: =L48 -> 0 | M49: ='AP03'!D42 -> 2319.85 | N49: =SUM('AP05'!$F49:$L49) -> 2218.4024 | O49: ='AP05'!$M49-'AP05'!$N49 -> 101.44761 | P49: =Q48*('AP05'!$R49-1) -> 0 | Q49: =(Q48*'AP05'!$R49)-'AP05'!$G49-'AP05'!$O49 -> 270109.03 | R49: =R48 -> 1
A50: =A49+1 -> 36 | B50: =EDATE(B49,1) -> 44337 | C50: =C49 -> 0.062 | D50: =D49 -> 0.005025 | E50: ='AP05'!$F50+'AP05'!$G50 -> 2188.4026 | F50: =(Q49*'AP05'!$R50)*'AP05'!$D50 -> 1357.2979 | G50: =(Q49*'AP05'!$R50)/($I$5-A49) -> 831.10471 | H50: =H49 -> 0 | I50: =I49 -> 0 | J50: =J49 -> 25 | K50: =K49 -> 0 | L50: =L49 -> 0 | M50: ='AP03'!D43 -> 2315.51 | N50: =SUM('AP05'!$F50:$L50) -> 2213.4026 | O50: ='AP05'!$M50-'AP05'!$N50 -> 102.1074 | P50: =Q49*('AP05'!$R50-1) -> 0 | Q50: =(Q49*'AP05'!$R50)-'AP05'!$G50-'AP05'!$O50 -> 269175.82 | R50: =R49 -> 1
A51: =A50+1 -> 37 | B51: =EDATE(B50,1) -> 44368 | C51: =C50 -> 0.062 | D51: =D50 -> 0.005025 | E51: ='AP05'!$F51+'AP05'!$G51 -> 2183.3981 | F51: =(Q50*'AP05'!$R51)*'AP05'!$D51 -> 1352.6085 | G51: =(Q50*'AP05'!$R51)/($I$5-A50) -> 830.78957 | H51: =H50 -> 0 | I51: =I50 -> 0 | J51: =J50 -> 25 | K51: =K50 -> 0 | L51: =L50 -> 0 | M51: ='AP03'!D44 -> 2311.16 | N51: =SUM('AP05'!$F51:$L51) -> 2208.3981 | O51: ='AP05'!$M51-'AP05'!$N51 -> 102.76194 | P51: =Q50*('AP05'!$R51-1) -> 0 | Q51: =(Q50*'AP05'!$R51)-'AP05'!$G51-'AP05'!$O51 -> 268242.27 | R51: =R50 -> 1
A52: =A51+1 -> 38 | B52: =EDATE(B51,1) -> 44398 | C52: =C51 -> 0.062 | D52: =D51 -> 0.005025 | E52: ='AP05'!$F52+'AP05'!$G52 -> 2178.3888 | F52: =(Q51*'AP05'!$R52)*'AP05'!$D52 -> 1347.9174 | G52: =(Q51*'AP05'!$R52)/($I$5-A51) -> 830.47142 | H52: =H51 -> 0 | I52: =I51 -> 0 | J52: =J51 -> 25 | K52: =K51 -> 0 | L52: =L51 -> 0 | M52: ='AP03'!D45 -> 2306.81 | N52: =SUM('AP05'!$F52:$L52) -> 2203.3888 | O52: ='AP05'!$M52-'AP05'!$N52 -> 103.42118 | P52: =Q51*('AP05'!$R52-1) -> 0 | Q52: =(Q51*'AP05'!$R52)-'AP05'!$G52-'AP05'!$O52 -> 267308.38 | R52: =R51 -> 1
A53: =A52+1 -> 39 | B53: =EDATE(B52,1) -> 44429 | C53: =C52 -> 0.062 | D53: =D52 -> 0.005025 | E53: ='AP05'!$F53+'AP05'!$G53 -> 2173.3748 | F53: =(Q52*'AP05'!$R53)*'AP05'!$D53 -> 1343.2246 | G53: =(Q52*'AP05'!$R53)/($I$5-A52) -> 830.15024 | H53: =H52 -> 0 | I53: =I52 -> 0 | J53: =J52 -> 25 | K53: =K52 -> 0 | L53: =L52 -> 0 | M53: ='AP03'!D46 -> 2302.47 | N53: =SUM('AP05'!$F53:$L53) -> 2198.3748 | O53: ='AP05'!$M53-'AP05'!$N53 -> 104.09517 | P53: =Q52*('AP05'!$R53-1) -> 0 | Q53: =(Q52*'AP05'!$R53)-'AP05'!$G53-'AP05'!$O53 -> 266374.13 | R53: =R52 -> 1
... A57: =A56+1 -> 43 | B57: =EDATE(B56,1) -> 44551 | C57: =C56 -> 0.062 | D57: =D56 -> 0.005025 | E57: ='AP05'!$F57+'AP05'!$G57 -> 2153.2698 | F57: =(Q56*'AP05'!$R57)*'AP05'!$D57 -> 1324.4356 | G57: =(Q56*'AP05'!$R57)/($I$5-A56) -> 828.83418 | H57: =H56 -> 0 | I57: =I56 -> 0 | J57: =J56 -> 25 | K57: =K56 -> 0 | L57: =L56 -> 0 | M57: ='AP03'!D50 -> 2294.47 | N57: =SUM('AP05'!$F57:$L57) -> 2178.2698 | O57: ='AP05'!$M57-'AP05'!$N57 -> 116.20024 | P57: =Q56*('AP05'!$R57-1) -> 0 | Q57: =(Q56*'AP05'!$R57)-'AP05'!$G57-'AP05'!$O57 -> 262624.24 | R57: =R56 -> 1
A58: =A57+1 -> 44 | B58: =EDATE(B57,1) -> 44582 | C58: =C57 -> 0.062 | D58: =D57 -> 0.005025 | E58: ='AP05'!$F58+'AP05'!$G58 -> 2150.7214 | F58: =(Q57*'AP05'!$R58)*'AP05'!$D58 -> 1321.2638 | G58: =(Q57*'AP05'!$R58)/($I$5-A57) -> 829.45764 | H58: =H57 -> 0 | I58: =I57 -> 0 | J58: =J57 -> 25 | K58: =K57 -> 0 | L58: =L57 -> 0 | M58: ='AP03'!D51 -> 2292.79 | N58: =SUM('AP05'!$F58:$L58) -> 2175.7214 | O58: ='AP05'!$M58-'AP05'!$N58 -> 117.06855 | P58: =Q57*('AP05'!$R58-1) -> 313.83596 | Q58: =(Q57*'AP05'!$R58)-'AP05'!$G58-'AP05'!$O58 -> 261991.55 | R58: 1.001195
A59: =A58+1 -> 45 | B59: =EDATE(B58,1) -> 44613 | C59: =C58 -> 0.062 | D59: =D58 -> 0.005025 | E59: ='AP05'!$F59+'AP05'!$G59 -> 2147.3991 | F59: =(Q58*'AP05'!$R59)*'AP05'!$D59 -> 1317.6147 | G59: =(Q58*'AP05'!$R59)/($I$5-A58) -> 829.78443 | H59: =H58 -> 0 | I59: =I58 -> 0 | J59: =J58 -> 25 | K59: =K58 -> 0 | L59: =L58 -> 0 | M59: ='AP03'!D52 -> 2290.94 | N59: =SUM('AP05'!$F59:$L59) -> 2172.3991 | O59: ='AP05'!$M59-'AP05'!$N59 -> 118.54087 | P59: =Q58*('AP05'!$R59-1) -> 220.33489 | Q59: =(Q58*'AP05'!$R59)-'AP05'!$G59-'AP05'!$O59 -> 261263.55 | R59: 1.000841
A60: =A59+1 -> 46 | B60: =EDATE(B59,1) -> 44641 | C60: =C59 -> 0.062 | D60: =D59 -> 0.005025 | E60: ='AP05'!$F60+'AP05'!$G60 -> 2142.2575 | F60: =(Q59*'AP05'!$R60)*'AP05'!$D60 -> 1312.8494 | G60: =(Q59*'AP05'!$R60)/($I$5-A59) -> 829.40811 | H60: =H59 -> 0 | I60: =I59 -> 0 | J60: =J59 -> 25 | K60: =K59 -> 0 | L60: =L59 -> 0 | M60: ='AP03'!D53 -> 2286.56 | N60: =SUM('AP05'!$F60:$L60) -> 2167.2575 | O60: ='AP05'!$M60-'AP05'!$N60 -> 119.30253 | P60: =Q59*('AP05'!$R60-1) -> 0 | Q60: =(Q59*'AP05'!$R60)-'AP05'!$G60-'AP05'!$O60 -> 260314.84 | R60: 1
A61: =A60+1 -> 47 | B61: =EDATE(B60,1) -> 44672 | C61: =C60 -> 0.062 | D61: =D60 -> 0.005025 | E61: ='AP05'!$F61+'AP05'!$G61 -> 2139.9355 | F61: =(Q60*'AP05'!$R61)*'AP05'!$D61 -> 1309.8114 | G61: =(Q60*'AP05'!$R61)/($I$5-A60) -> 830.12414 | H61: =H60 -> 0 | I61: =I60 -> 0 | J61: =J60 -> 25 | K61: =K60 -> 0 | L61: =L60 -> 0 | M61: ='AP03'!D54 -> 2282.17 | N61: =SUM('AP05'!$F61:$L61) -> 2164.9355 | O61: ='AP05'!$M61-'AP05'!$N61 -> 117.23448 | P61: =Q60*('AP05'!$R61-1) -> 344.13622 | Q61: =(Q60*'AP05'!$R61)-'AP05'!$G61-'AP05'!$O61 -> 259711.62 | R61: 1.001322
A62: =A61+1 -> 48 | B62: =EDATE(B61,1) -> 44702 | C62: =C61 -> 0.062 | D62: =D61 -> 0.005025 | E62: ='AP05'!$F62+'AP05'!$G62 -> 2137.58 | F62: =(Q61*'AP05'!$R62)*'AP05'!$D62 -> 1306.7501 | G62: =(Q61*'AP05'!$R62)/($I$5-A61) -> 830.82992 | H62: =H61 -> 0 | I62: =I61 -> 0 | J62: =J61 -> 25 | K62: =K61 -> 0 | L62: =L61 -> 0 | M62: ='AP03'!D55 -> 2283.71 | N62: =SUM('AP05'!$F62:$L62) -> 2162.58 | O62: ='AP05'!$M62-'AP05'!$N62 -> 121.13 | P62: =Q61*('AP05'!$R62-1) -> 338.14453 | Q62: =(Q61*'AP05'!$R62)-'AP05'!$G62-'AP05'!$O62 -> 259097.81 | R62: 1.001302
A63: =A62+1 -> 49 | B63: =EDATE(B62,1) -> 44733 | C63: =C62 -> 0.062 | D63: =D62 -> 0.005025 | E63: =E62 -> 2137.58 | F63: =(Q62*'AP05'!$R63)*'AP05'!$D63 -> 1303.3492 | G63: =(Q62*'AP05'!$R63)/($I$5-A62) -> 831.32362 | H63: =H62 -> 0 | I63: =I62 -> 0 | J63: =J62 -> 25 | K63: =K62 -> 0 | L63: =L62 -> 0 | M63: ='AP03'!D56 -> 2284.69 | N63: =SUM('AP05'!$F63:$L63) -> 2159.6728 | O63: ='AP05'!$M63-'AP05'!$N63 -> 125.01722 | P63: =Q62*('AP05'!$R63-1) -> 275.16187 | Q63: =(Q62*'AP05'!$R63)-'AP05'!$G63-'AP05'!$O63 -> 258416.63 | R63: 1.001062
A64: =A63+1 -> 50 | B64: =EDATE(B63,1) -> 44763 | C64: =C63 -> 0.062 | D64: =D63 -> 0.005025 | E64: =E63 -> 2137.58 | F64: =(Q63*'AP05'!$R64)*'AP05'!$D64 -> 1301.0407 | G64: =(Q63*'AP05'!$R64)/($I$5-A63) -> 832.51949 | H64: =H63 -> 0 | I64: =I63 -> 0 | J64: =J63 -> 25 | K64: =K63 -> 0 | L64: =L63 -> 0 | M64: ='AP03'!D57 -> 2281.63 | N64: =SUM('AP05'!$F64:$L64) -> 2158.5601 | O64: ='AP05'!$M64-'AP05'!$N64 -> 123.06986 | P64: =Q63*('AP05'!$R64-1) -> 496.93517 | Q64: =(Q63*'AP05'!$R64)-'AP05'!$G64-'AP05'!$O64 -> 257957.97 | R64: 1.001923
A65: =A64+1 -> 51 | B65: =EDATE(B64,1) -> 44794 | C65: =C64 -> 0.062 | D65: =D64 -> 0.005025 | E65: =E64 -> 2137.58 | F65: =(Q64*'AP05'!$R65)*'AP05'!$D65 -> 1298.948 | G65: =(Q64*'AP05'!$R65)/($I$5-A64) -> 833.86163 | H65: =H64 -> 0 | I65: =I64 -> 0 | J65: =J64 -> 25 | K65: =K64 -> 0 | L65: =L64 -> 0 | M65: ='AP03'!D58 -> 2281.94 | N65: =SUM('AP05'!$F65:$L65) -> 2157.8096 | O65: ='AP05'!$M65-'AP05'!$N65 -> 124.13042 | P65: =Q64*('AP05'!$R65-1) -> 539.13216 | Q65: =(Q64*'AP05'!$R65)-'AP05'!$G65-'AP05'!$O65 -> 257539.11 | R65: 1.00209
A66: =A65+1 -> 52 | B66: =EDATE(B65,1) -> 44825 | C66: =C65 -> 0.062 | D66: =D65 -> 0.005025 | E66: =E65 -> 2137.58 | F66: =(Q65*'AP05'!$R66)*'AP05'!$D66 -> 1296.4531 | G66: =(Q65*'AP05'!$R66)/($I$5-A65) -> 834.95347 | H66: =H65 -> 0 | I66: =I65 -> 0 | J66: =J65 -> 25 | K66: =K65 -> 0 | L66: =L65 -> 0 | M66: ='AP03'!D59 -> 2281.56 | N66: =SUM('AP05'!$F66:$L66) -> 2156.4066 | O66: ='AP05'!$M66-'AP05'!$N66 -> 125.15339 | P66: =Q65*('AP05'!$R66-1) -> 461.51009 | Q66: =(Q65*'AP05'!$R66)-'AP05'!$G66-'AP05'!$O66 -> 257040.52 | R66: 1.001792
A67: =A66+1 -> 53 | B67: =EDATE(B66,1) -> 44855 | C67: =C66 -> 0.062 | D67: =D66 -> 0.005025 | E67: =E66 -> 2137.58 | F67: =(Q66*'AP05'!$R67)*'AP05'!$D67 -> 1294 | G67: =(Q66*'AP05'!$R67)/($I$5-A66) -> 836.07936 | H67: =H66 -> 0 | I67: =I66 -> 0 | J67: =J66 -> 25 | K67: =K66 -> 0 | L67: =L66 -> 0 | M67: ='AP03'!D60 -> 2281.26 | N67: =SUM('AP05'!$F67:$L67) -> 2155.0794 | O67: ='AP05'!$M67-'AP05'!$N67 -> 126.18061 | P67: =Q66*('AP05'!$R67-1) -> 471.92639 | Q67: =(Q66*'AP05'!$R67)-'AP05'!$G67-'AP05'!$O67 -> 256550.18 | R67: 1.001836
A68: =A67+1 -> 54 | B68: =EDATE(B67,1) -> 44886 | C68: =C67 -> 0.062 | D68: =D67 -> 0.005025 | E68: =E67 -> 2137.58 | F68: =(Q67*'AP05'!$R68)*'AP05'!$D68 -> 1290.6304 | G68: =(Q67*'AP05'!$R68)/($I$5-A67) -> 836.6185 | H68: =H67 -> 0 | I68: =I67 -> 0 | J68: =J67 -> 25 | K68: =K67 -> 0 | L68: =L67 -> 0 | M68: ='AP03'!D61 -> 2279.39 | N68: =SUM('AP05'!$F68:$L68) -> 2152.249 | O68: ='AP05'!$M68-'AP05'!$N68 -> 127.14105 | P68: =Q67*('AP05'!$R68-1) -> 291.69756 | Q68: =(Q67*'AP05'!$R68)-'AP05'!$G68-'AP05'!$O68 -> 255878.12 | R68: 1.001137
A69: =A68+1 -> 55 | B69: =EDATE(B68,1) -> 44916 | C69: =C68 -> 0.062 | D69: =D68 -> 0.005025 | E69: =E68 -> 2137.58 | F69: =(Q68*'AP05'!$R69)*'AP05'!$D69 -> 1288.4787 | G69: =(Q68*'AP05'!$R69)/($I$5-A68) -> 837.95318 | H69: =H68 -> 0 | I69: =I68 -> 0 | J69: =J68 -> 25 | K69: =K68 -> 0 | L69: =L68 -> 0 | M69: ='AP03'!D62 -> 2281.2 | N69: =SUM('AP05'!$F69:$L69) -> 2151.4319 | O69: ='AP05'!$M69-'AP05'!$N69 -> 129.76811 | P69: =Q68*('AP05'!$R69-1) -> 535.55291 | Q69: =(Q68*'AP05'!$R69)-'AP05'!$G69-'AP05'!$O69 -> 255445.95 | R69: 1.002093
A70: =A69+1 -> 56 | B70: =EDATE(B69,1) -> 44947 | C70: =C69 -> 0.062 | D70: =D69 -> 0.005025 | E70: =E69 -> 2137.58 | F70: =(Q69*'AP05'!$R70)*'AP05'!$D70 -> 1286.7094 | G70: =(Q69*'AP05'!$R70)/($I$5-A69) -> 839.54615 | H70: =H69 -> 0 | I70: =I69 -> 0 | J70: =J69 -> 25 | K70: =K69 -> 0 | L70: =L69 -> 0 | M70: ='AP03'!D63 -> 2282.16 | N70: =SUM('AP05'!$F70:$L70) -> 2151.2556 | O70: ='AP05'!$M70-'AP05'!$N70 -> 130.90442 | P70: =Q69*('AP05'!$R70-1) -> 615.62475 | Q70: =(Q69*'AP05'!$R70)-'AP05'!$G70-'AP05'!$O70 -> 255091.13 | R70: 1.00241
A71: =A70+1 -> 57 | B71: =EDATE(B70,1) -> 44978 | C71: =C70 -> 0.062 | D71: =D70 -> 0.005025 | E71: =E70 -> 2137.58 | F71: =(Q70*'AP05'!$R71)*'AP05'!$D71 -> 1283.7403 | G71: =(Q70*'AP05'!$R71)/($I$5-A70) -> 840.36415 | H71: =H70 -> 0 | I71: =I70 -> 0 | J71: =J70 -> 25 | K71: =K70 -> 0 | L71: =L70 -> 0 | M71: ='AP03'!D64 -> 2281.76 | N71: =SUM('AP05'!$F71:$L71) -> 2149.1044 | O71: ='AP05'!$M71-'AP05'!$N71 -> 132.65557 | P71: =Q70*('AP05'!$R71-1) -> 379.5756 | Q71: =(Q70*'AP05'!$R71)-'AP05'!$G71-'AP05'!$O71 -> 254497.68 | R71: 1.001488
A72: =A71+1 -> 58 | B72: =EDATE(B71,1) -> 45006 | C72: =C71 -> 0.062 | D72: =D71 -> 0.005025 | E72: =E71 -> 2137.58 | F72: =(Q71*'AP05'!$R72)*'AP05'!$D72 -> 1280.2499 | G72: =(Q71*'AP05'!$R72)/($I$5-A71) -> 840.84522 | H72: =H71 -> 0 | I72: =I71 -> 0 | J72: =J71 -> 25 | K72: =K71 -> 0 | L72: =L71 -> 0 | M72: ='AP03'!D65 -> 2279.74 | N72: =SUM('AP05'!$F72:$L72) -> 2146.0951 | O72: ='AP05'!$M72-'AP05'!$N72 -> 133.64486 | P72: =Q71*('AP05'!$R72-1) -> 278.42046 | Q72: =(Q71*'AP05'!$R72)-'AP05'!$G72-'AP05'!$O72 -> 253801.61 | R72: 1.001094
A73: =A72+1 -> 59 | B73: =EDATE(B72,1) -> 45037 | C73: =C72 -> 0.062 | D73: =D72 -> 0.005025 | E73: =E72 -> 2137.58 | F73: =(Q72*'AP05'!$R73)*'AP05'!$D73 -> 1278.0173 | G73: =(Q72*'AP05'!$R73)/($I$5-A72) -> 842.15829 | H73: =H72 -> 0 | I73: =I72 -> 0 | J73: =J72 -> 25 | K73: =K72 -> 0 | L73: =L72 -> 0 | M73: ='AP03'!D66 -> 2279.98 | N73: =SUM('AP05'!$F73:$L73) -> 2145.1756 | O73: ='AP05'!$M73-'AP05'!$N73 -> 134.80439 | P73: =Q72*('AP05'!$R73-1) -> 530.19157 | Q73: =(Q72*'AP05'!$R73)-'AP05'!$G73-'AP05'!$O73 -> 253354.84 | R73: 1.002089
A74: =A73+1 -> 60 | B74: =EDATE(B73,1) -> 45067 | C74: =C73 -> 0.062 | D74: =D73 -> 0.005025 | E74: =E73 -> 2137.58 | F74: =(Q73*'AP05'!$R74)*'AP05'!$D74 -> 1274.534 | G74: =(Q73*'AP05'!$R74)/($I$5-A73) -> 842.65315 | H74: =H73 -> 0 | I74: =I73 -> 0 | J74: =J73 -> 25 | K74: =K73 -> 0 | L74: =L73 -> 0 | M74: ='AP03'!D67 -> 2278.01 | N74: =SUM('AP05'!$F74:$L74) -> 2142.1871 | O74: ='AP05'!$M74-'AP05'!$N74 -> 135.82289 | P74: =Q73*('AP05'!$R74-1) -> 283.75742 | Q74: =(Q73*'AP05'!$R74)-'AP05'!$G74-'AP05'!$O74 -> 252660.12 | R74: 1.00112
... A76: =A75+1 -> 62 | B76: =EDATE(B75,1) -> 45128 | C76: =C75 -> 0.062 | D76: =D75 -> 0.005025 | E76: =E75 -> 2137.58 | F76: =(Q75*'AP05'!$R76)*'AP05'!$D76 -> 1269.501 | G76: =(Q75*'AP05'!$R76)/($I$5-A75) -> 844.93983 | H76: =H75 -> 0 | I76: =I75 -> 0 | J76: =J75 -> 25 | K76: =K75 -> 0 | L76: =L75 -> 0 | M76: ='AP03'!D69 -> 2277.54 | N76: =SUM('AP05'!$F76:$L76) -> 2139.4408 | O76: ='AP05'!$M76-'AP05'!$N76 -> 138.0992 | P76: =Q75*('AP05'!$R76-1) -> 505.02037 | Q76: =(Q75*'AP05'!$R76)-'AP05'!$G76-'AP05'!$O76 -> 251653.97 | R76: 1.002003
A77: =A76+1 -> 63 | B77: =EDATE(B76,1) -> 45159 | C77: =I7 -> 0.0775 | D77: =I6 -> 0.0062 | E77: =E76 -> 2137.58 | F77: =(Q76*'AP05'!$R77)*'AP05'!$D77 -> 1562.7198 | G77: =(Q76*'AP05'!$R77)/($I$5-A76) -> 845.81068 | H77: =H76 -> 0 | I77: =I76 -> 0 | J77: =J76 -> 25 | K77: =K76 -> 0 | L77: =L76 -> 0 | M77: ='AP03'!D70 -> 3133.63 | N77: =SUM('AP05'!$F77:$L77) -> 2433.5305 | O77: ='AP05'!$M77-'AP05'!$N77 -> 700.0995 | P77: =Q76*('AP05'!$R77-1) -> 397.61327 | Q77: =(Q76*'AP05'!$R77)-'AP05'!$G77-'AP05'!$O77 -> 250505.67 | R77: 1.00158
A78: =A77+1 -> 64 | B78: =EDATE(B77,1) -> 45190 | C78: =C77 -> 0.0775 | D78: =D77 -> 0.0062 | E78: =E77 -> 2137.58 | F78: =(Q77*'AP05'!$R78)*'AP05'!$D78 -> 1555.8966 | G78: =(Q77*'AP05'!$R78)/($I$5-A77) -> 844.9531 | H78: =H77 -> 0 | I78: =I77 -> 0 | J78: =J77 -> 25 | K78: =K77 -> 0 | L78: =L77 -> 0 | M78: ='AP03'!D71 -> 3131.76 | N78: =SUM('AP05'!$F78:$L78) -> 2425.8498 | O78: ='AP05'!$M78-'AP05'!$N78 -> 705.91025 | P78: =Q77*('AP05'!$R78-1) -> 445.39909 | Q78: =(Q77*'AP05'!$R78)-'AP05'!$G78-'AP05'!$O78 -> 249400.21 | R78: 1.001778
A79: =A78+1 -> 65 | B79: =EDATE(B78,1) -> 45220 | C79: =C78 -> 0.0775 | D79: =((1+'AP05'!$C79)^(1/12))-1 -> 0.0062396815 | E79: =E78 -> 2137.58 | F79: =(Q78*'AP05'!$R79)*'AP05'!$D79 -> 1557.9675 | G79: =(Q78*'AP05'!$R79)/($I$5-A78) -> 843.53723 | H79: =H78 -> 0 | I79: =I78 -> 0 | J79: =J78 -> 25 | K79: =K78 -> 0 | L79: =L78 -> 0 | M79: ='AP03'!D72 -> 3127.92 | N79: =SUM('AP05'!$F79:$L79) -> 2426.5047 | O79: ='AP05'!$M79-'AP05'!$N79 -> 701.41531 | P79: =Q78*('AP05'!$R79-1) -> 286.81024 | Q79: =(Q78*'AP05'!$R79)-'AP05'!$G79-'AP05'!$O79 -> 248142.07 | R79: 1.00115
A80: =A79+1 -> 66 | B80: =EDATE(B79,1) -> 45251 | C80: =C79 -> 0.0775 | D80: =((1+'AP05'!$C80)^(1/12))-1 -> 0.0062396815 | E80: =E79 -> 2137.58 | F80: =(Q79*'AP05'!$R80)*'AP05'!$D80 -> 1549.097 | G80: =(Q79*'AP05'!$R80)/($I$5-A79) -> 841.5776 | H80: =H79 -> 0 | I80: =I79 -> 0 | J80: =J79 -> 25 | K80: =K79 -> 0 | L80: =L79 -> 0 | M80: ='AP03'!D73 -> 3122.04 | N80: =SUM('AP05'!$F80:$L80) -> 2415.6746 | O80: ='AP05'!$M80-'AP05'!$N80 -> 706.36543 | P80: =Q79*('AP05'!$R80-1) -> 123.32661 | Q80: =(Q79*'AP05'!$R80)-'AP05'!$G80-'AP05'!$O80 -> 246717.45 | R80: 1.000497
A81: =A80+1 -> 67 | B81: =EDATE(B80,1) -> 45281 | C81: =C80 -> 0.0775 | D81: =((1+'AP05'!$C81)^(1/12))-1 -> 0.0062396815 | E81: =E80 -> 2137.58 | F81: =(Q80*'AP05'!$R81)*'AP05'!$D81 -> 1541.4042 | G81: =(Q80*'AP05'!$R81)/($I$5-A80) -> 840.24663 | H81: =H80 -> 0 | I81: =I80 -> 0 | J81: =J80 -> 25 | K81: =K80 -> 0 | L81: =L80 -> 0 | M81: ='AP03'!D74 -> 3120.41 | N81: =SUM('AP05'!$F81:$L81) -> 2406.6508 | O81: ='AP05'!$M81-'AP05'!$N81 -> 713.75921 | P81: =Q80*('AP05'!$R81-1) -> 315.05818 | Q81: =(Q80*'AP05'!$R81)-'AP05'!$G81-'AP05'!$O81 -> 245478.5 | R81: 1.001277
A82: =A81+1 -> 68 | B82: =EDATE(B81,1) -> 45312 | C82: =C81 -> 0.0775 | D82: =((1+'AP05'!$C82)^(1/12))-1 -> 0.0062396815 | E82: =E81 -> 2137.58 | F82: =(Q81*'AP05'!$R82)*'AP05'!$D82 -> 1532.4184 | G82: =(Q81*'AP05'!$R82)/($I$5-A81) -> 838.19933 | H82: =H81 -> 0 | I82: =I81 -> 0 | J82: =J81 -> 25 | K82: =K81 -> 0 | L82: =L81 -> 0 | M82: ='AP03'!D75 -> 3114.42 | N82: =SUM('AP05'!$F82:$L82) -> 2395.6177 | O82: ='AP05'!$M82-'AP05'!$N82 -> 718.8023 | P82: =Q81*('AP05'!$R82-1) -> 113.90203 | Q82: =(Q81*'AP05'!$R82)-'AP05'!$G82-'AP05'!$O82 -> 244035.4 | R82: 1.000464
A83: =A82+1 -> 69 | B83: =EDATE(B82,1) -> 45343 | C83: =C82 -> 0.0775 | D83: =((1+'AP05'!$C83)^(1/12))-1 -> 0.0062396815 | E83: =E82 -> 2137.58 | F83: =(Q82*'AP05'!$R83)*'AP05'!$D83 -> 1523.2772 | G83: =(Q82*'AP05'!$R83)/($I$5-A82) -> 836.05275 | H83: =H82 -> 0 | I83: =I82 -> 0 | J83: =J82 -> 25 | K83: =K82 -> 0 | L83: =L82 -> 0 | M83: ='AP03'!D76 -> 3109.21 | N83: =SUM('AP05'!$F83:$L83) -> 2384.33 | O83: ='AP05'!$M83-'AP05'!$N83 -> 724.88001 | P83: =Q82*('AP05'!$R83-1) -> 92.001347 | Q83: =(Q82*'AP05'!$R83)-'AP05'!$G83-'AP05'!$O83 -> 242566.47 | R83: 1.000377
A84: =A83+1 -> 70 | B84: =EDATE(B83,1) -> 45372 | C84: =C83 -> 0.0775 | D84: =((1+'AP05'!$C84)^(1/12))-1 -> 0.0062396815 | E84: =E83 -> 2137.58 | F84: =(Q83*'AP05'!$R84)*'AP05'!$D84 -> 1514.5183 | G84: =(Q83*'AP05'!$R84)/($I$5-A83) -> 834.1019 | H84: =H83 -> 0 | I84: =I83 -> 0 | J84: =J83 -> 25 | K84: =K83 -> 0 | L84: =L83 -> 0 | M84: ='AP03'!D77 -> 3103.77 | N84: =SUM('AP05'!$F84:$L84) -> 2373.6202 | O84: ='AP05'!$M84-'AP05'!$N84 -> 730.14981 | P84: =Q83*('AP05'!$R84-1) -> 157.18307 | Q84: =(Q83*'AP05'!$R84)-'AP05'!$G84-'AP05'!$O84 -> 241159.4 | R84: 1.000648 | T84: ='AP05'!$Q84+0.02 -> 241159.42 | U84: 3103.77 | V84: =T84+U84-'AP05'!$G84 -> 243429.09
A85: =A84+1 -> 71 | B85: =EDATE(B84,1) -> 45403 | C85: =C84 -> 0.0775 | D85: =((1+'AP05'!$C85)^(1/12))-1 -> 0.0062396815 | E85: =E84 -> 2137.58 | F85: =(Q84*'AP05'!$R85)*'AP05'!$D85 -> 1505.7028 | G85: =(Q84*'AP05'!$R85)/($I$5-A84) -> 832.10638 | H85: =H84 -> 0 | I85: =I84 -> 0 | J85: =J84 -> 25 | K85: =K84 -> 0 | L85: =L84 -> 0 | M85: ='AP03'!D78 -> 3135.52 | N85: =SUM('AP05'!$F85:$L85) -> 2362.8092 | O85: ='AP05'!$M85-'AP05'!$N85 -> 772.71078 | P85: =Q84*('AP05'!$R85-1) -> 151.4481 | Q85: =(Q84*'AP05'!$R85)+'AP05'!$F85 -> 242816.55 | R85: 1.000628 | T85: =(T84*'AP05'!$R85)+(U84*'AP05'!$R85) -> 244416.59 | U85: =2115.97+871.08+51.45+40.27+25 -> 3103.77
A86: =A85+1 -> 72 | B86: =EDATE(B85,1) -> 45433 | C86: =C85 -> 0.0775 | D86: =((1+'AP05'!$C86)^(1/12))-1 -> 0.0062396815 | E86: =E85 -> 2137.58 | F86: =(Q85*'AP05'!$R86)*'AP05'!$D86 -> 1515.6479 | G86: =(Q85*'AP05'!$R86)/($I$5-A85) -> 840.50068 | H86: =H85 -> 0 | I86: =I85 -> 0 | J86: =J85 -> 25 | K86: =K85 -> 0 | L86: =L85 -> 0 | M86: ='AP03'!D79 -> 3977.85 | N86: =SUM('AP05'!$F86:$L86) -> 2381.1486 | O86: ='AP05'!$M86-'AP05'!$N86 -> 1596.7014 | P86: =Q85*('AP05'!$R86-1) -> 88.142409 | Q86: =(Q85*'AP05'!$R86)+'AP05'!$F86 -> 244420.34 | R86: 1.000363
A87: =A86+1 -> 73 | B87: =EDATE(B86,1) -> 45464 | C87: =C86 -> 0.0775 | D87: =((1+'AP05'!$C87)^(1/12))-1 -> 0.0062396815 | E87: =E86 -> 2137.58 | F87: =(Q86*'AP05'!$R87)*'AP05'!$D87 -> 1526.5097 | G87: =(Q86*'AP05'!$R87)/($I$5-A86) -> 849.46339 | H87: =H86 -> 0 | I87: =I86 -> 0 | J87: =J86 -> 25 | K87: =K86 -> 0 | L87: =L86 -> 0 | M87: ='AP03'!D80 -> 3898.81 | N87: =SUM('AP05'!$F87:$L87) -> 2400.9731 | O87: ='AP05'!$M87-'AP05'!$N87 -> 1497.8369 | P87: =Q86*('AP05'!$R87-1) -> 225.11114 | Q87: =(Q86*'AP05'!$R87)-'AP05'!$G87-'AP05'!$O87 -> 242298.15 | R87: 1.000921 | T87: 254994.68
A88: =A87+1 -> 74 | B88: =EDATE(B87,1) -> 45494 | C88: =C87 -> 0.0775 | D88: =((1+'AP05'!$C88)^(1/12))-1 -> 0.0062396815 | E88: =E87 -> 2137.58 | F88: =(Q87*'AP05'!$R88)*'AP05'!$D88 -> 1512.8506 | G88: =(Q87*'AP05'!$R88)/($I$5-A87) -> 844.79573 | H88: =H87 -> 0 | I88: =I87 -> 0 | J88: =J87 -> 25 | K88: =K87 -> 0 | L88: =L87 -> 0 | M88: ='AP03'!D81 -> 3822.16 | N88: =SUM('AP05'!$F88:$L88) -> 2382.6463 | O88: ='AP05'!$M88-'AP05'!$N88 -> 1439.5137 | P88: =Q87*('AP05'!$R88-1) -> 158.2207 | Q88: =(Q87*'AP05'!$R88)-'AP05'!$G88-'AP05'!$O88 -> 240172.07 | R88: 1.000653 | T88: =T87-T84 -> 13835.257
A89: =A88+1 -> 75 | B89: =EDATE(B88,1) -> 45525 | C89: =C88 -> 0.0775 | D89: =((1+'AP05'!$C89)^(1/12))-1 -> 0.0062396815 | E89: =E88 -> 2137.58 | F89: =(Q88*'AP05'!$R89)*'AP05'!$D89 -> 1499.6582 | G89: =(Q88*'AP05'!$R89)/($I$5-A88) -> 840.35702 | H89: =H88 -> 0 | I89: =I88 -> 0 | J89: =J88 -> 25 | K89: =K88 -> 0 | L89: =L88 -> 0 | M89: ='AP03'!D82 -> 3745.51 | N89: =SUM('AP05'!$F89:$L89) -> 2365.0152 | O89: ='AP05'!$M89-'AP05'!$N89 -> 1380.4948 | P89: =Q88*('AP05'!$R89-1) -> 170.04182 | Q89: =(Q88*'AP05'!$R89)-'AP05'!$G89-'AP05'!$O89 -> 238121.26 | R89: 1.000708 | T89: =T88-2115.97 -> 11719.287
A90: =A89+1 -> 76 | B90: =EDATE(B89,1) -> 45556 | C90: =C89 -> 0.0775 | D90: =((1+'AP05'!$C90)^(1/12))-1 -> 0.0062396815 | E90: =E89 -> 2137.58 | F90: =(Q89*'AP05'!$R90)*'AP05'!$D90 -> 1486.9077 | G90: =(Q89*'AP05'!$R90)/($I$5-A89) -> 836.13564 | H90: =H89 -> 0 | I90: =I89 -> 0 | J90: =J89 -> 25 | K90: =K89 -> 0 | L90: =L89 -> 0 | M90: ='AP03'!D83 -> 3670.04 | N90: =SUM('AP05'!$F90:$L90) -> 2348.0433 | O90: ='AP05'!$M90-'AP05'!$N90 -> 1321.9967 | P90: =Q89*('AP05'!$R90-1) -> 177.40034 | Q90: =(Q89*'AP05'!$R90)-'AP05'!$G90-'AP05'!$O90 -> 236140.52 | R90: 1.000745 | T90: =51.45+40.27+51.94+40.3+50 -> 233.96
A91: =A90+1 -> 77 | B91: =EDATE(B90,1) -> 45586 | C91: =C90 -> 0.0775 | D91: =((1+'AP05'!$C91)^(1/12))-1 -> 0.0062396815 | E91: =E90 -> 2137.58 | F91: =(Q90*'AP05'!$R91)*'AP05'!$D91 -> 1474.4215 | G91: =(Q90*'AP05'!$R91)/($I$5-A90) -> 832.03365 | H91: =H90 -> 0 | I91: =I90 -> 0 | J91: =J90 -> 25 | K91: =K90 -> 0 | L91: =L90 -> 0 | M91: ='AP03'!D84 -> 3596.87 | N91: =SUM('AP05'!$F91:$L91) -> 2331.4551 | O91: ='AP05'!$M91-'AP05'!$N91 -> 1265.4149 | P91: =Q90*('AP05'!$R91-1) -> 157.03345 | Q91: =(Q90*'AP05'!$R91)-'AP05'!$G91-'AP05'!$O91 -> 234200.11 | R91: 1.000665
A92: =A91+1 -> 78 | B92: =EDATE(B91,1) -> 45617 | C92: =C91 -> 0.0775 | D92: =((1+'AP05'!$C92)^(1/12))-1 -> 0.0062396815 | E92: =E91 -> 2137.58 | F92: =(Q91*'AP05'!$R92)*'AP05'!$D92 -> 1462.3906 | G92: =(Q91*'AP05'!$R92)/($I$5-A91) -> 828.16055 | H92: =H91 -> 0 | I92: =I91 -> 0 | J92: =J91 -> 25 | K92: =K91 -> 0 | L92: =L91 -> 0 | M92: ='AP03'!D85 -> 3523.71 | N92: =SUM('AP05'!$F92:$L92) -> 2315.5512 | O92: ='AP05'!$M92-'AP05'!$N92 -> 1208.1588 | P92: =Q91*('AP05'!$R92-1) -> 169.32668 | Q92: =(Q91*'AP05'!$R92)-'AP05'!$G92-'AP05'!$O92 -> 232333.12 | R92: 1.000723
